Workbook

Sheet Jawa Tengah
A1: start | B1: end | C1: name_enum | D1: name | E1: telp | F1: house_coordinate | G1: house_lat | H1: house_long | I1: house_altitude | J1: house_precision | K1: house_coordinate_am | L1: biogas_coordinate | M1: biogas_lat | N1: biogas_long | O1: biogas_altitude | P1: precision_biogas | Q1: biogas_coordinate_am | R1: province | S1: Informasi Demografis/4a. Provinsi/Lampung | T1: Informasi Demografis/4a. Provinsi/Banten | U1: Informasi Demografis/4a. Provinsi/Jawa Barat | V1: Informasi Demografis/4a. Provinsi/Jawa Tengah | W1: Informasi Demografis/4a. Provinsi/DIY | X1: Informasi Demografis/4a. Provinsi/Jawa Timur | Y1: Informasi Demografis/4a. Provinsi/Bali | Z1: Informasi Demografis/4a. Provinsi/NTB | AA1: Informasi Demografis/4a. Provinsi/NTT | AB1: Informasi Demografis/4a. Provinsi/Sulawesi Selatan | AC1: district | AD1: subdistrict | AE1: village | AF1: name_cpo | AG1: plant_code | AH1: year_of_use | AI1: vpa | AJ1: status_biogas | AK1: age | AL1: gender | AM1: marriage_status | AN1: education | AO1: Informasi Demografis/10. Pekerjaan utama | AP1: Informasi Demografis/10. Pekerjaan utama/Petani | AQ1: Informasi Demografis/10. Pekerjaan utama/Peternak | AR1: Informasi Demografis/10. Pekerjaan utama/Pekerja lepas | AS1: Informasi Demografis/10. Pekerjaan utama/Wiraswasta | AT1: Informasi Demografis/10. Pekerjaan utama/Pegawai pemerintah | AU1: Informasi Demografis/10. Pekerjaan utama/Pegawai swasta | AV1: Informasi Demografis/10. Pekerjaan utama/Lainnya | AW1: Informasi Demografis/10. Pekerjaan utama/Tidak ada | AX1: Informasi Demografis/10a. Lainnya: | AY1: Informasi Demografis/11. Pekerjaan sampingan | AZ1: Informasi Demografis/11. Pekerjaan sampingan/Petani | BA1: Informasi Demografis/11. Pekerjaan sampingan/Peternak | BB1: Informasi Demografis/11. Pekerjaan sampingan/Pekerja lepas | BC1: Informasi Demografis/11. Pekerjaan sampingan/Wiraswasta | BD1: Informasi Demografis/11. Pekerjaan sampingan/Pegawai pemerintah | BE1: Informasi Demografis/11. Pekerjaan sampingan/Pegawai swasta | BF1: Informasi Demografis/11. Pekerjaan sampingan/Lainnya | BG1: Informasi Demografis/11. Pekerjaan sampingan/Tidak ada | BH1: Informasi Demografis/11a. Lainnya: | BI1: monthly_income | BJ1: hh_men | BK1: hh_women | BL1: hh_children | BM1: hh_elders | BN1: house_ownership | BO1: Informasi Demografis/15. Jenis dinding rumah | BP1: Informasi Demografis/15. Jenis dinding rumah/Permanen (dinding bata dan semen) | BQ1: Informasi Demografis/15. Jenis dinding rumah/Semi-permanen (semen dan kayu) | BR1: Informasi Demografis/15. Jenis dinding rumah/Sederhana (tripleks, pelepah kayu, anyaman bambu) | BS1: Informasi Demografis/15. Jenis dinding rumah/Seng | BT1: Informasi Demografis/15. Jenis dinding rumah/Lainnya | BU1: Informasi Demografis/15a. Lainnya: | BV1: Informasi Demografis/16. Jenis lantai rumah | BW1: Informasi Demografis/16. Jenis lantai rumah/Bambu/kayu | BX1: Informasi Demografis/16. Jenis lantai rumah/Semen | BY1: Informasi Demografis/16. Jenis lantai rumah/Keramik/ubin | BZ1: Informasi Demografis/16. Jenis lantai rumah/Tanah | CA1: Informasi Demografis/16. Jenis lantai rumah/Lainnya | CB1: Informasi Demografis/16a. Lainnya: | CC1: Informasi Demografis/17. Jenis atap rumah | CD1: Informasi Demografis/17. Jenis atap rumah/Asbes | CE1: Informasi Demografis/17. Jenis atap rumah/Atap beton | CF1: Informasi Demografis/17. Jenis atap rumah/Daun nipah/palem | CG1: Informasi Demografis/17. Jenis atap rumah/Keramik | CH1: Informasi Demografis/17. Jenis atap rumah/Seng | CI1: Informasi Demografis/17. Jenis atap rumah/Genting | CJ1: Informasi Demografis/17. Jenis atap rumah/Lainnya | CK1: Informasi Demografis/17a. Lainnya: | CL1: A. Performa Teknis Sistem Biogas /A1. Apakah terdapat instalasi biogas di rumah Anda? | CM1: year_completion | CN1: type_digester | CO1: size_digester | CP1: A. Performa Teknis Sistem Biogas /A5. Siapa yang mengajukan pemasangan biogas di rumah? | CQ1: A. Performa Teknis Sistem Biogas /A5. Siapa yang mengajukan pemasangan biogas di rumah?/Anggota keluarga - laki-laki | CR1: A. Performa Teknis Sistem Biogas /A5. Siapa yang mengajukan pemasangan biogas di rumah?/Anggota keluarga - perempuan dewasa | CS1: A. Performa Teknis Sistem Biogas /A5. Siapa yang mengajukan pemasangan biogas di rumah?/Koperasi | CT1: A. Performa Teknis Sistem Biogas /A5. Siapa yang mengajukan pemasangan biogas di rumah?/Lainnya | CU1: A. Performa Teknis Sistem Biogas /A5. Siapa yang mengajukan pemasangan biogas di rumah?/Anggota keluarga - laki-laki | CV1: A. Performa Teknis Sistem Biogas /A5. Siapa yang mengajukan pemasangan biogas di rumah?/Anggota keluarga - perempuan dewasa | CW1: A. Performa Teknis Sistem Biogas /A5. Siapa yang mengajukan pemasangan biogas di rumah?/Koperasi | CX1: A. Performa Teknis Sistem Biogas /A5. Siapa yang mengajukan pemasangan biogas di rumah?/Lainnya | CY1: A. Performa Teknis Sistem Biogas /A6. Siapa yang menyetujui pemasangan biogas? | CZ1: A. Performa Teknis Sistem Biogas /A6. Siapa yang menyetujui pemasangan biogas?/Anggota keluarga - laki-laki | DA1: A. Performa Teknis Sistem Biogas /A6. Siapa yang menyetujui pemasangan biogas?/Anggota keluarga - perempuan dewasa | DB1: A. Performa Teknis Sistem Biogas /A6. Siapa yang menyetujui pemasangan biogas?/Lainnya | DC1: A. Performa Teknis Sistem Biogas /A6-a. Lainnya: | DD1: A. Performa Teknis Sistem Biogas /A7. Siapa yang menentukan titik atau lokasi pemasangan sistem biogas? | DE1: A. Performa Teknis Sistem Biogas /A7. Siapa yang menentukan titik atau lokasi pemasangan sistem biogas?/Anggota keluarga - laki-laki | DF1: A. Performa Teknis Sistem Biogas /A7. Siapa yang menentukan titik atau lokasi pemasangan sistem biogas?/Anggota keluarga - perempuan dewasa | DG1: A. Performa Teknis Sistem Biogas /A7. Siapa yang menentukan titik atau lokasi pemasangan sistem biogas?/CPO atau pendamping | DH1: A. Performa Teknis Sistem Biogas /A7. Siapa yang menentukan titik atau lokasi pemasangan sistem biogas?/Lainnya | DI1: A. Performa Teknis Sistem Biogas /A7-a. Lainnya: | DJ1: A. Performa Teknis Sistem Biogas /A8. Siapa yang mendampingi atau mengawasi pemasangan biogas? | DK1: A. Performa Teknis Sistem Biogas /A8. Siapa yang mendampingi atau mengawasi pemasangan biogas?/Anggota keluarga - laki-laki | DL1: A. Performa Teknis Sistem Biogas /A8. Siapa yang mendampingi atau mengawasi pemasangan biogas?/Anggota keluarga - perempuan dewasa | DM1: A. Performa Teknis Sistem Biogas /A8. Siapa yang mendampingi atau mengawasi pemasangan biogas?/CPO atau pendamping | DN1: A. Performa Teknis Sistem Biogas /A8. Siapa yang mendampingi atau mengawasi pemasangan biogas?/Lainnya | DO1: A. Performa Teknis Sistem Biogas /A8-a. Lainnya: | DP1: A. Performa Teknis Sistem Biogas /A9. Apakah sistem biogas Anda masih berfungsi dengan baik? | DQ1: A. Performa Teknis Sistem Biogas /A10. Sejak kapan digester biogas Anda tidak berfungsi? | DR1: A. Performa Teknis Sistem Biogas /A11. Apa saja penyebab sistem biogas Anda tidak berfungsi atau difungsikan lagi? | DS1: A. Performa Teknis Sistem Biogas /A11-a. Lainnya: | DT1: A. Performa Teknis Sistem Biogas /A12. Apabila menjawab masalah teknis, bagian apa yang mengalami kerusakan? | DU1: A. Performa Teknis Sistem Biogas /A12. Apabila menjawab masalah teknis, bagian apa yang mengalami kerusakan?/Kompor | DV1: A. Performa Teknis Sistem Biogas /A12. Apabila menjawab masalah teknis, bagian apa yang mengalami kerusakan?/Lampu | DW1: A. Performa Teknis Sistem Biogas /A12. Apabila menjawab masalah teknis, bagian apa yang mengalami kerusakan?/Keran gas (Tap) | DX1: A. Performa Teknis Sistem Biogas /A12. Apabila menjawab masalah teknis, bagian apa yang mengalami kerusakan?/Manometer | DY1: A. Performa Teknis Sistem Biogas /A12. Apabila menjawab masalah teknis, bagian apa yang mengalami kerusakan?/Pipa gas utama | DZ1: A. Performa Teknis Sistem Biogas /A12. Apabila menjawab masalah teknis, bagian apa yang mengalami kerusakan?/Katup gas utama | EA1: A. Performa Teknis Sistem Biogas /A12. Apabila menjawab masalah teknis, bagian apa yang mengalami kerusakan?/Turet | EB1: A. Performa Teknis Sistem Biogas /A12. Apabila menjawab masalah teknis, bagian apa yang mengalami kerusakan?/Mixer | EC1: A. Performa Teknis Sistem Biogas /A12. Apabila menjawab masalah teknis, bagian apa yang mengalami kerusakan?/Inlet | ED1: A. Performa Teknis Sistem Biogas /A12. Apabila menjawab masalah teknis, bagian apa yang mengalami kerusakan?/Reaktor biogas (penampung gas, digester, manhole, outlet, dan overflow) | EE1: A. Performa Teknis Sistem Biogas /A12. Apabila menjawab masalah teknis, bagian apa yang mengalami kerusakan?/Saluran Pipa Gas | EF1: A. Performa Teknis Sistem Biogas /A12. Apabila menjawab masalah teknis, bagian apa yang mengalami kerusakan?/Water drain (penguras air/pemisah air) | EG1: A. Performa Teknis Sistem Biogas /A12. Apabila menjawab masalah teknis, bagian apa yang mengalami kerusakan?/Saluran air (Water drain) | EH1: A. Performa Teknis Sistem Biogas /A12. Apabila menjawab masalah teknis, bagian apa yang mengalami kerusakan?/Bio-Slurry Outlet (Lubang Bio-slurry) | EI1: A. Performa Teknis Sistem Biogas /A13. Masalah non-teknis apa yang pernah Anda hadapi sebagai pengguna biogas? | EJ1: A. Performa Teknis Sistem Biogas /A13. Masalah non-teknis apa yang pernah Anda hadapi sebagai pengguna biogas?/Konflik dengan anggota keluarga atau masyarakat terkait penggunaan biogas | EK1: A. Performa Teknis Sistem Biogas /A13. Masalah non-teknis apa yang pernah Anda hadapi sebagai pengguna biogas?/Kurangnya dukungan atau pemantauan dari pemerintah atau CPO | EL1: A. Performa Teknis Sistem Biogas /A13. Masalah non-teknis apa yang pernah Anda hadapi sebagai pengguna biogas?/Keterbatasan akses terhadap informasi atau pelatihan terkait biogas | EM1: A. Performa Teknis Sistem Biogas /A13. Masalah non-teknis apa yang pernah Anda hadapi sebagai pengguna biogas?/Tidak ada masalah | EN1: A. Performa Teknis Sistem Biogas /A13. Masalah non-teknis apa yang pernah Anda hadapi sebagai pengguna biogas?/Lainnya | EO1: A. Performa Teknis Sistem Biogas /A13-a. Lainnya: | EP1: A. Performa Teknis Sistem Biogas /A14. Apakah Anda sebagai pengguna biogas menerima instruksi yang jelas terkait pengoperasian dan perawatan sistem biogas? | EQ1: A. Performa Teknis Sistem Biogas /A15. Dalam bentuk apa Anda menerima instruksi tersebut? | ER1: A. Performa Teknis Sistem Biogas /A16. Siapa yang menyelenggarakan pelatihan atau memberikan instruksi tersebut? | ES1: A. Performa Teknis Sistem Biogas /A16. Siapa yang menyelenggarakan pelatihan atau memberikan instruksi tersebut?/CPO atau pendamping | ET1: A. Performa Teknis Sistem Biogas /A16. Siapa yang menyelenggarakan pelatihan atau memberikan instruksi tersebut?/Staff BIRU | EU1: A. Performa Teknis Sistem Biogas /A16. Siapa yang menyelenggarakan pelatihan atau memberikan instruksi tersebut?/Pegawai koperasi | EV1: A. Performa Teknis Sistem Biogas /A16. Siapa yang menyelenggarakan pelatihan atau memberikan instruksi tersebut?/Lainnya | EW1: A. Performa Teknis Sistem Biogas /A16-a. Lainnya: | EX1: A. Performa Teknis Sistem Biogas /A17. Siapa yang menerima pelatihan atau instruksi tersebut? | EY1: A. Performa Teknis Sistem Biogas /A17. Siapa yang menerima pelatihan atau instruksi tersebut?/Anggota keluarga - Laki-laki | EZ1: A. Performa Teknis Sistem Biogas /A17. Siapa yang menerima pelatihan atau instruksi tersebut?/Anggota keluarga - Perempuan dewasa | FA1: A. Performa Teknis Sistem Biogas /A17. Siapa yang menerima pelatihan atau instruksi tersebut?/Lainnya | FB1: A. Performa Teknis Sistem Biogas /A17-a. Lainnya: | FC1: A. Performa Teknis Sistem Biogas /A18. Seberapa sering Anda melakukan perawatan atau perbaikan pada sistem biogas? | FD1: A. Performa Teknis Sistem Biogas /A19. Berapa biaya pemeliharaan tahunan instalasi biogas Anda? | FE1: A. Performa Teknis Sistem Biogas /A20. Apakah Anda mengetahui cara membaca manometer? Yang jika air berada di angka 0-15, maka Anda tidak dapat menggunakan kompornya? | FF1: A. Performa Teknis Sistem Biogas /A21. Seberapa sering Anda membaca manometer? | FG1: A. Performa Teknis Sistem Biogas /A22. Apakah Anda mengetahui cara membersihkan setiap komponen dari kompor biogas? | FH1: A. Performa Teknis Sistem Biogas /A23. Seberapa sering Anda membersihkan tiap komponen kompor biogas? | FI1: A. Performa Teknis Sistem Biogas /A24. Apakah Anda mengetahui cara menyalakan kompor yang benar, yaitu dengan menyalakan korek terlebih dahulu lalu gas di atas kompor? | FJ1: A. Performa Teknis Sistem Biogas /A25. Seberapa sering Anda menyalakan kompor dengan cara yang benar? | FK1: A. Performa Teknis Sistem Biogas /A26. Apakah Anda mengetahui cara mengecek kebocoran gas dengan benar, yaitu menggunakan sabun dan tanpa api? | FL1: A. Performa Teknis Sistem Biogas /A27. Seberapa sering Anda mengecek kebocoran gas dengan benar? | FM1: A. Performa Teknis Sistem Biogas /A28. Apakah Anda mengetahui cara membersihkan luapan (lubang saluran slurry) dan saluran keluar dari kotoran yang mengeras? | FN1: A. Performa Teknis Sistem Biogas /A29. Seberapa sering Anda membersihkan saluran slurry dan saluran keluar tersebut? | FO1: A. Performa Teknis Sistem Biogas /A30. Apakah Anda mengetahui cara mengeringkan pengering air? | FP1: A. Performa Teknis Sistem Biogas /A31. Seberapa sering Anda mengeringkan pengering air? | FQ1: A. Performa Teknis Sistem Biogas /A32. Apakah Anda mengetahui bahwa outlet beton harus selalu ditutup? | FR1: A. Performa Teknis Sistem Biogas /A32-a. Apakah Anda yakin bahwa outlet tersebut dipastikan akan ditutup kembali setelah pengecekan atau pembersihan? | FS1: A. Performa Teknis Sistem Biogas /A33. Apakah Anda mengetahui bahwa gas tap harus ditutup jika tidak digunakan? | FT1: A. Performa Teknis Sistem Biogas /A34. Apakah Anda menutup kembali gas tap tersebut jika tidak digunakan? | FU1: A. Performa Teknis Sistem Biogas /A35. Siapa yang bertanggung jawab untuk pengoperasian dan perawatan biogas, termasuk pengumpulan kotoran ternak? | FV1: A. Performa Teknis Sistem Biogas /A35. Siapa yang bertanggung jawab untuk pengoperasian dan perawatan biogas, termasuk pengumpulan kotoran ternak? /Laki-laki dewasa | FW1: A. Performa Teknis Sistem Biogas /A35. Siapa yang bertanggung jawab untuk pengoperasian dan perawatan biogas, termasuk pengumpulan kotoran ternak? /Perempuan dewasa | FX1: A. Performa Teknis Sistem Biogas /A35. Siapa yang bertanggung jawab untuk pengoperasian dan perawatan biogas, termasuk pengumpulan kotoran ternak? /Anak-anak | FY1: A. Performa Teknis Sistem Biogas /A35. Siapa yang bertanggung jawab untuk pengoperasian dan perawatan biogas, termasuk pengumpulan kotoran ternak? /Pekerja tambahan | FZ1: A. Performa Teknis Sistem Biogas /A36. Seberapa paham Anda mengenai langkah-langkah keselamatan dalam operasi dan pemeliharaan biogas? | GA1: A. Performa Teknis Sistem Biogas /A37. Jika Anda memahami, dari mana Anda mengetahui langkah-langkah tersebut? | GB1: A. Performa Teknis Sistem Biogas /A37. Jika Anda memahami, dari mana Anda mengetahui langkah-langkah tersebut?/CPO | GC1: A. Performa Teknis Sistem Biogas /A37. Jika Anda memahami, dari mana Anda mengetahui langkah-langkah tersebut?/Pelatihan | GD1: A. Performa Teknis Sistem Biogas /A37. Jika Anda memahami, dari mana Anda mengetahui langkah-langkah tersebut?/Teman/keluarga | GE1: A. Performa Teknis Sistem Biogas /A37. Jika Anda memahami, dari mana Anda mengetahui langkah-langkah tersebut?/Lainnya | GF1: A. Performa Teknis Sistem Biogas /A37-a. Lainnya: | GG1: A. Performa Teknis Sistem Biogas /A38. Seberapa sering Anda menerapkan langkah-langkah keselamatan ini? | GH1: A. Performa Teknis Sistem Biogas /A39. Apakah Anda pernah mempromosikan manfaat biogas kepada orang lain? | GI1: A. Performa Teknis Sistem Biogas /A40. Jika pernah melakukan promosi, kepada siapa saja Anda mempromosikan biogas? | GJ1: A. Performa Teknis Sistem Biogas /A40. Jika pernah melakukan promosi, kepada siapa saja Anda mempromosikan biogas? /Tetangga | GK1: A. Performa Teknis Sistem Biogas /A40. Jika pernah melakukan promosi, kepada siapa saja Anda mempromosikan biogas? /Teman/keluarga | GL1: A. Performa Teknis Sistem Biogas /A40. Jika pernah melakukan promosi, kepada siapa saja Anda mempromosikan biogas? /Komunitas lokal | GM1: A. Performa Teknis Sistem Biogas /A40. Jika pernah melakukan promosi, kepada siapa saja Anda mempromosikan biogas? /Lainnya | GN1: A. Performa Teknis Sistem Biogas /A40-a. Lainnya: | GO1: A. Performa Teknis Sistem Biogas /A41. Apakah Anda akan merekomendasikan penggunaan Biogas? | GP1: B1_biogas_use | GQ1: B2_fuel | GR1: B2-a_LPG | GS1: B2-b_firewood | GT1: B2-c_kerosene | GU1: B2-d_agriculture-waste | GV1: B2-e_animal-manure | GW1: B2-f_charcoal | GX1: B2-g_other | GY1: B. Energi, Pengurangan Emisi, dan Dampak Terhadap Lingkungan /B2-a. Lainnya: | GZ1: B. Energi, Pengurangan Emisi, dan Dampak Terhadap Lingkungan /B3. Apakah masih ingat dengan harga bahan bakar sebelum menggunakan biogas? | HA1: B4-a1_firewood_qty | HB1: B4-a2_firewood_price | HC1: B5-a1_firewood_qty | HD1: B5-a2_firewood_price | HE1: B4-b1_LPG_qty | HF1: B4-b2_LPG_price | HG1: B5-b1_LPG_qty | HH1: B5-b2_LPG_price | HI1: B4-c1_agricultural-waste_qty | HJ1: B4-c2_agricultural-waste_price | HK1: B5-c1_agricultural-waste_qty | HL1: B5-c2_agricultural-waste_price | HM1: B4-d1_animal-manure_qty | HN1: B4-d2_animal-manure_price | HO1: B5-d1_animal-manure_qty | HP1: B5-d2_animal-manure_price | HQ1: B4-e1_charcoal_qty | HR1: B4-e2_charcoal_price | HS1: B5-e1_charcoal_qty | HT1: B5-e2_charcoal_price | HU1: B4-f1_kerosene_qty | HV1: B4-f2_kerosene_price | HW1: B5-f1_kerosene_qty | HX1: B5-f2_kerosene_price | HY1: B6-a1_firewood_reduction_mass | HZ1: B6-a2_firewood_reduction_price | IA1: B6-b1_LPG_reduction_mass | IB1: B6-b2_LPG_reduction_price | IC1: B6-c1_agriculture-waste_reduction_mass | ID1: B6-c2_agriculture-waste_reduction_price | IE1: B6-d1_animal-manure_reduction_mass | IF1: B6-d2_animal-manure_reduction_price | IG1: B6-e1_charcoal_reduction_mass | IH1: B6-e2_charcoal_reduction_price | II1: B6-f1_kerosene_reduction_mass | IJ1: B6-f2_kerosene_reduction_price | IK1: B. Energi, Pengurangan Emisi, dan Dampak Terhadap Lingkungan /B7. Berapa kilogram bahan bakar (kotoran ternak) yang Anda gunakan untuk biogas per hari? | IL1: B. Energi, Pengurangan Emisi, dan Dampak Terhadap Lingkungan /B8. Berapa lama rata-rata kompor biogas Anda menyala setiap hari? | IM1: B. Energi, Pengurangan Emisi, dan Dampak Terhadap Lingkungan /B9. Apakah penggunaan biogas membantu mengurangi penebangan kayu untuk kebutuhan bahan bakar? | IN1: C. Dampak Kesehatan dan Sanitasi /C1. Apakah Anda merenovasi atau membuat dapur baru untuk memasak menggunakan biogas? | IO1: C. Dampak Kesehatan dan Sanitasi /C2. Bagaimana perbandingan kebersihan dapur setelah menggunakan biogas? | IP1: C. Dampak Kesehatan dan Sanitasi /C3. Seberapa sering Anda terpapar asap di dapur setelah menggunakan biogas? | IQ1: C. Dampak Kesehatan dan Sanitasi /C4. Setelah menggunakan biogas, bagaimana perbandingan Anda atau anggota keluarga mengalami masalah pernafasan? | IR1: C. Dampak Kesehatan dan Sanitasi /C5. Siapa yang pernah mengalami infeksi pernapasan SEBELUM menggunakan biogas? | IS1: C. Dampak Kesehatan dan Sanitasi /C5. Siapa yang pernah mengalami infeksi pernapasan SEBELUM menggunakan biogas? /Laki-laki dewasa | IT1: C. Dampak Kesehatan dan Sanitasi /C5. Siapa yang pernah mengalami infeksi pernapasan SEBELUM menggunakan biogas? /Perempuan dewasa | IU1: C. Dampak Kesehatan dan Sanitasi /C5. Siapa yang pernah mengalami infeksi pernapasan SEBELUM menggunakan biogas? /Anak-anak (0-18 tahun) | IV1: C. Dampak Kesehatan dan Sanitasi /C6. Siapa yang pernah mengalami infeksi pernapasan SETELAH menggunakan biogas? | IW1: C. Dampak Kesehatan dan Sanitasi /C6. Siapa yang pernah mengalami infeksi pernapasan SETELAH menggunakan biogas? /Laki-laki dewasa | IX1: C. Dampak Kesehatan dan Sanitasi /C6. Siapa yang pernah mengalami infeksi pernapasan SETELAH menggunakan biogas? /Perempuan dewasa | IY1: C. Dampak Kesehatan dan Sanitasi /C6. Siapa yang pernah mengalami infeksi pernapasan SETELAH menggunakan biogas? /Anak-anak (0-18 tahun) | IZ1: C. Dampak Kesehatan dan Sanitasi /C7. SETELAH menggunakan biogas, bagaimana perbandingan Anda atau anggota keluarga mengalami masalah iritasi mata? | JA1: C. Dampak Kesehatan dan Sanitasi /C8. Siapa yang pernah mengalami masalah iritasi mata SEBELUM menggunakan biogas? | JB1: C. Dampak Kesehatan dan Sanitasi /C8. Siapa yang pernah mengalami masalah iritasi mata SEBELUM menggunakan biogas? /Laki-laki dewasa | JC1: C. Dampak Kesehatan dan Sanitasi /C8. Siapa yang pernah mengalami masalah iritasi mata SEBELUM menggunakan biogas? /Perempuan dewasa | JD1: C. Dampak Kesehatan dan Sanitasi /C8. Siapa yang pernah mengalami masalah iritasi mata SEBELUM menggunakan biogas? /Anak-anak (0-18 tahun) | JE1: C. Dampak Kesehatan dan Sanitasi /C9. Siapa yang pernah mengalami masalah iritasi mata SETELAH menggunakan biogas? | JF1: C. Dampak Kesehatan dan Sanitasi /C9. Siapa yang pernah mengalami masalah iritasi mata SETELAH menggunakan biogas? /Laki-laki dewasa | JG1: C. Dampak Kesehatan dan Sanitasi /C9. Siapa yang pernah mengalami masalah iritasi mata SETELAH menggunakan biogas? /Perempuan dewasa | JH1: C. Dampak Kesehatan dan Sanitasi /C9. Siapa yang pernah mengalami masalah iritasi mata SETELAH menggunakan biogas? /Anak-anak (0-18 tahun) | JI1: C. Dampak Kesehatan dan Sanitasi /C10. SETELAH menggunakan biogas, bagaimana perbandingan Anda atau anggota keluarga mengalami penyakit saluran pencernaan? | JJ1: C. Dampak Kesehatan dan Sanitasi /C11. Siapa yang pernah mengalami penyakit saluran pencernaan SEBELUM menggunakan biogas? | JK1: C. Dampak Kesehatan dan Sanitasi /C11. Siapa yang pernah mengalami penyakit saluran pencernaan SEBELUM menggunakan biogas? /Laki-laki dewasa | JL1: C. Dampak Kesehatan dan Sanitasi /C11. Siapa yang pernah mengalami penyakit saluran pencernaan SEBELUM menggunakan biogas? /Perempuan dewasa | JM1: C. Dampak Kesehatan dan Sanitasi /C11. Siapa yang pernah mengalami penyakit saluran pencernaan SEBELUM menggunakan biogas? /Anak-anak (0-18 tahun) | JN1: C. Dampak Kesehatan dan Sanitasi /C12. Siapa yang pernah mengalami penyakit saluran pencernaan SETELAH menggunakan biogas? | JO1: C. Dampak Kesehatan dan Sanitasi /C12. Siapa yang pernah mengalami penyakit saluran pencernaan SETELAH menggunakan biogas? /Laki-laki dewasa | JP1: C. Dampak Kesehatan dan Sanitasi /C12. Siapa yang pernah mengalami penyakit saluran pencernaan SETELAH menggunakan biogas? /Perempuan dewasa | JQ1: C. Dampak Kesehatan dan Sanitasi /C12. Siapa yang pernah mengalami penyakit saluran pencernaan SETELAH menggunakan biogas? /Anak-anak (0-18 tahun) | JR1: C. Dampak Kesehatan dan Sanitasi /C13. SETELAH menggunakan biogas, bagaimana perbandingan Anda atau anggota keluarga pernah mengalami penyakit yang disebabkan gigitan nyamuk? contoh: malaria, demam berdarah, cikungunya, dan lain sebagainya. | JS1: C. Dampak Kesehatan dan Sanitasi /C14. Siapa yang pernah mengalami penyakit akibat gigitan nyamuk SEBELUM menggunakan biogas? | JT1: C. Dampak Kesehatan dan Sanitasi /C14. Siapa yang pernah mengalami penyakit akibat gigitan nyamuk SEBELUM menggunakan biogas? /Laki-laki dewasa | JU1: C. Dampak Kesehatan dan Sanitasi /C14. Siapa yang pernah mengalami penyakit akibat gigitan nyamuk SEBELUM menggunakan biogas? /Perempuan dewasa | JV1: C. Dampak Kesehatan dan Sanitasi /C14. Siapa yang pernah mengalami penyakit akibat gigitan nyamuk SEBELUM menggunakan biogas? /Anak-anak (0-18 tahun) | JW1: C. Dampak Kesehatan dan Sanitasi /C15. Siapa yang pernah mengalami penyakit akibat gigitan nyamuk SETELAH menggunakan biogas? | JX1: C. Dampak Kesehatan dan Sanitasi /C15. Siapa yang pernah mengalami penyakit akibat gigitan nyamuk SETELAH menggunakan biogas? /Laki-laki dewasa | JY1: C. Dampak Kesehatan dan Sanitasi /C15. Siapa yang pernah mengalami penyakit akibat gigitan nyamuk SETELAH menggunakan biogas? /Perempuan dewasa | JZ1: C. Dampak Kesehatan dan Sanitasi /C15. Siapa yang pernah mengalami penyakit akibat gigitan nyamuk SETELAH menggunakan biogas? /Anak-anak (0-18 tahun) | KA1: C. Dampak Kesehatan dan Sanitasi /C16. SETELAH menggunakan biogas, bagaimana perbandingan terjadinya kecelakaan akibat api (kebakaran) dirumah Anda? | KB1: C. Dampak Kesehatan dan Sanitasi /C17. Siapa yang pernah mengalami kecelakaan akibat api SEBELUM menggunakan biogas? | KC1: C. Dampak Kesehatan dan Sanitasi /C17. Siapa yang pernah mengalami kecelakaan akibat api SEBELUM menggunakan biogas?/Laki-laki dewasa | KD1: C. Dampak Kesehatan dan Sanitasi /C17. Siapa yang pernah mengalami kecelakaan akibat api SEBELUM menggunakan biogas?/Perempuan dewasa | KE1: C. Dampak Kesehatan dan Sanitasi /C17. Siapa yang pernah mengalami kecelakaan akibat api SEBELUM menggunakan biogas?/Anak-anak (0-18 tahun) | KF1: C. Dampak Kesehatan dan Sanitasi /C18. Siapa yang pernah mengalami kecelakaan akibat api SETELAH menggunakan biogas? | KG1: C. Dampak Kesehatan dan Sanitasi /C18. Siapa yang pernah mengalami kecelakaan akibat api SETELAH menggunakan biogas?/Laki-laki dewasa | KH1: C. Dampak Kesehatan dan Sanitasi /C18. Siapa yang pernah mengalami kecelakaan akibat api SETELAH menggunakan biogas?/Perempuan dewasa | KI1: C. Dampak Kesehatan dan Sanitasi /C18. Siapa yang pernah mengalami kecelakaan akibat api SETELAH menggunakan biogas?/Anak-anak (0-18 tahun) | KJ1: C. Dampak Kesehatan dan Sanitasi /C19. SETELAH menggunakan biogas, bagaimana perbandingan dialaminya penyakit psikis lainnya? (misalkan stress, sedikit waktu senggang, dll) | KK1: C. Dampak Kesehatan dan Sanitasi /C20. Siapa yang pernah mengalami penyakit psikisi SEBELUM menggunakan biogas? | KL1: C. Dampak Kesehatan dan Sanitasi /C20. Siapa yang pernah mengalami penyakit psikisi SEBELUM menggunakan biogas?/Laki-laki dewasa | KM1: C. Dampak Kesehatan dan Sanitasi /C20. Siapa yang pernah mengalami penyakit psikisi SEBELUM menggunakan biogas?/Perempuan dewasa | KN1: C. Dampak Kesehatan dan Sanitasi /C20. Siapa yang pernah mengalami penyakit psikisi SEBELUM menggunakan biogas?/Anak-anak (0-18 tahun) | KO1: C. Dampak Kesehatan dan Sanitasi /C21. Siapa yang pernah mengalami penyakit psikisi SETELAH menggunakan biogas? | KP1: C. Dampak Kesehatan dan Sanitasi /C21. Siapa yang pernah mengalami penyakit psikisi SETELAH menggunakan biogas?/Laki-laki dewasa | KQ1: C. Dampak Kesehatan dan Sanitasi /C21. Siapa yang pernah mengalami penyakit psikisi SETELAH menggunakan biogas?/Perempuan dewasa | KR1: C. Dampak Kesehatan dan Sanitasi /C21. Siapa yang pernah mengalami penyakit psikisi SETELAH menggunakan biogas?/Anak-anak (0-18 tahun) | KS1: C. Dampak Kesehatan dan Sanitasi /C22. Bagaimana Anda menilai kondisi kesehatan umum anggota keluarga Anda SETELAH menggunakan biogas? | KT1: C. Dampak Kesehatan dan Sanitasi /C23. SEBELUM menggunakan biogas, dalam satu tahun berapa kali anggota keluarga Anda memeriksakan diri ke dokter/rumah sakit? | KU1: C. Dampak Kesehatan dan Sanitasi /C24. SETELAH menggunakan biogas, dalam satu tahun berapa kali anggota keluarga Anda memeriksakan diri ke doket/rumah sakit? | KV1: C. Dampak Kesehatan dan Sanitasi /C25. Siapa saja yang memeriksakan diri ke dokter/rumah sakit dalam satu tahun terakhir? | KW1: C. Dampak Kesehatan dan Sanitasi /C25. Siapa saja yang memeriksakan diri ke dokter/rumah sakit dalam satu tahun terakhir? /Laki-laki dewasa | KX1: C. Dampak Kesehatan dan Sanitasi /C25. Siapa saja yang memeriksakan diri ke dokter/rumah sakit dalam satu tahun terakhir? /Perempuan dewasa | KY1: C. Dampak Kesehatan dan Sanitasi /C25. Siapa saja yang memeriksakan diri ke dokter/rumah sakit dalam satu tahun terakhir? /Anak-anak (0-18 tahun) | KZ1: C. Dampak Kesehatan dan Sanitasi /C25. Siapa saja yang memeriksakan diri ke dokter/rumah sakit dalam satu tahun terakhir? /Tidak ada | LA1: C. Dampak Kesehatan dan Sanitasi /C26. Apakah pemasangan sistem biogas meningkatkan kondisi kebersihan rumah Anda? | LB1: C. Dampak Kesehatan dan Sanitasi /C27. Apakah pemasangan sistem biogas meningkatkan kondisi kebersihan di kandang ternak Anda? | LC1: D. Dampak Sosial-Ekonomi /D1. Setelah menggunakan biogas, berapa lama waktu yang Anda habiskan untuk kegiatan menghasilkan pendapatan?/a. Bertani | LD1: D. Dampak Sosial-Ekonomi /D1. Setelah menggunakan biogas, berapa lama waktu yang Anda habiskan untuk kegiatan menghasilkan pendapatan?/b. Beternak | LE1: D. Dampak Sosial-Ekonomi /D1. Setelah menggunakan biogas, berapa lama waktu yang Anda habiskan untuk kegiatan menghasilkan pendapatan?/c. Berjualan | LF1: D. Dampak Sosial-Ekonomi /D1. Setelah menggunakan biogas, berapa lama waktu yang Anda habiskan untuk kegiatan menghasilkan pendapatan?/d. Lainnya | LG1: D. Dampak Sosial-Ekonomi /D1-a. Apakah secara umum pendapatan Anda meningkat setelah penggunaan biogas? | LH1: D. Dampak Sosial-Ekonomi /D2. Apabila pendapatan bertambah, berapa peningkatannya? | LI1: D. Dampak Sosial-Ekonomi /D3. Apabila pendapatan menurun, berapa penurunannya? | LJ1: D. Dampak Sosial-Ekonomi /D4. Untuk apa tambahan uang hasil penghematan atau tambahan pendapatan dari penggunaan biogas tersebut Anda gunakan? | LK1: D. Dampak Sosial-Ekonomi /D4. Untuk apa tambahan uang hasil penghematan atau tambahan pendapatan dari penggunaan biogas tersebut Anda gunakan?/Tabungan | LL1: D. Dampak Sosial-Ekonomi /D4. Untuk apa tambahan uang hasil penghematan atau tambahan pendapatan dari penggunaan biogas tersebut Anda gunakan?/Kesehatan | LM1: D. Dampak Sosial-Ekonomi /D4. Untuk apa tambahan uang hasil penghematan atau tambahan pendapatan dari penggunaan biogas tersebut Anda gunakan?/Modal Usaha | LN1: D. Dampak Sosial-Ekonomi /D4. Untuk apa tambahan uang hasil penghematan atau tambahan pendapatan dari penggunaan biogas tersebut Anda gunakan?/Investasi lainnya | LO1: D. Dampak Sosial-Ekonomi /D4. Untuk apa tambahan uang hasil penghematan atau tambahan pendapatan dari penggunaan biogas tersebut Anda gunakan?/Kebutuhan rumah tangga | LP1: D. Dampak Sosial-Ekonomi /D4. Untuk apa tambahan uang hasil penghematan atau tambahan pendapatan dari penggunaan biogas tersebut Anda gunakan?/Pendidikan anggota keluarga | LQ1: D. Dampak Sosial-Ekonomi /D4. Untuk apa tambahan uang hasil penghematan atau tambahan pendapatan dari penggunaan biogas tersebut Anda gunakan?/Lainnya | LR1: D. Dampak Sosial-Ekonomi /D4-a. Lainnya: | LS1: D. Dampak Sosial-Ekonomi /D5. Berapa menit yang dihabiskan untuk mengumpulkan kotoran ternak? (per hari)/Laki-laki dewasa | LT1: D. Dampak Sosial-Ekonomi /D5. Berapa menit yang dihabiskan untuk mengumpulkan kotoran ternak? (per hari)/Perempuan dewasa | LU1: D. Dampak Sosial-Ekonomi /D5. Berapa menit yang dihabiskan untuk mengumpulkan kotoran ternak? (per hari)/Lainnya (anak-anak, pekerja, dsb) | LV1: D. Dampak Sosial-Ekonomi /D6. Berapa menit yang dihabiskan untuk mencampurkan kotoran ternak dan air di dalam inlet? (per hari) /Laki-laki dewasa | LW1: D. Dampak Sosial-Ekonomi /D6. Berapa menit yang dihabiskan untuk mencampurkan kotoran ternak dan air di dalam inlet? (per hari) /Perempuan dewasa | LX1: D. Dampak Sosial-Ekonomi /D6. Berapa menit yang dihabiskan untuk mencampurkan kotoran ternak dan air di dalam inlet? (per hari) /Lainnya (anak-anak, pekerja, dsb) | LY1: D. Dampak Sosial-Ekonomi /D7. Berapa menit yang dihabiskan untuk mengaduk kotoran ternak dan air? (per hari) /Laki-laki dewasa | LZ1: D. Dampak Sosial-Ekonomi /D7. Berapa menit yang dihabiskan untuk mengaduk kotoran ternak dan air? (per hari) /Perempuan dewasa | MA1: D. Dampak Sosial-Ekonomi /D7. Berapa menit yang dihabiskan untuk mengaduk kotoran ternak dan air? (per hari) /Lainnya (anak-anak, pekerja, dsb) | MB1: D. Dampak Sosial-Ekonomi /D8. Secara umum, apakah setelah penggunaan biogas, Anda memiliki waktu luang lebih banyak? | MC1: D. Dampak Sosial-Ekonomi /a. Laki-laki dewasa/D9-a1. Berapa lama waktu yang dibutuhkan Laki-laki dewasa untuk mengumpulkan bahan bakar sebelum menggunakan biogas? | MD1: D. Dampak Sosial-Ekonomi /a. Laki-laki dewasa/D9-a2. Berapa lama waktu yang dibutuhkan Laki-laki dewasa untuk mengumpulkan bahan bakar setelah menggunakan biogas? | ME1: D. Dampak Sosial-Ekonomi /b. Perembuan dewasa/D9-b1. Berapa lama waktu yang dibutuhkan Perempuan dewasa untuk mengumpulkan bahan bakar sebelum menggunakan biogas? | MF1: D. Dampak Sosial-Ekonomi /b. Perembuan dewasa/D9-b2. Berapa lama waktu yang dibutuhkan Perempuan dewasa untuk mengumpulkan bahan bakar setelah menggunakan biogas? | MG1: D. Dampak Sosial-Ekonomi /c. Lainnya (anak-anak, pekerja, dll)/D9-c1. Berapa lama waktu yang dibutuhkan anggota lainnya untuk mengumpulkan bahan bakar sebelum menggunakan biogas? | MH1: D. Dampak Sosial-Ekonomi /c. Lainnya (anak-anak, pekerja, dll)/D9-c2. Berapa lama waktu yang dibutuhkan anggota lainnya untuk mengumpulkan bahan bakar setelah menggunakan biogas? | MI1: D. Dampak Sosial-Ekonomi /D10. Bagaimana keluarga Anda menggunakan waktu yang dihemat dari penggunaan biogas? | MJ1: D. Dampak Sosial-Ekonomi /D10. Bagaimana keluarga Anda menggunakan waktu yang dihemat dari penggunaan biogas?/ Pendidikan anak (mengantar sekolah, menemani anak belajar, menyiapkan bekal dsb) | MK1: D. Dampak Sosial-Ekonomi /D10. Bagaimana keluarga Anda menggunakan waktu yang dihemat dari penggunaan biogas?/Aktivitas sosial diluar rumah (misalnya, berkumpul dengan tetangga, mengikuti kegiatan PKK, dsb) | ML1: D. Dampak Sosial-Ekonomi /D10. Bagaimana keluarga Anda menggunakan waktu yang dihemat dari penggunaan biogas?/Istirahat | MM1: D. Dampak Sosial-Ekonomi /D10. Bagaimana keluarga Anda menggunakan waktu yang dihemat dari penggunaan biogas?/Pendidikan diri sendiri | MN1: D. Dampak Sosial-Ekonomi /D10. Bagaimana keluarga Anda menggunakan waktu yang dihemat dari penggunaan biogas?/Bekerja | MO1: D. Dampak Sosial-Ekonomi /D10. Bagaimana keluarga Anda menggunakan waktu yang dihemat dari penggunaan biogas?/Lainnya | MP1: D. Dampak Sosial-Ekonomi /D10-a. Lainnya: | MQ1: D. Dampak Sosial-Ekonomi /D11-a. Jika keluarga Anda menggunakan waktu yang dihemat untuk bekerja, apa jenis pekerjaan yang dilakukan? | MR1: D. Dampak Sosial-Ekonomi /D11-b. Jika keluarga Anda tidak menggunakan waktu yang dihemat untuk bekerja, mengapa? | MS1: D. Dampak Sosial-Ekonomi /D12-a. Jika keluarga Anda menggunakan waktu yang dihemat untuk aktivitas sosial, apa jenis kegiatan sosial yang keluarga Anda ikuti? | MT1: D. Dampak Sosial-Ekonomi /D12-b. Jika keluarga Anda tidak menggunakan waktu yang dihemat untuk aktivitas sosial melakukan aktivitas sosial, mengapa? | MU1: D. Dampak Sosial-Ekonomi /D13. Apakah pemasangan sistem biogas menciptakan peluang kerja bagi Anda atau anggota keluarga? | MV1: D. Dampak Sosial-Ekonomi /D13-a. Jika pemasangan sistem biogas menciptakan peluang kerja untuk anggota keluarga atau orang lain, dalam bentuk apa? | MW1: D. Dampak Sosial-Ekonomi /D13-a. Jika pemasangan sistem biogas menciptakan peluang kerja untuk anggota keluarga atau orang lain, dalam bentuk apa? /Perawatan sistem biogas | MX1: D. Dampak Sosial-Ekonomi /D13-a. Jika pemasangan sistem biogas menciptakan peluang kerja untuk anggota keluarga atau orang lain, dalam bentuk apa? /Pemasangan sistem biogas | MY1: D. Dampak Sosial-Ekonomi /D13-a. Jika pemasangan sistem biogas menciptakan peluang kerja untuk anggota keluarga atau orang lain, dalam bentuk apa? /Produksi dan penjualan bioslurry | MZ1: D. Dampak Sosial-Ekonomi /D13-a. Jika pemasangan sistem biogas menciptakan peluang kerja untuk anggota keluarga atau orang lain, dalam bentuk apa? /Lainnya | NA1: D. Dampak Sosial-Ekonomi /D13-a-a. Lainnya: | NB1: D. Dampak Sosial-Ekonomi /D13-b. Berapa banyak tenaga kerja yang Anda pekerjakan untuk pengelolaan sistem biogas? | NC1: D. Dampak Sosial-Ekonomi /D14. Apa bentuk bioslurry yang Anda jual? | ND1: D. Dampak Sosial-Ekonomi /D14. Apa bentuk bioslurry yang Anda jual?/Cair | NE1: D. Dampak Sosial-Ekonomi /D14. Apa bentuk bioslurry yang Anda jual?/Padat | NF1: D. Dampak Sosial-Ekonomi /D15. Berapa bioslurry yang terjual per bulan?/Liter (cair) | NG1: D. Dampak Sosial-Ekonomi /D15. Berapa bioslurry yang terjual per bulan?/Kilogram (padat) | NH1: D. Dampak Sosial-Ekonomi /D15. Berapa bioslurry yang terjual per bulan?/Tuliskan jumlah dalam satuan lain | NI1: D. Dampak Sosial-Ekonomi /D16. Berapa harga jual bioslurry?/Rp/liter (cair) | NJ1: D. Dampak Sosial-Ekonomi /D16. Berapa harga jual bioslurry?/Rp/kg (padat) | NK1: D. Dampak Sosial-Ekonomi /D16. Berapa harga jual bioslurry?/Tuliskan jumlah dalam satuan lain | NL1: D. Dampak Sosial-Ekonomi /D17. Apakah ada IDBP hotline sticker? | NM1: D. Dampak Sosial-Ekonomi /D18. Darimana sumber pembiayaan untuk memasang sistem biogas? | NN1: D. Dampak Sosial-Ekonomi /D19. Berapa total biaya yang Anda keluarkan untuk memasang sistem biogas (termasuk instalasi, peralatan, dan biaya operasional awal)? | NO1: D. Dampak Sosial-Ekonomi /D20. Jika terdapat dana hibah untuk sumber pembiayaan, siapa pemberi dana tersebut? | NP1: D. Dampak Sosial-Ekonomi /D20-a. Lainnya: | NQ1: D. Dampak Sosial-Ekonomi /D21. Jika terdapat kredit atau pinjaman untuk sumber pembiayaan, siapa pemberi pinjaman tersebut? | NR1: D. Dampak Sosial-Ekonomi /D21-a. Lainnya | NS1: D. Dampak Sosial-Ekonomi /D22. Jika pinjaman atau kredit, berapa jangka waktu pinjaman? | NT1: D. Dampak Sosial-Ekonomi /D23. Jika pinjaman atau kredit, siapa yang menghubungi pemberi pinjaman? | NU1: D. Dampak Sosial-Ekonomi /D23-a. Lainnya: | NV1: D. Dampak Sosial-Ekonomi /D24. Jika ada kontribusi pembiayaan sendiri, siapa yang memutuskan untuk membiayai secara cash pemasangan biogas tersebut? | NW1: D. Dampak Sosial-Ekonomi /D24-a. Lainnya: | NX1: D. Dampak Sosial-Ekonomi /D25. Apakah Anda merasa bahwa investasi pada sistem biogas telah meningkatkan kesejahteraan ekonomi keluarga anda? | NY1: D. Dampak Sosial-Ekonomi /D26. Setelah penggunaan biogas, berapa lama waktu yang dialokasikan untuk memasak? (menit/hari)/Perempuan dewasa | NZ1: D. Dampak Sosial-Ekonomi /D26. Setelah penggunaan biogas, berapa lama waktu yang dialokasikan untuk memasak? (menit/hari)/Laki-laki dewasa | OA1: D. Dampak Sosial-Ekonomi /D26. Setelah penggunaan biogas, berapa lama waktu yang dialokasikan untuk memasak? (menit/hari)/Anak-anak | OB1: D. Dampak Sosial-Ekonomi /D27. Setelah penggunaan biogas, berapa lama waktu yang dialokasikan untuk mengoperasikan dan merawat biogas? (menit/hari)/Perempuan dewasa | OC1: D. Dampak Sosial-Ekonomi /D27. Setelah penggunaan biogas, berapa lama waktu yang dialokasikan untuk mengoperasikan dan merawat biogas? (menit/hari)/Laki-laki dewasa | OD1: D. Dampak Sosial-Ekonomi /D27. Setelah penggunaan biogas, berapa lama waktu yang dialokasikan untuk mengoperasikan dan merawat biogas? (menit/hari)/Anak-anak | OE1: D. Dampak Sosial-Ekonomi /D28. Bagaimana Anda melihat kondisi sosial dan ekonomi keluarga Anda setelah menggunakan biogas? | OF1: D. Dampak Sosial-Ekonomi /D29. Bagaimana perubahan proses dan beban kerja untuk memasak jika menggunakan biogas dibandingkan bahan bakar konvensional (sebelum menggunakan biogas)? | OG1: E. Dampak Terhadap Agrikultur /E1. Apakah ternak yang Anda rawat merupakan milik Anda pribadi? | OH1: E. Dampak Terhadap Agrikultur /E2. Berapa banyak hewan ternak yang dimiliki sekarang?/a. Sapi pedaging | OI1: E. Dampak Terhadap Agrikultur /E2. Berapa banyak hewan ternak yang dimiliki sekarang?/b. Sapi perah | OJ1: E. Dampak Terhadap Agrikultur /E2. Berapa banyak hewan ternak yang dimiliki sekarang?/c. Sapi untuk kegunaan lainnya (misal kerbau) | OK1: E. Dampak Terhadap Agrikultur /E2. Berapa banyak hewan ternak yang dimiliki sekarang?/d. Babi ternak | OL1: E. Dampak Terhadap Agrikultur /E2. Berapa banyak hewan ternak yang dimiliki sekarang?/e. Kuda | OM1: E. Dampak Terhadap Agrikultur /E2. Berapa banyak hewan ternak yang dimiliki sekarang?/f. Kambing | ON1: E. Dampak Terhadap Agrikultur /E2. Berapa banyak hewan ternak yang dimiliki sekarang?/g. Ayam | OO1: E. Dampak Terhadap Agrikultur /E2. Berapa banyak hewan ternak yang dimiliki sekarang?/h. Unggas Lainnya | OP1: E3-a. Hewan ternak apa saja yang Anda miliki sebelum menggunakan biogas? | OQ1: E3-a. Hewan ternak apa saja yang Anda miliki sebelum menggunakan biogas?/Sapi pedaging | OR1: E3-a. Hewan ternak apa saja yang Anda miliki sebelum menggunakan biogas?/Sapi perah | OS1: E3-a. Hewan ternak apa saja yang Anda miliki sebelum menggunakan biogas?/Sapi untuk penggunaan lain | OT1: E3-a. Hewan ternak apa saja yang Anda miliki sebelum menggunakan biogas?/Babi ternak | OU1: E3-a. Hewan ternak apa saja yang Anda miliki sebelum menggunakan biogas?/Kuda | OV1: E3-a. Hewan ternak apa saja yang Anda miliki sebelum menggunakan biogas?/Kambing | OW1: E3-a. Hewan ternak apa saja yang Anda miliki sebelum menggunakan biogas?/Ayam | OX1: E3-a. Hewan ternak apa saja yang Anda miliki sebelum menggunakan biogas?/Unggas lainnya | OY1: E3-a. Hewan ternak apa saja yang Anda miliki sebelum menggunakan biogas?/Tidak ada | OZ1: E3-b. Hewan ternak apa saja yang Anda miliki saat ini (setelah menggunakan biogas)? | PA1: E3-b. Hewan ternak apa saja yang Anda miliki saat ini (setelah menggunakan biogas)?/Sapi pedaging | PB1: E3-b. Hewan ternak apa saja yang Anda miliki saat ini (setelah menggunakan biogas)?/Sapi perah | PC1: E3-b. Hewan ternak apa saja yang Anda miliki saat ini (setelah menggunakan biogas)?/Sapi untuk penggunaan lain | PD1: E3-b. Hewan ternak apa saja yang Anda miliki saat ini (setelah menggunakan biogas)?/Babi ternak | PE1: E3-b. Hewan ternak apa saja yang Anda miliki saat ini (setelah menggunakan biogas)?/Kuda | PF1: E3-b. Hewan ternak apa saja yang Anda miliki saat ini (setelah menggunakan biogas)?/Kambing | PG1: E3-b. Hewan ternak apa saja yang Anda miliki saat ini (setelah menggunakan biogas)?/Ayam | PH1: E3-b. Hewan ternak apa saja yang Anda miliki saat ini (setelah menggunakan biogas)?/Unggas lainnya | PI1: E3-b. Hewan ternak apa saja yang Anda miliki saat ini (setelah menggunakan biogas)?/Tidak ada | PJ1: E3-c. Selama 12 bulan terakhir, hewan apa saja yang dijual, mati, lahir, dan dibeli? | PK1: E3-c. Selama 12 bulan terakhir, hewan apa saja yang dijual, mati, lahir, dan dibeli?/Sapi pedaging | PL1: E3-c. Selama 12 bulan terakhir, hewan apa saja yang dijual, mati, lahir, dan dibeli?/Sapi perah | PM1: E3-c. Selama 12 bulan terakhir, hewan apa saja yang dijual, mati, lahir, dan dibeli?/Sapi untuk penggunaan lain | PN1: E3-c. Selama 12 bulan terakhir, hewan apa saja yang dijual, mati, lahir, dan dibeli?/Babi ternak | PO1: E3-c. Selama 12 bulan terakhir, hewan apa saja yang dijual, mati, lahir, dan dibeli?/Kuda | PP1: E3-c. Selama 12 bulan terakhir, hewan apa saja yang dijual, mati, lahir, dan dibeli?/Kambing | PQ1: E3-c. Selama 12 bulan terakhir, hewan apa saja yang dijual, mati, lahir, dan dibeli?/Ayam | PR1: E3-c. Selama 12 bulan terakhir, hewan apa saja yang dijual, mati, lahir, dan dibeli?/Unggas lainnya | PS1: E3-c. Selama 12 bulan terakhir, hewan apa saja yang dijual, mati, lahir, dan dibeli?/Tidak ada | PT1: E. Dampak Terhadap Agrikultur /E4. Sebelum menggunakan biogas, apa yang Anda lakukan untuk kotoran ternak? (Pertanyaan disesuaikan dengan jawaban E3)/a. Sapi pedaging | PU1: E. Dampak Terhadap Agrikultur /E4. Sebelum menggunakan biogas, apa yang Anda lakukan untuk kotoran ternak? (Pertanyaan disesuaikan dengan jawaban E3)/a. Sapi pedaging/a. Sangat teratur (setiap hari) | PV1: E. Dampak Terhadap Agrikultur /E4. Sebelum menggunakan biogas, apa yang Anda lakukan untuk kotoran ternak? (Pertanyaan disesuaikan dengan jawaban E3)/a. Sapi pedaging/b. Teratur (2-6 hari sekali) | PW1: E. Dampak Terhadap Agrikultur /E4. Sebelum menggunakan biogas, apa yang Anda lakukan untuk kotoran ternak? (Pertanyaan disesuaikan dengan jawaban E3)/a. Sapi pedaging/c. Cukup teratur (setiap minggu) | PX1: E. Dampak Terhadap Agrikultur /E4. Sebelum menggunakan biogas, apa yang Anda lakukan untuk kotoran ternak? (Pertanyaan disesuaikan dengan jawaban E3)/a. Sapi pedaging/d. Jarang (2-3 minggu sekali) | PY1: E. Dampak Terhadap Agrikultur /E4. Sebelum menggunakan biogas, apa yang Anda lakukan untuk kotoran ternak? (Pertanyaan disesuaikan dengan jawaban E3)/a. Sapi pedaging/e. Sangat jarang (>1 bulan sekali) | PZ1: E. Dampak Terhadap Agrikultur /E4. Sebelum menggunakan biogas, apa yang Anda lakukan untuk kotoran ternak? (Pertanyaan disesuaikan dengan jawaban E3)/a. Sapi pedaging/1-Disebarkan ke lahan terbuka | QA1: E. Dampak Terhadap Agrikultur /E4. Sebelum menggunakan biogas, apa yang Anda lakukan untuk kotoran ternak? (Pertanyaan disesuaikan dengan jawaban E3)/a. Sapi pedaging/2-Dibuang ke sungai | QB1: E. Dampak Terhadap Agrikultur /E4. Sebelum menggunakan biogas, apa yang Anda lakukan untuk kotoran ternak? (Pertanyaan disesuaikan dengan jawaban E3)/a. Sapi pedaging/3-Dijual | QC1: E. Dampak Terhadap Agrikultur /E4. Sebelum menggunakan biogas, apa yang Anda lakukan untuk kotoran ternak? (Pertanyaan disesuaikan dengan jawaban E3)/a. Sapi pedaging/4-Lainnya | QD1: E. Dampak Terhadap Agrikultur /E4. Sebelum menggunakan biogas, apa yang Anda lakukan untuk kotoran ternak? (Pertanyaan disesuaikan dengan jawaban E3)/E4a-a. Lainnya: | QE1: E. Dampak Terhadap Agrikultur /E4. Sebelum menggunakan biogas, apa yang Anda lakukan untuk kotoran ternak? (Pertanyaan disesuaikan dengan jawaban E3)/b. Sapi perah | QF1: E. Dampak Terhadap Agrikultur /E4. Sebelum menggunakan biogas, apa yang Anda lakukan untuk kotoran ternak? (Pertanyaan disesuaikan dengan jawaban E3)/b. Sapi perah/a. Sangat teratur (setiap hari) | QG1: E. Dampak Terhadap Agrikultur /E4. Sebelum menggunakan biogas, apa yang Anda lakukan untuk kotoran ternak? (Pertanyaan disesuaikan dengan jawaban E3)/b. Sapi perah/b. Teratur (2-6 hari sekali) | QH1: E. Dampak Terhadap Agrikultur /E4. Sebelum menggunakan biogas, apa yang Anda lakukan untuk kotoran ternak? (Pertanyaan disesuaikan dengan jawaban E3)/b. Sapi perah/c. Cukup teratur (setiap minggu) | QI1: E. Dampak Terhadap Agrikultur /E4. Sebelum menggunakan biogas, apa yang Anda lakukan untuk kotoran ternak? (Pertanyaan disesuaikan dengan jawaban E3)/b. Sapi perah/d. Jarang (2-3 minggu sekali) | QJ1: E. Dampak Terhadap Agrikultur /E4. Sebelum menggunakan biogas, apa yang Anda lakukan untuk kotoran ternak? (Pertanyaan disesuaikan dengan jawaban E3)/b. Sapi perah/e. Sangat jarang (>1 bulan sekali) | QK1: E. Dampak Terhadap Agrikultur /E4. Sebelum menggunakan biogas, apa yang Anda lakukan untuk kotoran ternak? (Pertanyaan disesuaikan dengan jawaban E3)/b. Sapi perah/1-Disebarkan ke lahan terbuka | QL1: E. Dampak Terhadap Agrikultur /E4. Sebelum menggunakan biogas, apa yang Anda lakukan untuk kotoran ternak? (Pertanyaan disesuaikan dengan jawaban E3)/b. Sapi perah/2-Dibuang ke sungai | QM1: E. Dampak Terhadap Agrikultur /E4. Sebelum menggunakan biogas, apa yang Anda lakukan untuk kotoran ternak? (Pertanyaan disesuaikan dengan jawaban E3)/b. Sapi perah/3-Dijual | QN1: E. Dampak Terhadap Agrikultur /E4. Sebelum menggunakan biogas, apa yang Anda lakukan untuk kotoran ternak? (Pertanyaan disesuaikan dengan jawaban E3)/b. Sapi perah/4-Lainnya | QO1: E. Dampak Terhadap Agrikultur /E4. Sebelum menggunakan biogas, apa yang Anda lakukan untuk kotoran ternak? (Pertanyaan disesuaikan dengan jawaban E3)/E4b-a. Lainnya: | QP1: E. Dampak Terhadap Agrikultur /E4. Sebelum menggunakan biogas, apa yang Anda lakukan untuk kotoran ternak? (Pertanyaan disesuaikan dengan jawaban E3)/c. Sapi untuk penggunaan lain | QQ1: E. Dampak Terhadap Agrikultur /E4. Sebelum menggunakan biogas, apa yang Anda lakukan untuk kotoran ternak? (Pertanyaan disesuaikan dengan jawaban E3)/c. Sapi untuk penggunaan lain/1-Disebarkan ke lahan terbuka | QR1: E. Dampak Terhadap Agrikultur /E4. Sebelum menggunakan biogas, apa yang Anda lakukan untuk kotoran ternak? (Pertanyaan disesuaikan dengan jawaban E3)/c. Sapi untuk penggunaan lain/2-Dibuang ke sungai | QS1: E. Dampak Terhadap Agrikultur /E4. Sebelum menggunakan biogas, apa yang Anda lakukan untuk kotoran ternak? (Pertanyaan disesuaikan dengan jawaban E3)/c. Sapi untuk penggunaan lain/3-Dijual | QT1: E. Dampak Terhadap Agrikultur /E4. Sebelum menggunakan biogas, apa yang Anda lakukan untuk kotoran ternak? (Pertanyaan disesuaikan dengan jawaban E3)/c. Sapi untuk penggunaan lain/4-Lainnya | QU1: E. Dampak Terhadap Agrikultur /E4. Sebelum menggunakan biogas, apa yang Anda lakukan untuk kotoran ternak? (Pertanyaan disesuaikan dengan jawaban E3)/E4c-a. Lainnya: | QV1: E. Dampak Terhadap Agrikultur /E4. Sebelum menggunakan biogas, apa yang Anda lakukan untuk kotoran ternak? (Pertanyaan disesuaikan dengan jawaban E3)/d. Babi ternak | QW1: E. Dampak Terhadap Agrikultur /E4. Sebelum menggunakan biogas, apa yang Anda lakukan untuk kotoran ternak? (Pertanyaan disesuaikan dengan jawaban E3)/d. Babi ternak/a. Sangat teratur (setiap hari) | QX1: E. Dampak Terhadap Agrikultur /E4. Sebelum menggunakan biogas, apa yang Anda lakukan untuk kotoran ternak? (Pertanyaan disesuaikan dengan jawaban E3)/d. Babi ternak/b. Teratur (2-6 hari sekali) | QY1: E. Dampak Terhadap Agrikultur /E4. Sebelum menggunakan biogas, apa yang Anda lakukan untuk kotoran ternak? (Pertanyaan disesuaikan dengan jawaban E3)/d. Babi ternak/c. Cukup teratur (setiap minggu) | QZ1: E. Dampak Terhadap Agrikultur /E4. Sebelum menggunakan biogas, apa yang Anda lakukan untuk kotoran ternak? (Pertanyaan disesuaikan dengan jawaban E3)/d. Babi ternak/d. Jarang (2-3 minggu sekali) | RA1: E. Dampak Terhadap Agrikultur /E4. Sebelum menggunakan biogas, apa yang Anda lakukan untuk kotoran ternak? (Pertanyaan disesuaikan dengan jawaban E3)/d. Babi ternak/e. Sangat jarang (>1 bulan sekali) | RB1: E. Dampak Terhadap Agrikultur /E4. Sebelum menggunakan biogas, apa yang Anda lakukan untuk kotoran ternak? (Pertanyaan disesuaikan dengan jawaban E3)/d. Babi ternak/1-Disebarkan ke lahan terbuka | RC1: E. Dampak Terhadap Agrikultur /E4. Sebelum menggunakan biogas, apa yang Anda lakukan untuk kotoran ternak? (Pertanyaan disesuaikan dengan jawaban E3)/d. Babi ternak/2-Dibuang ke sungai | RD1: E. Dampak Terhadap Agrikultur /E4. Sebelum menggunakan biogas, apa yang Anda lakukan untuk kotoran ternak? (Pertanyaan disesuaikan dengan jawaban E3)/d. Babi ternak/3-Dijual | RE1: E. Dampak Terhadap Agrikultur /E4. Sebelum menggunakan biogas, apa yang Anda lakukan untuk kotoran ternak? (Pertanyaan disesuaikan dengan jawaban E3)/d. Babi ternak/4-Lainnya | RF1: E. Dampak Terhadap Agrikultur /E4. Sebelum menggunakan biogas, apa yang Anda lakukan untuk kotoran ternak? (Pertanyaan disesuaikan dengan jawaban E3)/E4d-a. Lainnya: | RG1: E. Dampak Terhadap Agrikultur /E4. Sebelum menggunakan biogas, apa yang Anda lakukan untuk kotoran ternak? (Pertanyaan disesuaikan dengan jawaban E3)/e. Kuda | RH1: E. Dampak Terhadap Agrikultur /E4. Sebelum menggunakan biogas, apa yang Anda lakukan untuk kotoran ternak? (Pertanyaan disesuaikan dengan jawaban E3)/e. Kuda/a. Sangat teratur (setiap hari) | RI1: E. Dampak Terhadap Agrikultur /E4. Sebelum menggunakan biogas, apa yang Anda lakukan untuk kotoran ternak? (Pertanyaan disesuaikan dengan jawaban E3)/e. Kuda/b. Teratur (2-6 hari sekali) | RJ1: E. Dampak Terhadap Agrikultur /E4. Sebelum menggunakan biogas, apa yang Anda lakukan untuk kotoran ternak? (Pertanyaan disesuaikan dengan jawaban E3)/e. Kuda/c. Cukup teratur (setiap minggu) | RK1: E. Dampak Terhadap Agrikultur /E4. Sebelum menggunakan biogas, apa yang Anda lakukan untuk kotoran ternak? (Pertanyaan disesuaikan dengan jawaban E3)/e. Kuda/d. Jarang (2-3 minggu sekali) | RL1: E. Dampak Terhadap Agrikultur /E4. Sebelum menggunakan biogas, apa yang Anda lakukan untuk kotoran ternak? (Pertanyaan disesuaikan dengan jawaban E3)/e. Kuda/e. Sangat jarang (>1 bulan sekali) | RM1: E. Dampak Terhadap Agrikultur /E4. Sebelum menggunakan biogas, apa yang Anda lakukan untuk kotoran ternak? (Pertanyaan disesuaikan dengan jawaban E3)/e. Kuda/1-Disebarkan ke lahan terbuka | RN1: E. Dampak Terhadap Agrikultur /E4. Sebelum menggunakan biogas, apa yang Anda lakukan untuk kotoran ternak? (Pertanyaan disesuaikan dengan jawaban E3)/e. Kuda/2-Dibuang ke sungai | RO1: E. Dampak Terhadap Agrikultur /E4. Sebelum menggunakan biogas, apa yang Anda lakukan untuk kotoran ternak? (Pertanyaan disesuaikan dengan jawaban E3)/e. Kuda/3-Dijual | RP1: E. Dampak Terhadap Agrikultur /E4. Sebelum menggunakan biogas, apa yang Anda lakukan untuk kotoran ternak? (Pertanyaan disesuaikan dengan jawaban E3)/e. Kuda/4-Lainnya | RQ1: E. Dampak Terhadap Agrikultur /E4. Sebelum menggunakan biogas, apa yang Anda lakukan untuk kotoran ternak? (Pertanyaan disesuaikan dengan jawaban E3)/E4e-a. Lainnya: | RR1: E. Dampak Terhadap Agrikultur /E4. Sebelum menggunakan biogas, apa yang Anda lakukan untuk kotoran ternak? (Pertanyaan disesuaikan dengan jawaban E3)/f. Kambing | RS1: E. Dampak Terhadap Agrikultur /E4. Sebelum menggunakan biogas, apa yang Anda lakukan untuk kotoran ternak? (Pertanyaan disesuaikan dengan jawaban E3)/f. Kambing/a. Sangat teratur (setiap hari) | RT1: E. Dampak Terhadap Agrikultur /E4. Sebelum menggunakan biogas, apa yang Anda lakukan untuk kotoran ternak? (Pertanyaan disesuaikan dengan jawaban E3)/f. Kambing/b. Teratur (2-6 hari sekali) | RU1: E. Dampak Terhadap Agrikultur /E4. Sebelum menggunakan biogas, apa yang Anda lakukan untuk kotoran ternak? (Pertanyaan disesuaikan dengan jawaban E3)/f. Kambing/c. Cukup teratur (setiap minggu) | RV1: E. Dampak Terhadap Agrikultur /E4. Sebelum menggunakan biogas, apa yang Anda lakukan untuk kotoran ternak? (Pertanyaan disesuaikan dengan jawaban E3)/f. Kambing/d. Jarang (2-3 minggu sekali) | RW1: E. Dampak Terhadap Agrikultur /E4. Sebelum menggunakan biogas, apa yang Anda lakukan untuk kotoran ternak? (Pertanyaan disesuaikan dengan jawaban E3)/f. Kambing/e. Sangat jarang (>1 bulan sekali) | RX1: E. Dampak Terhadap Agrikultur /E4. Sebelum menggunakan biogas, apa yang Anda lakukan untuk kotoran ternak? (Pertanyaan disesuaikan dengan jawaban E3)/f. Kambing/1-Disebarkan ke lahan terbuka | RY1: E. Dampak Terhadap Agrikultur /E4. Sebelum menggunakan biogas, apa yang Anda lakukan untuk kotoran ternak? (Pertanyaan disesuaikan dengan jawaban E3)/f. Kambing/2-Dibuang ke sungai | RZ1: E. Dampak Terhadap Agrikultur /E4. Sebelum menggunakan biogas, apa yang Anda lakukan untuk kotoran ternak? (Pertanyaan disesuaikan dengan jawaban E3)/f. Kambing/3-Dijual | SA1: E. Dampak Terhadap Agrikultur /E4. Sebelum menggunakan biogas, apa yang Anda lakukan untuk kotoran ternak? (Pertanyaan disesuaikan dengan jawaban E3)/f. Kambing/4-Lainnya | SB1: E. Dampak Terhadap Agrikultur /E4. Sebelum menggunakan biogas, apa yang Anda lakukan untuk kotoran ternak? (Pertanyaan disesuaikan dengan jawaban E3)/E4f-a. Lainnya: | SC1: E. Dampak Terhadap Agrikultur /E4. Sebelum menggunakan biogas, apa yang Anda lakukan untuk kotoran ternak? (Pertanyaan disesuaikan dengan jawaban E3)/g. Ayam | SD1: E. Dampak Terhadap Agrikultur /E4. Sebelum menggunakan biogas, apa yang Anda lakukan untuk kotoran ternak? (Pertanyaan disesuaikan dengan jawaban E3)/g. Ayam/a. Sangat teratur (setiap hari) | SE1: E. Dampak Terhadap Agrikultur /E4. Sebelum menggunakan biogas, apa yang Anda lakukan untuk kotoran ternak? (Pertanyaan disesuaikan dengan jawaban E3)/g. Ayam/b. Teratur (2-6 hari sekali) | SF1: E. Dampak Terhadap Agrikultur /E4. Sebelum menggunakan biogas, apa yang Anda lakukan untuk kotoran ternak? (Pertanyaan disesuaikan dengan jawaban E3)/g. Ayam/c. Cukup teratur (setiap minggu) | SG1: E. Dampak Terhadap Agrikultur /E4. Sebelum menggunakan biogas, apa yang Anda lakukan untuk kotoran ternak? (Pertanyaan disesuaikan dengan jawaban E3)/g. Ayam/d. Jarang (2-3 minggu sekali) | SH1: E. Dampak Terhadap Agrikultur /E4. Sebelum menggunakan biogas, apa yang Anda lakukan untuk kotoran ternak? (Pertanyaan disesuaikan dengan jawaban E3)/g. Ayam/e. Sangat jarang (>1 bulan sekali) | SI1: E. Dampak Terhadap Agrikultur /E4. Sebelum menggunakan biogas, apa yang Anda lakukan untuk kotoran ternak? (Pertanyaan disesuaikan dengan jawaban E3)/g. Ayam/1-Disebarkan ke lahan terbuka | SJ1: E. Dampak Terhadap Agrikultur /E4. Sebelum menggunakan biogas, apa yang Anda lakukan untuk kotoran ternak? (Pertanyaan disesuaikan dengan jawaban E3)/g. Ayam/2-Dibuang ke sungai | SK1: E. Dampak Terhadap Agrikultur /E4. Sebelum menggunakan biogas, apa yang Anda lakukan untuk kotoran ternak? (Pertanyaan disesuaikan dengan jawaban E3)/g. Ayam/3-Dijual | SL1: E. Dampak Terhadap Agrikultur /E4. Sebelum menggunakan biogas, apa yang Anda lakukan untuk kotoran ternak? (Pertanyaan disesuaikan dengan jawaban E3)/g. Ayam/4-Lainnya | SM1: E. Dampak Terhadap Agrikultur /E4. Sebelum menggunakan biogas, apa yang Anda lakukan untuk kotoran ternak? (Pertanyaan disesuaikan dengan jawaban E3)/E4g-a. Lainnya: | SN1: E. Dampak Terhadap Agrikultur /E4. Sebelum menggunakan biogas, apa yang Anda lakukan untuk kotoran ternak? (Pertanyaan disesuaikan dengan jawaban E3)/h. Unggas lainnya | SO1: E. Dampak Terhadap Agrikultur /E4. Sebelum menggunakan biogas, apa yang Anda lakukan untuk kotoran ternak? (Pertanyaan disesuaikan dengan jawaban E3)/h. Unggas lainnya/a. Sangat teratur (setiap hari) | SP1: E. Dampak Terhadap Agrikultur /E4. Sebelum menggunakan biogas, apa yang Anda lakukan untuk kotoran ternak? (Pertanyaan disesuaikan dengan jawaban E3)/h. Unggas lainnya/b. Teratur (2-6 hari sekali) | SQ1: E. Dampak Terhadap Agrikultur /E4. Sebelum menggunakan biogas, apa yang Anda lakukan untuk kotoran ternak? (Pertanyaan disesuaikan dengan jawaban E3)/h. Unggas lainnya/c. Cukup teratur (setiap minggu) | SR1: E. Dampak Terhadap Agrikultur /E4. Sebelum menggunakan biogas, apa yang Anda lakukan untuk kotoran ternak? (Pertanyaan disesuaikan dengan jawaban E3)/h. Unggas lainnya/d. Jarang (2-3 minggu sekali) | SS1: E. Dampak Terhadap Agrikultur /E4. Sebelum menggunakan biogas, apa yang Anda lakukan untuk kotoran ternak? (Pertanyaan disesuaikan dengan jawaban E3)/h. Unggas lainnya/e. Sangat jarang (>1 bulan sekali) | ST1: E. Dampak Terhadap Agrikultur /E4. Sebelum menggunakan biogas, apa yang Anda lakukan untuk kotoran ternak? (Pertanyaan disesuaikan dengan jawaban E3)/h. Unggas lainnya/1-Disebarkan ke lahan terbuka | SU1: E. Dampak Terhadap Agrikultur /E4. Sebelum menggunakan biogas, apa yang Anda lakukan untuk kotoran ternak? (Pertanyaan disesuaikan dengan jawaban E3)/h. Unggas lainnya/2-Dibuang ke sungai | SV1: E. Dampak Terhadap Agrikultur /E4. Sebelum menggunakan biogas, apa yang Anda lakukan untuk kotoran ternak? (Pertanyaan disesuaikan dengan jawaban E3)/h. Unggas lainnya/3-Dijual | SW1: E. Dampak Terhadap Agrikultur /E4. Sebelum menggunakan biogas, apa yang Anda lakukan untuk kotoran ternak? (Pertanyaan disesuaikan dengan jawaban E3)/h. Unggas lainnya/4-Lainnya | SX1: E. Dampak Terhadap Agrikultur /E4. Sebelum menggunakan biogas, apa yang Anda lakukan untuk kotoran ternak? (Pertanyaan disesuaikan dengan jawaban E3)/E4h-a. Jika menjawab lainnya, apa yang Anda lakukan untuk kotoran ternak? | SY1: E. Dampak Terhadap Agrikultur /E5-a. Berapa jumlah hewan ternak yang Anda miliki sebelum menggunakan biogas?/a. Sapi pedaging (ekor)/Memiliki | SZ1: E. Dampak Terhadap Agrikultur /E5-a. Berapa jumlah hewan ternak yang Anda miliki sebelum menggunakan biogas?/b. Sapi perah (ekor)/Memiliki | TA1: E. Dampak Terhadap Agrikultur /E5-a. Berapa jumlah hewan ternak yang Anda miliki sebelum menggunakan biogas?/c. Sapi untuk kegunaan lainnya (ekor)/Memiliki | TB1: E. Dampak Terhadap Agrikultur /E5-a. Berapa jumlah hewan ternak yang Anda miliki sebelum menggunakan biogas?/d. Babi ternak/Memiliki | TC1: E. Dampak Terhadap Agrikultur /E5-a. Berapa jumlah hewan ternak yang Anda miliki sebelum menggunakan biogas?/e. Kuda (ekor)/Memiliki | TD1: E. Dampak Terhadap Agrikultur /E5-a. Berapa jumlah hewan ternak yang Anda miliki sebelum menggunakan biogas?/f. Kambing (ekor)/Memiliki | TE1: E. Dampak Terhadap Agrikultur /E5-a. Berapa jumlah hewan ternak yang Anda miliki sebelum menggunakan biogas?/g. Ayam (ekor)/Memiliki | TF1: E. Dampak Terhadap Agrikultur /E5-a. Berapa jumlah hewan ternak yang Anda miliki sebelum menggunakan biogas?/h. Unggas lainnya (ekor)/Memiliki | TG1: E. Dampak Terhadap Agrikultur /E5-b. Berapa jumlah hewan ternak yang Anda miliki saat ini (setelah menggunakan biogas)?/a. Sapi pedaging (ekor)/Memiliki | TH1: E. Dampak Terhadap Agrikultur /E5-b. Berapa jumlah hewan ternak yang Anda miliki saat ini (setelah menggunakan biogas)?/b. Sapi perah (ekor)/Memiliki | TI1: E. Dampak Terhadap Agrikultur /E5-b. Berapa jumlah hewan ternak yang Anda miliki saat ini (setelah menggunakan biogas)?/c. Sapi untuk penggunaan lain (ekor)/Memiliki | TJ1: E. Dampak Terhadap Agrikultur /E5-b. Berapa jumlah hewan ternak yang Anda miliki saat ini (setelah menggunakan biogas)?/d. Babi ternak (ekor)/Memiliki | TK1: E. Dampak Terhadap Agrikultur /E5-b. Berapa jumlah hewan ternak yang Anda miliki saat ini (setelah menggunakan biogas)?/e. Kuda (ekor)/Memiliki | TL1: E. Dampak Terhadap Agrikultur /E5-b. Berapa jumlah hewan ternak yang Anda miliki saat ini (setelah menggunakan biogas)?/f. Kambing (ekor)/Memiliki | TM1: E. Dampak Terhadap Agrikultur /E5-b. Berapa jumlah hewan ternak yang Anda miliki saat ini (setelah menggunakan biogas)?/g. Ayam (ekor)/Memiliki | TN1: E. Dampak Terhadap Agrikultur /E5-b. Berapa jumlah hewan ternak yang Anda miliki saat ini (setelah menggunakan biogas)?/h. Unggas lainnya (ekor)/Memiliki | TO1: E. Dampak Terhadap Agrikultur /E5-c. Dalam 12 bulan terakhir, berapa jumlah hewan ternak Anda yang mengalami perubahan berikut?/a. Sapi pedaging (ekor)/Menjual | TP1: E. Dampak Terhadap Agrikultur /E5-c. Dalam 12 bulan terakhir, berapa jumlah hewan ternak Anda yang mengalami perubahan berikut?/a. Sapi pedaging (ekor)/Membeli | TQ1: E. Dampak Terhadap Agrikultur /E5-c. Dalam 12 bulan terakhir, berapa jumlah hewan ternak Anda yang mengalami perubahan berikut?/a. Sapi pedaging (ekor)/Lahir | TR1: E. Dampak Terhadap Agrikultur /E5-c. Dalam 12 bulan terakhir, berapa jumlah hewan ternak Anda yang mengalami perubahan berikut?/a. Sapi pedaging (ekor)/Mati | TS1: E. Dampak Terhadap Agrikultur /E5-c. Dalam 12 bulan terakhir, berapa jumlah hewan ternak Anda yang mengalami perubahan berikut?/b. Sapi perah (ekor)/Menjual | TT1: E. Dampak Terhadap Agrikultur /E5-c. Dalam 12 bulan terakhir, berapa jumlah hewan ternak Anda yang mengalami perubahan berikut?/b. Sapi perah (ekor)/Membeli | TU1: E. Dampak Terhadap Agrikultur /E5-c. Dalam 12 bulan terakhir, berapa jumlah hewan ternak Anda yang mengalami perubahan berikut?/b. Sapi perah (ekor)/Lahir | TV1: E. Dampak Terhadap Agrikultur /E5-c. Dalam 12 bulan terakhir, berapa jumlah hewan ternak Anda yang mengalami perubahan berikut?/b. Sapi perah (ekor)/Mati | TW1: E. Dampak Terhadap Agrikultur /E5-c. Dalam 12 bulan terakhir, berapa jumlah hewan ternak Anda yang mengalami perubahan berikut?/c. Sapi untuk penggunaan lain (ekor)/Menjual | TX1: E. Dampak Terhadap Agrikultur /E5-c. Dalam 12 bulan terakhir, berapa jumlah hewan ternak Anda yang mengalami perubahan berikut?/c. Sapi untuk penggunaan lain (ekor)/Membeli | TY1: E. Dampak Terhadap Agrikultur /E5-c. Dalam 12 bulan terakhir, berapa jumlah hewan ternak Anda yang mengalami perubahan berikut?/c. Sapi untuk penggunaan lain (ekor)/Lahir | TZ1: E. Dampak Terhadap Agrikultur /E5-c. Dalam 12 bulan terakhir, berapa jumlah hewan ternak Anda yang mengalami perubahan berikut?/c. Sapi untuk penggunaan lain (ekor)/Mati | UA1: E. Dampak Terhadap Agrikultur /E5-c. Dalam 12 bulan terakhir, berapa jumlah hewan ternak Anda yang mengalami perubahan berikut?/d. Babi ternak (ekor)/Menjual | UB1: E. Dampak Terhadap Agrikultur /E5-c. Dalam 12 bulan terakhir, berapa jumlah hewan ternak Anda yang mengalami perubahan berikut?/d. Babi ternak (ekor)/Membeli | UC1: E. Dampak Terhadap Agrikultur /E5-c. Dalam 12 bulan terakhir, berapa jumlah hewan ternak Anda yang mengalami perubahan berikut?/d. Babi ternak (ekor)/Lahir | UD1: E. Dampak Terhadap Agrikultur /E5-c. Dalam 12 bulan terakhir, berapa jumlah hewan ternak Anda yang mengalami perubahan berikut?/d. Babi ternak (ekor)/Mati | UE1: E. Dampak Terhadap Agrikultur /E5-c. Dalam 12 bulan terakhir, berapa jumlah hewan ternak Anda yang mengalami perubahan berikut?/e. Kuda (ekor)/Menjual | UF1: E. Dampak Terhadap Agrikultur /E5-c. Dalam 12 bulan terakhir, berapa jumlah hewan ternak Anda yang mengalami perubahan berikut?/e. Kuda (ekor)/Membeli | UG1: E. Dampak Terhadap Agrikultur /E5-c. Dalam 12 bulan terakhir, berapa jumlah hewan ternak Anda yang mengalami perubahan berikut?/e. Kuda (ekor)/Lahir | UH1: E. Dampak Terhadap Agrikultur /E5-c. Dalam 12 bulan terakhir, berapa jumlah hewan ternak Anda yang mengalami perubahan berikut?/e. Kuda (ekor)/Mati | UI1: E. Dampak Terhadap Agrikultur /E5-c. Dalam 12 bulan terakhir, berapa jumlah hewan ternak Anda yang mengalami perubahan berikut?/f. Kambing (ekor)/Menjual | UJ1: E. Dampak Terhadap Agrikultur /E5-c. Dalam 12 bulan terakhir, berapa jumlah hewan ternak Anda yang mengalami perubahan berikut?/f. Kambing (ekor)/Membeli | UK1: E. Dampak Terhadap Agrikultur /E5-c. Dalam 12 bulan terakhir, berapa jumlah hewan ternak Anda yang mengalami perubahan berikut?/f. Kambing (ekor)/Lahir | UL1: E. Dampak Terhadap Agrikultur /E5-c. Dalam 12 bulan terakhir, berapa jumlah hewan ternak Anda yang mengalami perubahan berikut?/f. Kambing (ekor)/Mati | UM1: E. Dampak Terhadap Agrikultur /E5-c. Dalam 12 bulan terakhir, berapa jumlah hewan ternak Anda yang mengalami perubahan berikut?/g. Ayam (ekor)/Menjual | UN1: E. Dampak Terhadap Agrikultur /E5-c. Dalam 12 bulan terakhir, berapa jumlah hewan ternak Anda yang mengalami perubahan berikut?/g. Ayam (ekor)/Membeli | UO1: E. Dampak Terhadap Agrikultur /E5-c. Dalam 12 bulan terakhir, berapa jumlah hewan ternak Anda yang mengalami perubahan berikut?/g. Ayam (ekor)/Lahir | UP1: E. Dampak Terhadap Agrikultur /E5-c. Dalam 12 bulan terakhir, berapa jumlah hewan ternak Anda yang mengalami perubahan berikut?/g. Ayam (ekor)/Mati | UQ1: E. Dampak Terhadap Agrikultur /E5-c. Dalam 12 bulan terakhir, berapa jumlah hewan ternak Anda yang mengalami perubahan berikut?/h. Unggas lainnya (ekor)/Menjual | UR1: E. Dampak Terhadap Agrikultur /E5-c. Dalam 12 bulan terakhir, berapa jumlah hewan ternak Anda yang mengalami perubahan berikut?/h. Unggas lainnya (ekor)/Membeli | US1: E. Dampak Terhadap Agrikultur /E5-c. Dalam 12 bulan terakhir, berapa jumlah hewan ternak Anda yang mengalami perubahan berikut?/h. Unggas lainnya (ekor)/Lahir | UT1: E. Dampak Terhadap Agrikultur /E5-c. Dalam 12 bulan terakhir, berapa jumlah hewan ternak Anda yang mengalami perubahan berikut?/h. Unggas lainnya (ekor)/Mati | UU1: E. Dampak Terhadap Agrikultur /E6. Bagaimana cara Anda menggembalakan hewan ternak? (Pertanyaan disesuaikan dengan jawaban E2)/a. Sapi pedaging | UV1: E. Dampak Terhadap Agrikultur /E6. Bagaimana cara Anda menggembalakan hewan ternak? (Pertanyaan disesuaikan dengan jawaban E2)/b. Sapi perah | UW1: E. Dampak Terhadap Agrikultur /E6. Bagaimana cara Anda menggembalakan hewan ternak? (Pertanyaan disesuaikan dengan jawaban E2)/c. Sapi untuk kegunaan lain | UX1: E. Dampak Terhadap Agrikultur /E6. Bagaimana cara Anda menggembalakan hewan ternak? (Pertanyaan disesuaikan dengan jawaban E2)/d. Babi ternak | UY1: E. Dampak Terhadap Agrikultur /E6. Bagaimana cara Anda menggembalakan hewan ternak? (Pertanyaan disesuaikan dengan jawaban E2)/e. Kuda | UZ1: E. Dampak Terhadap Agrikultur /E6. Bagaimana cara Anda menggembalakan hewan ternak? (Pertanyaan disesuaikan dengan jawaban E2)/f. Kambing | VA1: E. Dampak Terhadap Agrikultur /E6. Bagaimana cara Anda menggembalakan hewan ternak? (Pertanyaan disesuaikan dengan jawaban E2)/g. Ayam | VB1: E. Dampak Terhadap Agrikultur /E6. Bagaimana cara Anda menggembalakan hewan ternak? (Pertanyaan disesuaikan dengan jawaban E2)/h. Unggas lainnya | VC1: E. Dampak Terhadap Agrikultur /E7. Bagaimana Anda mengelola kesehatan ternak Anda? (misal: pemberian vaksin)/a. Sapi pedaging | VD1: E. Dampak Terhadap Agrikultur /E7. Bagaimana Anda mengelola kesehatan ternak Anda? (misal: pemberian vaksin)/b. Sapi perah | VE1: E. Dampak Terhadap Agrikultur /E7. Bagaimana Anda mengelola kesehatan ternak Anda? (misal: pemberian vaksin)/c. Sapi untuk kegunaan lain | VF1: E. Dampak Terhadap Agrikultur /E7. Bagaimana Anda mengelola kesehatan ternak Anda? (misal: pemberian vaksin)/d. Babi ternak | VG1: E. Dampak Terhadap Agrikultur /E7. Bagaimana Anda mengelola kesehatan ternak Anda? (misal: pemberian vaksin)/e. Kuda | VH1: E. Dampak Terhadap Agrikultur /E7. Bagaimana Anda mengelola kesehatan ternak Anda? (misal: pemberian vaksin)/f. Kambing | VI1: E. Dampak Terhadap Agrikultur /E7. Bagaimana Anda mengelola kesehatan ternak Anda? (misal: pemberian vaksin)/g. Ayam | VJ1: E. Dampak Terhadap Agrikultur /E7. Bagaimana Anda mengelola kesehatan ternak Anda? (misal: pemberian vaksin)/h. Unggas lainnya | VK1: E. Dampak Terhadap Agrikultur /E8. Seberapa sering Anda merawat atau membersihkan kandang ternak?/a. Sapi pedaging | VL1: E. Dampak Terhadap Agrikultur /E8. Seberapa sering Anda merawat atau membersihkan kandang ternak?/b. Sapi perah | VM1: E. Dampak Terhadap Agrikultur /E8. Seberapa sering Anda merawat atau membersihkan kandang ternak?/c. Sapi untuk kegunaan lain | VN1: E. Dampak Terhadap Agrikultur /E8. Seberapa sering Anda merawat atau membersihkan kandang ternak?/d. Babi ternak | VO1: E. Dampak Terhadap Agrikultur /E8. Seberapa sering Anda merawat atau membersihkan kandang ternak?/e. Kuda | VP1: E. Dampak Terhadap Agrikultur /E8. Seberapa sering Anda merawat atau membersihkan kandang ternak?/f. Kambing | VQ1: E. Dampak Terhadap Agrikultur /E8. Seberapa sering Anda merawat atau membersihkan kandang ternak?/g. Ayam | VR1: E. Dampak Terhadap Agrikultur /E8. Seberapa sering Anda merawat atau membersihkan kandang ternak?/h. Unggas lainnya | VS1: E. Dampak Terhadap Agrikultur /E9. Bagaimana kotoran ternak biasa disimpan?/a. Sapi pedaging | VT1: E. Dampak Terhadap Agrikultur /E9. Bagaimana kotoran ternak biasa disimpan?/a. Sapi pedaging/1-Disebarkan ke lahan terbuka | VU1: E. Dampak Terhadap Agrikultur /E9. Bagaimana kotoran ternak biasa disimpan?/a. Sapi pedaging/2-Dibuang ke sungai | VV1: E. Dampak Terhadap Agrikultur /E9. Bagaimana kotoran ternak biasa disimpan?/a. Sapi pedaging/3-Dijual | VW1: E. Dampak Terhadap Agrikultur /E9. Bagaimana kotoran ternak biasa disimpan?/a. Sapi pedaging/4-Lainnya | VX1: E. Dampak Terhadap Agrikultur /E9. Bagaimana kotoran ternak biasa disimpan?/a. Sapi pedaging/1-Kolam tertutup (laguna anaerobik) | VY1: E. Dampak Terhadap Agrikultur /E9. Bagaimana kotoran ternak biasa disimpan?/a. Sapi pedaging/2-Disimpan basah (slurry) | VZ1: E. Dampak Terhadap Agrikultur /E9. Bagaimana kotoran ternak biasa disimpan?/a. Sapi pedaging/3-Disimpan terbuka (dry lot) | WA1: E. Dampak Terhadap Agrikultur /E9. Bagaimana kotoran ternak biasa disimpan?/a. Sapi pedaging/4-Disimpan dalam kotak bersekat | WB1: E. Dampak Terhadap Agrikultur /E9. Bagaimana kotoran ternak biasa disimpan?/a. Sapi pedaging/5-Untuk disebar di tanah (dan dibajak) | WC1: E. Dampak Terhadap Agrikultur /E9. Bagaimana kotoran ternak biasa disimpan?/a. Sapi pedaging/6-Digester biogas | WD1: E. Dampak Terhadap Agrikultur /E9. Bagaimana kotoran ternak biasa disimpan?/a. Sapi pedaging/7-Dibakar untuk bahan bakar | WE1: E. Dampak Terhadap Agrikultur /E9. Bagaimana kotoran ternak biasa disimpan?/a. Sapi pedaging/8-Dibiarkan tersebar di ladang penggembalaan | WF1: E. Dampak Terhadap Agrikultur /E9. Bagaimana kotoran ternak biasa disimpan?/b. Sapi perah | WG1: E. Dampak Terhadap Agrikultur /E9. Bagaimana kotoran ternak biasa disimpan?/b. Sapi perah/1-Disebarkan ke lahan terbuka | WH1: E. Dampak Terhadap Agrikultur /E9. Bagaimana kotoran ternak biasa disimpan?/b. Sapi perah/2-Dibuang ke sungai | WI1: E. Dampak Terhadap Agrikultur /E9. Bagaimana kotoran ternak biasa disimpan?/b. Sapi perah/3-Dijual | WJ1: E. Dampak Terhadap Agrikultur /E9. Bagaimana kotoran ternak biasa disimpan?/b. Sapi perah/4-Lainnya | WK1: E. Dampak Terhadap Agrikultur /E9. Bagaimana kotoran ternak biasa disimpan?/b. Sapi perah/1-Kolam tertutup (laguna anaerobik) | WL1: E. Dampak Terhadap Agrikultur /E9. Bagaimana kotoran ternak biasa disimpan?/b. Sapi perah/2-Disimpan basah (slurry) | WM1: E. Dampak Terhadap Agrikultur /E9. Bagaimana kotoran ternak biasa disimpan?/b. Sapi perah/3-Disimpan terbuka (dry lot) | WN1: E. Dampak Terhadap Agrikultur /E9. Bagaimana kotoran ternak biasa disimpan?/b. Sapi perah/4-Disimpan dalam kotak bersekat | WO1: E. Dampak Terhadap Agrikultur /E9. Bagaimana kotoran ternak biasa disimpan?/b. Sapi perah/5-Untuk disebar di tanah (dan dibajak) | WP1: E. Dampak Terhadap Agrikultur /E9. Bagaimana kotoran ternak biasa disimpan?/b. Sapi perah/6-Digester biogas | WQ1: E. Dampak Terhadap Agrikultur /E9. Bagaimana kotoran ternak biasa disimpan?/b. Sapi perah/7-Dibakar untuk bahan bakar | WR1: E. Dampak Terhadap Agrikultur /E9. Bagaimana kotoran ternak biasa disimpan?/b. Sapi perah/8-Dibiarkan tersebar di ladang penggembalaan | WS1: E. Dampak Terhadap Agrikultur /E9. Bagaimana kotoran ternak biasa disimpan?/c. Sapi untuk kegunan lain | WT1: E. Dampak Terhadap Agrikultur /E9. Bagaimana kotoran ternak biasa disimpan?/c. Sapi untuk kegunan lain/1-Kolam tertutup (laguna anaerobik) | WU1: E. Dampak Terhadap Agrikultur /E9. Bagaimana kotoran ternak biasa disimpan?/c. Sapi untuk kegunan lain/2-Disimpan basah (slurry) | WV1: E. Dampak Terhadap Agrikultur /E9. Bagaimana kotoran ternak biasa disimpan?/c. Sapi untuk kegunan lain/3-Disimpan terbuka (dry lot) | WW1: E. Dampak Terhadap Agrikultur /E9. Bagaimana kotoran ternak biasa disimpan?/c. Sapi untuk kegunan lain/4-Disimpan dalam kotak bersekat | WX1: E. Dampak Terhadap Agrikultur /E9. Bagaimana kotoran ternak biasa disimpan?/c. Sapi untuk kegunan lain/5-Untuk disebar di tanah (dan dibajak) | WY1: E. Dampak Terhadap Agrikultur /E9. Bagaimana kotoran ternak biasa disimpan?/c. Sapi untuk kegunan lain/6-Digester biogas | WZ1: E. Dampak Terhadap Agrikultur /E9. Bagaimana kotoran ternak biasa disimpan?/c. Sapi untuk kegunan lain/7-Dibakar untuk bahan bakar | XA1: E. Dampak Terhadap Agrikultur /E9. Bagaimana kotoran ternak biasa disimpan?/c. Sapi untuk kegunan lain/8-Dibiarkan tersebar di ladang penggembalaan | XB1: E. Dampak Terhadap Agrikultur /E9. Bagaimana kotoran ternak biasa disimpan?/d. Babi ternak | XC1: E. Dampak Terhadap Agrikultur /E9. Bagaimana kotoran ternak biasa disimpan?/d. Babi ternak/a. Penggembalaan terbuka | XD1: E. Dampak Terhadap Agrikultur /E9. Bagaimana kotoran ternak biasa disimpan?/d. Babi ternak/b. Penggembalaan semi-terbuka | XE1: E. Dampak Terhadap Agrikultur /E9. Bagaimana kotoran ternak biasa disimpan?/d. Babi ternak/c. Pemberian pakan di kandang | XF1: E. Dampak Terhadap Agrikultur /E9. Bagaimana kotoran ternak biasa disimpan?/d. Babi ternak/1-Kolam tertutup (laguna anaerobik) | XG1: E. Dampak Terhadap Agrikultur /E9. Bagaimana kotoran ternak biasa disimpan?/d. Babi ternak/2-Disimpan basah (slurry) | XH1: E. Dampak Terhadap Agrikultur /E9. Bagaimana kotoran ternak biasa disimpan?/d. Babi ternak/3-Disimpan terbuka (dry lot) | XI1: E. Dampak Terhadap Agrikultur /E9. Bagaimana kotoran ternak biasa disimpan?/d. Babi ternak/4-Disimpan dalam kotak bersekat | XJ1: E. Dampak Terhadap Agrikultur /E9. Bagaimana kotoran ternak biasa disimpan?/d. Babi ternak/5-Untuk disebar di tanah (dan dibajak) | XK1: E. Dampak Terhadap Agrikultur /E9. Bagaimana kotoran ternak biasa disimpan?/d. Babi ternak/6-Digester biogas | XL1: E. Dampak Terhadap Agrikultur /E9. Bagaimana kotoran ternak biasa disimpan?/d. Babi ternak/7-Dibakar untuk bahan bakar | XM1: E. Dampak Terhadap Agrikultur /E9. Bagaimana kotoran ternak biasa disimpan?/d. Babi ternak/8-Dibiarkan tersebar di ladang penggembalaan | XN1: E. Dampak Terhadap Agrikultur /E9. Bagaimana kotoran ternak biasa disimpan?/e. Kuda | XO1: E. Dampak Terhadap Agrikultur /E9. Bagaimana kotoran ternak biasa disimpan?/e. Kuda/1-Disebarkan ke lahan terbuka | XP1: E. Dampak Terhadap Agrikultur /E9. Bagaimana kotoran ternak biasa disimpan?/e. Kuda/2-Dibuang ke sungai | XQ1: E. Dampak Terhadap Agrikultur /E9. Bagaimana kotoran ternak biasa disimpan?/e. Kuda/3-Dijual | XR1: E. Dampak Terhadap Agrikultur /E9. Bagaimana kotoran ternak biasa disimpan?/e. Kuda/4-Lainnya | XS1: E. Dampak Terhadap Agrikultur /E9. Bagaimana kotoran ternak biasa disimpan?/e. Kuda/1-Kolam tertutup (laguna anaerobik) | XT1: E. Dampak Terhadap Agrikultur /E9. Bagaimana kotoran ternak biasa disimpan?/e. Kuda/2-Disimpan basah (slurry) | XU1: E. Dampak Terhadap Agrikultur /E9. Bagaimana kotoran ternak biasa disimpan?/e. Kuda/3-Disimpan terbuka (dry lot) | XV1: E. Dampak Terhadap Agrikultur /E9. Bagaimana kotoran ternak biasa disimpan?/e. Kuda/4-Disimpan dalam kotak bersekat | XW1: E. Dampak Terhadap Agrikultur /E9. Bagaimana kotoran ternak biasa disimpan?/e. Kuda/5-Untuk disebar di tanah (dan dibajak) | XX1: E. Dampak Terhadap Agrikultur /E9. Bagaimana kotoran ternak biasa disimpan?/e. Kuda/6-Digester biogas | XY1: E. Dampak Terhadap Agrikultur /E9. Bagaimana kotoran ternak biasa disimpan?/e. Kuda/7-Dibakar untuk bahan bakar | XZ1: E. Dampak Terhadap Agrikultur /E9. Bagaimana kotoran ternak biasa disimpan?/e. Kuda/8-Dibiarkan tersebar di ladang penggembalaan | YA1: E. Dampak Terhadap Agrikultur /E9. Bagaimana kotoran ternak biasa disimpan?/f. Kambing | YB1: E. Dampak Terhadap Agrikultur /E9. Bagaimana kotoran ternak biasa disimpan?/f. Kambing/1-Disebarkan ke lahan terbuka | YC1: E. Dampak Terhadap Agrikultur /E9. Bagaimana kotoran ternak biasa disimpan?/f. Kambing/2-Dibuang ke sungai | YD1: E. Dampak Terhadap Agrikultur /E9. Bagaimana kotoran ternak biasa disimpan?/f. Kambing/3-Dijual | YE1: E. Dampak Terhadap Agrikultur /E9. Bagaimana kotoran ternak biasa disimpan?/f. Kambing/4-Lainnya | YF1: E. Dampak Terhadap Agrikultur /E9. Bagaimana kotoran ternak biasa disimpan?/f. Kambing/1-Kolam tertutup (laguna anaerobik) | YG1: E. Dampak Terhadap Agrikultur /E9. Bagaimana kotoran ternak biasa disimpan?/f. Kambing/2-Disimpan basah (slurry) | YH1: E. Dampak Terhadap Agrikultur /E9. Bagaimana kotoran ternak biasa disimpan?/f. Kambing/3-Disimpan terbuka (dry lot) | YI1: E. Dampak Terhadap Agrikultur /E9. Bagaimana kotoran ternak biasa disimpan?/f. Kambing/4-Disimpan dalam kotak bersekat | YJ1: E. Dampak Terhadap Agrikultur /E9. Bagaimana kotoran ternak biasa disimpan?/f. Kambing/5-Untuk disebar di tanah (dan dibajak) | YK1: E. Dampak Terhadap Agrikultur /E9. Bagaimana kotoran ternak biasa disimpan?/f. Kambing/6-Digester biogas | YL1: E. Dampak Terhadap Agrikultur /E9. Bagaimana kotoran ternak biasa disimpan?/f. Kambing/7-Dibakar untuk bahan bakar | YM1: E. Dampak Terhadap Agrikultur /E9. Bagaimana kotoran ternak biasa disimpan?/f. Kambing/8-Dibiarkan tersebar di ladang penggembalaan | YN1: E. Dampak Terhadap Agrikultur /E9. Bagaimana kotoran ternak biasa disimpan?/g. Ayam | YO1: E. Dampak Terhadap Agrikultur /E9. Bagaimana kotoran ternak biasa disimpan?/g. Ayam/1-Disebarkan ke lahan terbuka | YP1: E. Dampak Terhadap Agrikultur /E9. Bagaimana kotoran ternak biasa disimpan?/g. Ayam/2-Dibuang ke sungai | YQ1: E. Dampak Terhadap Agrikultur /E9. Bagaimana kotoran ternak biasa disimpan?/g. Ayam/3-Dijual | YR1: E. Dampak Terhadap Agrikultur /E9. Bagaimana kotoran ternak biasa disimpan?/g. Ayam/4-Lainnya | YS1: E. Dampak Terhadap Agrikultur /E9. Bagaimana kotoran ternak biasa disimpan?/g. Ayam/1-Kolam tertutup (laguna anaerobik) | YT1: E. Dampak Terhadap Agrikultur /E9. Bagaimana kotoran ternak biasa disimpan?/g. Ayam/2-Disimpan basah (slurry) | YU1: E. Dampak Terhadap Agrikultur /E9. Bagaimana kotoran ternak biasa disimpan?/g. Ayam/3-Disimpan terbuka (dry lot) | YV1: E. Dampak Terhadap Agrikultur /E9. Bagaimana kotoran ternak biasa disimpan?/g. Ayam/4-Disimpan dalam kotak bersekat | YW1: E. Dampak Terhadap Agrikultur /E9. Bagaimana kotoran ternak biasa disimpan?/g. Ayam/5-Untuk disebar di tanah (dan dibajak) | YX1: E. Dampak Terhadap Agrikultur /E9. Bagaimana kotoran ternak biasa disimpan?/g. Ayam/6-Digester biogas | YY1: E. Dampak Terhadap Agrikultur /E9. Bagaimana kotoran ternak biasa disimpan?/g. Ayam/7-Dibakar untuk bahan bakar | YZ1: E. Dampak Terhadap Agrikultur /E9. Bagaimana kotoran ternak biasa disimpan?/g. Ayam/8-Dibiarkan tersebar di ladang penggembalaan | ZA1: E. Dampak Terhadap Agrikultur /E9. Bagaimana kotoran ternak biasa disimpan?/h. Unggas lainnya | ZB1: E. Dampak Terhadap Agrikultur /E9. Bagaimana kotoran ternak biasa disimpan?/h. Unggas lainnya/1-Disebarkan ke lahan terbuka | ZC1: E. Dampak Terhadap Agrikultur /E9. Bagaimana kotoran ternak biasa disimpan?/h. Unggas lainnya/2-Dibuang ke sungai | ZD1: E. Dampak Terhadap Agrikultur /E9. Bagaimana kotoran ternak biasa disimpan?/h. Unggas lainnya/3-Dijual | ZE1: E. Dampak Terhadap Agrikultur /E9. Bagaimana kotoran ternak biasa disimpan?/h. Unggas lainnya/4-Lainnya | ZF1: E. Dampak Terhadap Agrikultur /E9. Bagaimana kotoran ternak biasa disimpan?/h. Unggas lainnya/1-Kolam tertutup (laguna anaerobik) | ZG1: E. Dampak Terhadap Agrikultur /E9. Bagaimana kotoran ternak biasa disimpan?/h. Unggas lainnya/2-Disimpan basah (slurry) | ZH1: E. Dampak Terhadap Agrikultur /E9. Bagaimana kotoran ternak biasa disimpan?/h. Unggas lainnya/3-Disimpan terbuka (dry lot) | ZI1: E. Dampak Terhadap Agrikultur /E9. Bagaimana kotoran ternak biasa disimpan?/h. Unggas lainnya/4-Disimpan dalam kotak bersekat | ZJ1: E. Dampak Terhadap Agrikultur /E9. Bagaimana kotoran ternak biasa disimpan?/h. Unggas lainnya/5-Untuk disebar di tanah (dan dibajak) | ZK1: E. Dampak Terhadap Agrikultur /E9. Bagaimana kotoran ternak biasa disimpan?/h. Unggas lainnya/6-Digester biogas | ZL1: E. Dampak Terhadap Agrikultur /E9. Bagaimana kotoran ternak biasa disimpan?/h. Unggas lainnya/7-Dibakar untuk bahan bakar | ZM1: E. Dampak Terhadap Agrikultur /E9. Bagaimana kotoran ternak biasa disimpan?/h. Unggas lainnya/8-Dibiarkan tersebar di ladang penggembalaan | ZN1: E. Dampak Terhadap Agrikultur /E10. Berapa banyak kotoran ternak yang dimasukkan ke dalam biodigester?/a. Sapi pedaging | ZO1: E. Dampak Terhadap Agrikultur /E10. Berapa banyak kotoran ternak yang dimasukkan ke dalam biodigester?/b. Sapi perah | ZP1: E. Dampak Terhadap Agrikultur /E10. Berapa banyak kotoran ternak yang dimasukkan ke dalam biodigester?/c. Sapi untuk kegunaan lain | ZQ1: E. Dampak Terhadap Agrikultur /E10. Berapa banyak kotoran ternak yang dimasukkan ke dalam biodigester?/d. Babi ternak | ZR1: E. Dampak Terhadap Agrikultur /E10. Berapa banyak kotoran ternak yang dimasukkan ke dalam biodigester?/e. Kuda | ZS1: E. Dampak Terhadap Agrikultur /E10. Berapa banyak kotoran ternak yang dimasukkan ke dalam biodigester?/f. Kambing | ZT1: E. Dampak Terhadap Agrikultur /E10. Berapa banyak kotoran ternak yang dimasukkan ke dalam biodigester?/g. Ayam | ZU1: E. Dampak Terhadap Agrikultur /E10. Berapa banyak kotoran ternak yang dimasukkan ke dalam biodigester?/h. Unggas lainnya | ZV1: E. Dampak Terhadap Agrikultur /E11. Seberapa sering Anda memberi pakan ternak Anda?/a. Sapi pedaging | ZW1: E. Dampak Terhadap Agrikultur /E11. Seberapa sering Anda memberi pakan ternak Anda?/b. Sapi perah | ZX1: E. Dampak Terhadap Agrikultur /E11. Seberapa sering Anda memberi pakan ternak Anda?/c. Sapi untuk kegunaan lain (misal kerbau) | ZY1: E. Dampak Terhadap Agrikultur /E11. Seberapa sering Anda memberi pakan ternak Anda?/d. Babi ternak | ZZ1: E. Dampak Terhadap Agrikultur /E11. Seberapa sering Anda memberi pakan ternak Anda?/e. Kuda | AAA1: E. Dampak Terhadap Agrikultur /E11. Seberapa sering Anda memberi pakan ternak Anda?/f. Kambing | AAB1: E. Dampak Terhadap Agrikultur /E11. Seberapa sering Anda memberi pakan ternak Anda?/g. Ayam | AAC1: E. Dampak Terhadap Agrikultur /E11. Seberapa sering Anda memberi pakan ternak Anda?/h. Unggas lainnya | AAD1: E. Dampak Terhadap Agrikultur /E12. Apa tipe pakan utama untuk ternak?/a. Sapi pedaging | AAE1: E. Dampak Terhadap Agrikultur /E12. Apa tipe pakan utama untuk ternak?/b. Sapi perah | AAF1: E. Dampak Terhadap Agrikultur /E12. Apa tipe pakan utama untuk ternak?/c. Sapi untuk kegunaan lain | AAG1: E. Dampak Terhadap Agrikultur /E12. Apa tipe pakan utama untuk ternak?/d. Babi ternak | AAH1: E. Dampak Terhadap Agrikultur /E12. Apa tipe pakan utama untuk ternak?/e. Kuda | AAI1: E. Dampak Terhadap Agrikultur /E12. Apa tipe pakan utama untuk ternak?/f. Kambing | AAJ1: E. Dampak Terhadap Agrikultur /E12. Apa tipe pakan utama untuk ternak?/g. Ayam | AAK1: E. Dampak Terhadap Agrikultur /E12. Apa tipe pakan utama untuk ternak?/h. Unggas lainnya | AAL1: E. Dampak Terhadap Agrikultur /E13. Apakah Anda menggunakan bio-slurry? | AAM1: E. Dampak Terhadap Agrikultur /E13-a. Dalam bentuk apa bioslurry yang Anda gunakan? | AAN1: E. Dampak Terhadap Agrikultur /E13-a. Dalam bentuk apa bioslurry yang Anda gunakan?/Padat | AAO1: E. Dampak Terhadap Agrikultur /E13-a. Dalam bentuk apa bioslurry yang Anda gunakan?/Cair | AAP1: E. Dampak Terhadap Agrikultur /E14. Berapa banyak bioslurry yang Anda gunakan setiap hari yang berasal dari sistem biogas Anda?/liter/hari (cair) | AAQ1: E. Dampak Terhadap Agrikultur /E14. Berapa banyak bioslurry yang Anda gunakan setiap hari yang berasal dari sistem biogas Anda?/kg/hari (padat) | AAR1: E. Dampak Terhadap Agrikultur /E15. Apakah Anda pernah mendapatkan pelatihan mengenai pemanfaatan bio-slurry oleh CPO? | AAS1: E. Dampak Terhadap Agrikultur /E16. Apakah Anda mengetahui manfaat bio-slurry? | AAT1: E. Dampak Terhadap Agrikultur /E17. Bagaimana Anda memanfaatkan bio-slurry? | AAU1: E. Dampak Terhadap Agrikultur /E17. Bagaimana Anda memanfaatkan bio-slurry?/Digunakan untuk pupuk di lahan pertanian sendiri | AAV1: E. Dampak Terhadap Agrikultur /E17. Bagaimana Anda memanfaatkan bio-slurry?/Digunakan untuk kegiatan peternakan sendiri | AAW1: E. Dampak Terhadap Agrikultur /E17. Bagaimana Anda memanfaatkan bio-slurry?/Dijual - baik tanpa diolah/diolah/dibuat kascing | AAX1: E. Dampak Terhadap Agrikultur /E17. Bagaimana Anda memanfaatkan bio-slurry?/Dibuang ke lahan sekitar kandang - yg ditanami tanaman | AAY1: E. Dampak Terhadap Agrikultur /E17. Bagaimana Anda memanfaatkan bio-slurry?/Diberikan gratis ke orang lain | AAZ1: E. Dampak Terhadap Agrikultur /E17. Bagaimana Anda memanfaatkan bio-slurry?/Didiamkan saja/dibiarkan di tempatnya (di bak/kolam penampung slurry) | ABA1: E. Dampak Terhadap Agrikultur /E17. Bagaimana Anda memanfaatkan bio-slurry?/Dibuang ke selokan | ABB1: E. Dampak Terhadap Agrikultur /E18. Jika digunakan sendiri, digunakan sebagai apa bioslurry Anda?/Pertanian: | ABC1: E. Dampak Terhadap Agrikultur /E18. Jika digunakan sendiri, digunakan sebagai apa bioslurry Anda?/Pertanian:/ Pupuk cair untuk tanaman | ABD1: E. Dampak Terhadap Agrikultur /E18. Jika digunakan sendiri, digunakan sebagai apa bioslurry Anda?/Pertanian:/Pembenah tanah (soil conditioner) | ABE1: E. Dampak Terhadap Agrikultur /E18. Jika digunakan sendiri, digunakan sebagai apa bioslurry Anda?/Pertanian:/Pestisida organik | ABF1: E. Dampak Terhadap Agrikultur /E18. Jika digunakan sendiri, digunakan sebagai apa bioslurry Anda?/Pertanian:/Media untuk pembibitan tanaman | ABG1: E. Dampak Terhadap Agrikultur /E18. Jika digunakan sendiri, digunakan sebagai apa bioslurry Anda?/Pertanian:/Lainnya | ABH1: E. Dampak Terhadap Agrikultur /E18. Jika digunakan sendiri, digunakan sebagai apa bioslurry Anda?/E18a-a. Lainnya: | ABI1: E. Dampak Terhadap Agrikultur /E18. Jika digunakan sendiri, digunakan sebagai apa bioslurry Anda?/Peternakan: | ABJ1: E. Dampak Terhadap Agrikultur /E18. Jika digunakan sendiri, digunakan sebagai apa bioslurry Anda?/Peternakan:/Campuran pakan ikan | ABK1: E. Dampak Terhadap Agrikultur /E18. Jika digunakan sendiri, digunakan sebagai apa bioslurry Anda?/Peternakan:/Campuran pakan unggas | ABL1: E. Dampak Terhadap Agrikultur /E18. Jika digunakan sendiri, digunakan sebagai apa bioslurry Anda?/Peternakan:/Media ternak cacing | ABM1: E. Dampak Terhadap Agrikultur /E18. Jika digunakan sendiri, digunakan sebagai apa bioslurry Anda?/Peternakan:/Pupuk kolam ikan | ABN1: E. Dampak Terhadap Agrikultur /E18. Jika digunakan sendiri, digunakan sebagai apa bioslurry Anda?/Peternakan:/Lainnya | ABO1: E. Dampak Terhadap Agrikultur /E18. Jika digunakan sendiri, digunakan sebagai apa bioslurry Anda?/E18b-a. Lainnya: | ABP1: E. Dampak Terhadap Agrikultur /E19. Jika Anda menjual bioslurry, dalam bentuk apa Anda menjual bio-slurry? | ABQ1: E. Dampak Terhadap Agrikultur /E20. Untuk jenis tanaman pertanian apa yang Anda gunakan bioslurry? | ABR1: E. Dampak Terhadap Agrikultur /E21. Seberapa sering Anda memberi bioslurry ke lahan pertanian Anda? | ABS1: E. Dampak Terhadap Agrikultur /E22. Berapa luas lahan Anda (m2) yang menggunakan bioslurry sebagai pupuk? | ABT1: E. Dampak Terhadap Agrikultur /E23. Berapa luas lahan Anda (m2) di sekitar kandang yang menjadi tempat pembuangan bioslurry? | ABU1: E. Dampak Terhadap Agrikultur /E24. Berapa jumlah bioslurry yang Anda gunakan untuk digunakan di lahan pertanian Anda dalam sekali pemakaian?/Liter (cair) | ABV1: E. Dampak Terhadap Agrikultur /E24. Berapa jumlah bioslurry yang Anda gunakan untuk digunakan di lahan pertanian Anda dalam sekali pemakaian?/Kilogram (padat) | ABW1: E. Dampak Terhadap Agrikultur /E25. Jenis pupuk apa yang Anda gunakan sebelum menggunakan bioslurry untuk pertanian? | ABX1: E. Dampak Terhadap Agrikultur /E25-a. Lainnya: | ABY1: E. Dampak Terhadap Agrikultur /E26. Berapa banyak pupuk kimia yang Anda gunakan sebelum menggunakan bioslurry? | ABZ1: E. Dampak Terhadap Agrikultur /E26-a. Berapa harga pupuk tersebut (saat sebelum menggunakan bioslurry) ? | ACA1: E. Dampak Terhadap Agrikultur /E27. Berapa banyak pupuk kimia yang Anda gunakan setelah menggantinya dengan bioslurry? | ACB1: E. Dampak Terhadap Agrikultur /E27-a. Berapa harga pupuk tersebut sekarang? | ACC1: E. Dampak Terhadap Agrikultur /E28. Berapa banyak hasil pertanian yang dapat Anda panen sebelum menggunakan bioslurry? | ACD1: E. Dampak Terhadap Agrikultur /E29. Berapa banyak hasil pertanian yang dapat Anda panen setelah menggunakan bioslurry? | ACE1: E. Dampak Terhadap Agrikultur /E30. Apakah bio-slurry memungkinkan Anda untuk menanam jenis tanaman baru? | ACF1: E. Dampak Terhadap Agrikultur /E31. Bagaimana kualitas tanah Anda setelah penggunaan bioslurry? | ACG1: E. Dampak Terhadap Agrikultur /E32. Bagaimana ketahanan tanaman terhadap hama atau penyakit setelah penggunaan bioslurry? | ACH1: E. Dampak Terhadap Agrikultur /E33. Apakah penggunaan bioslurry sebagai pupuk organik meningkatkan ketahanan tanaman terhadap kekeringan? | ACI1: E. Dampak Terhadap Agrikultur /E34. Apakah penggunaan bioslurry meningkatkan kualitas atau kuantitas pakan ternak yang dihasilkan dari kegiatan peternakan? (misal: peningkatan jumlah rumput) | ACJ1: E. Dampak Terhadap Agrikultur /E35. Apakah penggunaan bioslurry untuk peternakan (seperti campuran pakan ikan atau unggas) meningkatkan produktivitas hewan ternak (misalnya, lebih cepat tumbuh, lebih banyak produksi susu atau telur)? | ACK1: E. Dampak Terhadap Agrikultur /E36. Jika tidak memanfaatkan bioslurry, mengapa? | ACL1: E. Dampak Terhadap Agrikultur /E36. Jika tidak memanfaatkan bioslurry, mengapa? /Tidak/kurang baik untuk tanaman | ACM1: E. Dampak Terhadap Agrikultur /E36. Jika tidak memanfaatkan bioslurry, mengapa? /Tidak memiliki tempat untuk menyimpan | ACN1: E. Dampak Terhadap Agrikultur /E36. Jika tidak memanfaatkan bioslurry, mengapa? /Tidak punya waktu mengumpulkannya | ACO1: E. Dampak Terhadap Agrikultur /E36. Jika tidak memanfaatkan bioslurry, mengapa? /Ladang/sawah terlalu jauh, sulit untuk mengangkut ke sana | ACP1: E. Dampak Terhadap Agrikultur /E36. Jika tidak memanfaatkan bioslurry, mengapa? /Belum tau bahwa bioslurry bagus untuk pupuk | ACQ1: E. Dampak Terhadap Agrikultur /E36. Jika tidak memanfaatkan bioslurry, mengapa? /Lebih praktis menggunakan pupuk kimia | ACR1: E. Dampak Terhadap Agrikultur /E36. Jika tidak memanfaatkan bioslurry, mengapa? /Lainnya | ACS1: E. Dampak Terhadap Agrikultur /E36-a. Lainnya: | ACT1: E. Dampak Terhadap Agrikultur /E37. Apakah ada informasi tambahan lain terkait dengan sumber bahan baku pembuatan biogas? | ACU1: F. Dampak Terhadap Gender /F1. Apakah penggunaan biogas memberikan manfaat khusus bagi perempuan atau anak-anak dalam keluarga? | ACV1: F. Dampak Terhadap Gender /F2. Apakah secara umum beban kerja perempuan di rumah berkurang sejak penggunaan biogas? | ACW1: F. Dampak Terhadap Gender /F3. Jika dengan pemasangan biogas Anda dapat menghemat uang atau menambah pendapatan, siapa yang akan mengelola keuangan di rumah tangga? | ACX1: F. Dampak Terhadap Gender /F4. Menurut Anda, apakah secara umum sistem biogas dapat meningkatkan pemberdayaan perempuan di komunitas Anda? | ACY1: G. Kepuasan dan Persepsi Pengguna /G1. Siapa yang terdampak manfaat dari penggunaan biogas? | ACZ1: G. Kepuasan dan Persepsi Pengguna /G1. Siapa yang terdampak manfaat dari penggunaan biogas? /Anggota keluarga - Laki-laki dewasa | ADA1: G. Kepuasan dan Persepsi Pengguna /G1. Siapa yang terdampak manfaat dari penggunaan biogas? /Anggota keluarga - Perempuan dewasa | ADB1: G. Kepuasan dan Persepsi Pengguna /G1. Siapa yang terdampak manfaat dari penggunaan biogas? /Anggota keluarga - Anak-anak | ADC1: G. Kepuasan dan Persepsi Pengguna /G1. Siapa yang terdampak manfaat dari penggunaan biogas? /Tidak ada manfaat | ADD1: G. Kepuasan dan Persepsi Pengguna /G2. Seberapa puas Anda secara keseluruhan dengan biogas yang Anda gunakan? | ADE1: G. Kepuasan dan Persepsi Pengguna /G3. Bagaimana Anda menilai kualitas konstruksi dan peralatan biogas Anda (kompor, lampu, gas tap, dll.)? | ADF1: G. Kepuasan dan Persepsi Pengguna /G4. Seberapa puas Anda dengan pemasangan sistem biogas? | ADG1: G. Kepuasan dan Persepsi Pengguna /G5. Seberapa puas Anda dengan pengurangan biaya energi rumah tangga yang dihasilkan oleh sistem biogas? | ADH1: G. Kepuasan dan Persepsi Pengguna /G6. Apakah ada peralatan yang perlu diganti dalam 12 bulan terakhir? | ADI1: G. Kepuasan dan Persepsi Pengguna /G6-a. Apa saja peralatan yang diganti? | ADJ1: G. Kepuasan dan Persepsi Pengguna /G7. Seberapa puas Anda dengan layanan yang diberikan oleh Construction Partner Organization (CPO)? | ADK1: G. Kepuasan dan Persepsi Pengguna /G8. Jika Anda merasa kurang puas, mengapa? | ADL1: G. Kepuasan dan Persepsi Pengguna /G8. Jika Anda merasa kurang puas, mengapa?/ Pelayanan kurang ramah | ADM1: G. Kepuasan dan Persepsi Pengguna /G8. Jika Anda merasa kurang puas, mengapa?/ Pelatihan yang diberikan kurang menyeluruh/tidak lengkap atau tidak ada pelatihan | ADN1: G. Kepuasan dan Persepsi Pengguna /G8. Jika Anda merasa kurang puas, mengapa?/Sulit dihubungi ketika biogas bermasalah | ADO1: G. Kepuasan dan Persepsi Pengguna /G8. Jika Anda merasa kurang puas, mengapa?/Biogas yang dibangun sulit/tidak bisa langsung dioperasikan setelah dibangun | ADP1: G. Kepuasan dan Persepsi Pengguna /G8. Jika Anda merasa kurang puas, mengapa?/ Monitoring/pengawasan tidak rutin | ADQ1: G. Kepuasan dan Persepsi Pengguna /G8. Jika Anda merasa kurang puas, mengapa?/Penanganan kerusakannya lambat | ADR1: G. Kepuasan dan Persepsi Pengguna /G8. Jika Anda merasa kurang puas, mengapa?/Kualitas yang diberikan tidak sesuai biaya yang dikeluarkan | ADS1: G. Kepuasan dan Persepsi Pengguna /G8. Jika Anda merasa kurang puas, mengapa?/ Lainnya | ADT1: G. Kepuasan dan Persepsi Pengguna /G8-. Lainnya: | ADU1: G. Kepuasan dan Persepsi Pengguna /G9. Jika ada kerusakan, apa yang Anda lakukan? | ADV1: G. Kepuasan dan Persepsi Pengguna /G9. Jika ada kerusakan, apa yang Anda lakukan?/a. Menghubungi CPO atau pendamping | ADW1: G. Kepuasan dan Persepsi Pengguna /G9. Jika ada kerusakan, apa yang Anda lakukan?/b. Memperbaiki sendiri | ADX1: G. Kepuasan dan Persepsi Pengguna /G9. Jika ada kerusakan, apa yang Anda lakukan?/c. Dibiarkan saja | ADY1: G. Kepuasan dan Persepsi Pengguna /G9. Jika ada kerusakan, apa yang Anda lakukan?/d. Lainnya | ADZ1: G. Kepuasan dan Persepsi Pengguna /G9. Jika ada kerusakan, apa yang Anda lakukan?/Menghubungi CPO atau pendamping | AEA1: G. Kepuasan dan Persepsi Pengguna /G9. Jika ada kerusakan, apa yang Anda lakukan?/Memperbaiki sendiri | AEB1: G. Kepuasan dan Persepsi Pengguna /G9. Jika ada kerusakan, apa yang Anda lakukan?/Dibiarkan saja | AEC1: G. Kepuasan dan Persepsi Pengguna /G9. Jika ada kerusakan, apa yang Anda lakukan?/Lainnya | AED1: G. Kepuasan dan Persepsi Pengguna /G9-a. Lainnya: | AEE1: G. Kepuasan dan Persepsi Pengguna /G10. Jika menghubungi CPO, siapa yang menghubungi? | AEF1: G. Kepuasan dan Persepsi Pengguna /G10-a. Lainnya: | AEG1: G. Kepuasan dan Persepsi Pengguna /G11. Bagaimana Anda menghubungi CPO? | AEH1: G. Kepuasan dan Persepsi Pengguna /G11-a. Lainnya: | AEI1: G. Kepuasan dan Persepsi Pengguna /G12. Apakah Anda memiliki saran untuk meningkatkan layanan dan kualitas sistem biogas? | AEJ1: G. Kepuasan dan Persepsi Pengguna /G13. Apakah Anda merasa didengar oleh pihak penyedia layanan saat memberikan masukan? | AEK1: G. Kepuasan dan Persepsi Pengguna /G14. Apa saja manfaat yang Anda rasakan dari memiliki instalasi biogas? | AEL1: G. Kepuasan dan Persepsi Pengguna /G14. Apa saja manfaat yang Anda rasakan dari memiliki instalasi biogas?/Pengurangan pengeluaran rumah tangga (bahan bakar minyak, pupuk, dll.) | AEM1: G. Kepuasan dan Persepsi Pengguna /G14. Apa saja manfaat yang Anda rasakan dari memiliki instalasi biogas?/ Lebih mudah mendapatkan energi | AEN1: G. Kepuasan dan Persepsi Pengguna /G14. Apa saja manfaat yang Anda rasakan dari memiliki instalasi biogas?/Pasokan energi yang andal | AEO1: G. Kepuasan dan Persepsi Pengguna /G14. Apa saja manfaat yang Anda rasakan dari memiliki instalasi biogas?/ Memasak lebih cepat | AEP1: G. Kepuasan dan Persepsi Pengguna /G14. Apa saja manfaat yang Anda rasakan dari memiliki instalasi biogas?/ Lebih aman | AEQ1: G. Kepuasan dan Persepsi Pengguna /G14. Apa saja manfaat yang Anda rasakan dari memiliki instalasi biogas?/ Pengurangan waktu dan tenaga | AER1: G. Kepuasan dan Persepsi Pengguna /G14. Apa saja manfaat yang Anda rasakan dari memiliki instalasi biogas?/Peningkatan kebersihan kandang ternak | AES1: G. Kepuasan dan Persepsi Pengguna /G14. Apa saja manfaat yang Anda rasakan dari memiliki instalasi biogas?/Pemanfaatan bio-slurry sebagai pupuk | AET1: G. Kepuasan dan Persepsi Pengguna /G14. Apa saja manfaat yang Anda rasakan dari memiliki instalasi biogas?/Dapur lebih bersih dan bebas asap | AEU1: G. Kepuasan dan Persepsi Pengguna /G14. Apa saja manfaat yang Anda rasakan dari memiliki instalasi biogas?/Dapat dibayar melalui skema kredit | AEV1: G. Kepuasan dan Persepsi Pengguna /G14. Apa saja manfaat yang Anda rasakan dari memiliki instalasi biogas?/ Mendapatkan subsidi | AEW1: G. Kepuasan dan Persepsi Pengguna /G14. Apa saja manfaat yang Anda rasakan dari memiliki instalasi biogas?/Lainnya | AEX1: G. Kepuasan dan Persepsi Pengguna /G14-a. Lainnya: | AEY1: G. Kepuasan dan Persepsi Pengguna /G15. Apa alasan utama Anda memutuskan untuk memasang biogas? (Pilih satu) | AEZ1: G. Kepuasan dan Persepsi Pengguna /G15-a. Lainnya: | AFA1: G. Kepuasan dan Persepsi Pengguna /G16. Dari mana Anda mendapatkan informasi tentang biogas sebelum menjadi pengguna? | AFB1: G. Kepuasan dan Persepsi Pengguna /G16-a. Lainnya: | AFC1: Dokumentasi Survei/Unggah Foto Biodigester | AFD1: Dokumentasi Survei/Unggah Foto Biodigester_URL | AFE1: Dokumentasi Survei/Unggah Foto Proses Wawancara | AFF1: Dokumentasi Survei/Unggah Foto Proses Wawancara_URL | AFG1: Catatan Validasi Enum/Nama Enum/Username | AFH1: Catatan Validasi Enum/Catatan Validsi Enumerator (Field Notes) | AFI1: Catatan Validasi Enum/Jelaskan jika ada jawaban tidak lengkap, meragukan, atau butuh keterangan tambahan
A2: 46057 | B2: 46057 | C2: Marmanto | D2: Ponimin | E2: 6285602796489 | G2: -7.195 | H2: 110.97612 | J2: 4.77 | M2: -7.3556082 | N2: 110.3349 | P2: 4.06 | R2: Jawa Tengah | AC2: Klaten | AD2: Tulung | AE2: Mundu | AF2: CV. H&B PUTRA MANDIRI | AG2: HPP0049 | AH2: 5 | AI2: VPA2 | AJ2: Aktif | AK2: 56 | AL2: Laki-laki | AM2: Sudah menikah | AN2: SD/Sederajat | AO2: Petani | AP2: 1 | AQ2: 0 | AR2: 0 | AS2: 0 | AT2: 0 | AU2: 0 | AV2: 0 | AW2: 0 | AY2: Petani Peternak | AZ2: 1 | BA2: 1 | BB2: 0 | BC2: 0 | BD2: 0 | BE2: 0 | BF2: 0 | BG2: 0 | BI2: Rp2.500.000 - Rp3.500.000 | BJ2: 1 | BK2: 2 | BL2: 1 | BM2: 0 | BN2: Milik sendiri | BO2: Permanen (dinding bata dan semen) | BP2: 1 | BQ2: 0 | BR2: 0 | BS2: 0 | BT2: 0 | BV2: Keramik/ubin | BW2: 0 | BX2: 0 | BY2: 1 | BZ2: 0 | CA2: 0 | CC2: Genting | CD2: 0 | CE2: 0 | CF2: 0 | CG2: 0 | CH2: 0 | CI2: 1 | CJ2: 0 | CL2: Ya | CM2: 2020 | CN2: Fixed-Dome (Kubah Tetap) | CO2: 6 m³ (4-5 ekor sapi, ±5 jam memasak/hari, ±50 kg | CP2: Anggota keluarga - laki-laki | CQ2: 0 | CR2: 0 | CS2: 0 | CT2: 0 | CU2: 1 | CV2: 0 | CW2: 0 | CX2: 0 | CY2: Anggota keluarga - laki-laki | CZ2: 1 | DA2: 0 | DB2: 0 | DD2: CPO atau pendamping | DE2: 0 | DF2: 0 | DG2: 1 | DH2: 0 | DJ2: CPO atau pendamping | DK2: 0 | DL2: 0 | DM2: 1 | DN2: 0 | DP2: 1 | DQ2: 0 | DR2: 0 | DV2: Ya | EI2: Tidak ada masalah | EJ2: 0 | EK2: 0 | EL2: 0 | EM2: 1 | EN2: 0 | EP2: Ya, cukup jelas dan mudah diikuti | EQ2: Pelatihan | ER2: CPO atau pendamping | ES2: 1 | ET2: 0 | EU2: 0 | EV2: 0 | EX2: Anggota keluarga - Laki-laki | EY2: 1 | EZ2: 0 | FA2: 0 | FC2: Setiap minggu | FE2: Mengetahui | FF2: Selalu (setiap hari) | FG2: Mengetahui | FH2: Sering (setiap minggu) | FI2: Mengetahui | FJ2: Selalu (setiap hari) | FK2: Mengetahui | FL2: Jarang (setiap bulan atau lebih) | FM2: Mengetahui | FN2: Sering (setiap minggu) | FO2: Mengetahui | FP2: Jarang (setiap bulan atau lebih) | FQ2: Mengetahui | FR2: Ya | FS2: Mengetahui | FT2: Ya, selalu | FU2: Laki-laki dewasa | FV2: 1 | FW2: 0 | FX2: 0 | FY2: 0 | FZ2: Memahami | GA2: CPO | GB2: 1 | GC2: 0 | GD2: 0 | GE2: 0 | GG2: Sering | GH2: Ya | GI2: Tetangga | GJ2: 1 | GK2: 0 | GL2: 0 | GM2: 0 | GO2: 10 | GP2: Penuh (100%) | GQ2: Kayu bakar LPG | GR2: 1 | GS2: 1 | GT2: 0 | GU2: 0 | GV2: 0 | GW2: 0 | GX2: 0 | GZ2: Ya | HA2: 15 | HB2: 150000 | HC2: 0 | HD2: 0 | HE2: 3 | HF2: 75000 | HG2: 3 | HH2: 25000 | HY2: 15 | HZ2: 150000 | IA2: 6 | IB2: 75000 | IK2: 50-65 kg | IL2: 3-5 jam | IM2: Ya | IN2: Tidak | IO2: Lebih bersih | IQ2: Tidak pernah | IZ2: Tidak pernah | JI2: Tidak pernah | JR2: Tidak pernah | KA2: Tidak pernah | KJ2: Tidak pernah | KS2: Cukup membaik | KT2: 2-4 kali | KU2: 0-1 kali | KV2: Laki-laki dewasa | KW2: 1 | KX2: 0 | KY2: 0 | KZ2: 0 | LA2: Cukup membaik | LB2: Cukup membaik | LC2: 0 | LD2: 0 | LE2: 0 | LF2: 0 | LG2: Ya | LH2: 200000 | LJ2: Kebutuhan rumah tangga | LK2: 0 | LL2: 0 | LM2: 0 | LN2: 0 | LO2: 1 | LP2: 0 | LQ2: 0 | LS2: 15 | LT2: 15 | LU2: 15 | LV2: 5 | LW2: 5 | LX2: 5 | LY2: 5 | LZ2: 5 | MA2: 5 | MB2: Tidak | MC2: 60 | MD2: 0 | ME2: 60 | MF2: 0 | MG2: 60 | MH2: 0 | MR2: kumpul keluarga | MT2: kumpul keluarga dan santai | MU2: Ya, mempekerjakan orang lain | MV2: Perawatan sistem biogas Pemasangan sistem biogas Produksi dan penjualan bioslurry | MW2: 1 | MX2: 1 | MY2: 1 | MZ2: 0 | NB2: 3 | NC2: Padat | ND2: 0 | NE2: 1 | NG2: 50 | NH2: 1 | NJ2: 1000 | NK2: 1 | NL2: Tidak | NM2: Kombinasi dana mandiri dan dana hibah | NN2: 3.000.001-5.000.000 | NO2: Yayasan Rumah Energi atau BIRU | NV2: Anggota keluarga - Laki-laki dewasa | NX2: Sedikit meningkat | NY2: 120 | NZ2: 15 | OA2: 0 | OB2: 30 | OC2: 10 | OD2: 0 | OE2: Lebih baik | OF2: Lebih baik (beda waktu memasak 5-30 menit, ATAU tidak lagi ada rasa/bau makanan yang berubah, ATAU alasan lainnya) | OG2: Ya | OH2: 5 | OI2: 0 | OJ2: 0 | OK2: 0 | OL2: 0 | OM2: 0 | ON2: 0 | OO2: 0 | OP2: =VLOOKUP(AG2,'BUS 2'!$G$1:$CU$424,2,0) -> Sapi pedaging | OQ2: =VLOOKUP(AG2,'BUS 2'!$G$1:$CU$424,3,0) -> 1 | OR2: =VLOOKUP(AG2,'BUS 2'!$G$1:$CU$424,4,0) -> 0 | OS2: =VLOOKUP(AG2,'BUS 2'!$G$1:$CU$424,5,0) -> 0 | OT2: =VLOOKUP(AG2,'BUS 2'!$G$1:$CU$424,6,0) -> 0 | OU2: =VLOOKUP(AG2,'BUS 2'!$G$1:$CU$424,7,0) -> 0 | OV2: =VLOOKUP(AG2,'BUS 2'!$G$1:$CU$424,8,0) -> 0 | OW2: =VLOOKUP(AG2,'BUS 2'!$G$1:$CU$424,9,0) -> 0 | OX2: =VLOOKUP(AG2,'BUS 2'!$G$1:$CU$424,10,0) -> 0 | OY2: =VLOOKUP(AG2,'BUS 2'!$G$1:$CU$424,11,0) -> 0 | OZ2: =VLOOKUP(AG2,'BUS 2'!$G$1:$CU$424,12,0) -> Sapi pedaging | PA2: =VLOOKUP(AG2,'BUS 2'!$G$1:$CU$424,13,0) -> 1 | PB2: =VLOOKUP(AG2,'BUS 2'!$G$1:$CU$424,14,0) -> 0 | PC2: =VLOOKUP(AG2,'BUS 2'!$G$1:$CU$424,15,0) -> 0 | PD2: =VLOOKUP(AG2,'BUS 2'!$G$1:$CU$424,16,0) -> 0 | PE2: =VLOOKUP(AG2,'BUS 2'!$G$1:$CU$424,17,0) -> 0 | PF2: =VLOOKUP(AG2,'BUS 2'!$G$1:$CU$424,18,0) -> 0 | PG2: =VLOOKUP(AG2,'BUS 2'!$G$1:$CU$424,19,0) -> 0 | PH2: =VLOOKUP(AG2,'BUS 2'!$G$1:$CU$424,20,0) -> 0 | PI2: =VLOOKUP(AG2,'BUS 2'!$G$1:$CU$424,21,0) -> 0 | PJ2: =VLOOKUP(AG2,'BUS 2'!$G$1:$CU$424,22,0) -> Tidak ada | PK2: =VLOOKUP(AG2,'BUS 2'!$G$1:$CU$424,23,0) -> 0 | PL2: =VLOOKUP(AG2,'BUS 2'!$G$1:$CU$424,24,0) -> 0 | PM2: =VLOOKUP(AG2,'BUS 2'!$G$1:$CU$424,25,0) -> 0 | PN2: =VLOOKUP(AG2,'BUS 2'!$G$1:$CU$424,26,0) -> 0 | PO2: =VLOOKUP(AG2,'BUS 2'!$G$1:$CU$424,27,0) -> 0 | PP2: =VLOOKUP(AG2,'BUS 2'!$G$1:$CU$424,28,0) -> 0 | PQ2: =VLOOKUP(AG2,'BUS 2'!$G$1:$CU$424,29,0) -> 0 | PR2: =VLOOKUP(AG2,'BUS 2'!$G$1:$CU$424,30,0) -> 0 | PS2: =VLOOKUP(AG2,'BUS 2'!$G$1:$CU$424,31,0) -> 1 | PT2: 1-Disebarkan ke lahan terbuka | PU2: 1 | PV2: 0 | PW2: 0 | PX2: 0 | PY2: 0 | PZ2: 0 | QA2: 1 | QB2: 0 | QC2: 0 | QD2: 0 | SY2: =VLOOKUP(AG2,'BUS 2'!$G$1:$CU$424,33,0) -> 5 | SZ2: =VLOOKUP(AG2,'BUS 2'!$G$1:$CU$424,34,0) | TA2: =VLOOKUP(AG2,'BUS 2'!$G$1:$CU$424,35,0) | TB2: =VLOOKUP(AG2,'BUS 2'!$G$1:$CU$424,36,0) | TC2: =VLOOKUP(AG2,'BUS 2'!$G$1:$CU$424,37,0) | TD2: =VLOOKUP(AG2,'BUS 2'!$G$1:$CU$424,38,0) | TE2: =VLOOKUP(AG2,'BUS 2'!$G$1:$CU$424,39,0) | TF2: =VLOOKUP(AG2,'BUS 2'!$G$1:$CU$424,40,0) | TG2: =VLOOKUP(AG2,'BUS 2'!$G$1:$CU$424,42,0) -> 5 | TH2: =VLOOKUP(AG2,'BUS 2'!$G$1:$CU$424,43,0) | TI2: =VLOOKUP(AG2,'BUS 2'!$G$1:$CU$424,44,0) | TJ2: =VLOOKUP(AG2,'BUS 2'!$G$1:$CU$424,45,0) | TK2: =VLOOKUP(AG2,'BUS 2'!$G$1:$CU$424,46,0) | TL2: =VLOOKUP(AG2,'BUS 2'!$G$1:$CU$424,47,0) | TM2: =VLOOKUP(AG2,'BUS 2'!$G$1:$CU$424,48,0) | TN2: =VLOOKUP(AG2,'BUS 2'!$G$1:$CU$424,49,0) | TO2: =VLOOKUP(AG2,'BUS 2'!$G$1:$CU$424,50,0) | TP2: =VLOOKUP(AG2,'BUS 2'!$G$1:$CU$424,51,0) | TQ2: =VLOOKUP(AG2,'BUS 2'!$G$1:$CU$424,52,0) | TR2: =VLOOKUP(AG2,'BUS 2'!$G$1:$CU$424,53,0) | TS2: =VLOOKUP(AG2,'BUS 2'!$G$1:$CU$424,54,0) | TT2: =VLOOKUP(AG2,'BUS 2'!$G$1:$CU$424,55,0) | TU2: =VLOOKUP(AG2,'BUS 2'!$G$1:$CU$424,56,0) | TV2: =VLOOKUP(AG2,'BUS 2'!$G$1:$CU$424,57,0) | TW2: =VLOOKUP(AG2,'BUS 2'!$G$1:$CU$424,58,0) | TX2: =VLOOKUP(AG2,'BUS 2'!$G$1:$CU$424,59,0) | TY2: =VLOOKUP(AG2,'BUS 2'!$G$1:$CU$424,60,0) | TZ2: =VLOOKUP(AG2,'BUS 2'!$G$1:$CU$424,61,0) | UA2: =VLOOKUP(AG2,'BUS 2'!$G$1:$CU$424,62,0) | UB2: =VLOOKUP(AG2,'BUS 2'!$G$1:$CU$424,63,0) | UC2: =VLOOKUP(AG2,'BUS 2'!$G$1:$CU$424,64,0) | UD2: =VLOOKUP(AG2,'BUS 2'!$G$1:$CU$424,65,0) | UE2: =VLOOKUP(AG2,'BUS 2'!$G$1:$CU$424,66,0) | UF2: =VLOOKUP(AG2,'BUS 2'!$G$1:$CU$424,67,0) | UG2: =VLOOKUP(AG2,'BUS 2'!$G$1:$CU$424,68,0) | UH2: =VLOOKUP(AG2,'BUS 2'!$G$1:$CU$424,69,0) | UI2: =VLOOKUP(AG2,'BUS 2'!$G$1:$CU$424,70,0) | UJ2: =VLOOKUP(AG2,'BUS 2'!$G$1:$CU$424,71,0) | UK2: =VLOOKUP(AG2,'BUS 2'!$G$1:$CU$424,72,0) | UL2: =VLOOKUP(AG2,'BUS 2'!$G$1:$CU$424,73,0) | UM2: =VLOOKUP(AG2,'BUS 2'!$G$1:$CU$424,74,0) | UN2: =VLOOKUP(AG2,'BUS 2'!$G$1:$CU$424,75,0) | UO2: =VLOOKUP(AG2,'BUS 2'!$G$1:$CU$424,76,0) | UP2: =VLOOKUP(AG2,'BUS 2'!$G$1:$CU$424,77,0) | UQ2: =VLOOKUP(AG2,'BUS 2'!$G$1:$CU$424,78,0) | UR2: =VLOOKUP(AG2,'BUS 2'!$G$1:$CU$424,79,0) | US2: =VLOOKUP(AG2,'BUS 2'!$G$1:$CU$424,80,0) | UT2: =VLOOKUP(AG2,'BUS 2'!$G$1:$CU$424,81,0) | UU2: Pemberian pakan di kandang | VC2: Cukup teratur (setiap minggu) | VK2: Sering (1 kali sehari) | VS2: 4-Disimpan dalam kotak bersekat | VT2: 0 | VU2: 0 | VV2: 0 | VW2: 0 | VX2: 0 | VY2: 0 | VZ2: 0 | WA2: 1 | WB2: 0 | WC2: 0 | WD2: 0 | WE2: 0 | ZV2: 2 | AAD2: Pakan kering (misal: konsentrat, silase, pelet) | AAL2: Ya | AAM2: Padat | AAN2: 1 | AAO2: 0 | AAQ2: 50 | AAR2: Ya | AAS2: Mengetahui | AAT2: Digunakan untuk pupuk di lahan pertanian sendiri | AAU2: 1 | AAV2: 0 | AAW2: 0 | AAX2: 0 | AAY2: 0 | AAZ2: 0 | ABA2: 0 | ABB2: Pupuk cair untuk tanaman | ABC2: 1 | ABD2: 0 | ABE2: 0 | ABF2: 0 | ABG2: 0 | ABQ2: Rumput pakan ternak | ABR2: Cukup (2 minggu sekali) | ABS2: 1000 | ABU2: 50 | ABV2: 50 | ABW2: NPK | ABY2: 40 | ABZ2: 7000 | ACA2: 20 | ACB2: 7000 | ACC2: 400 | ACD2: 500 | ACE2: Ya | ACF2: Cukup meningkat | ACG2: Cukup meningkat | ACH2: Cukup meningkat | ACT2: tidak | ACU2: Manfaat cukup signifikan, terasa di kehidupan sehari-hari | ACV2: Sama saja | ACW2: Anggota keluarga - Perempuan dewasa | ACX2: Setuju | ACY2: Anggota keluarga - Perempuan dewasa | ACZ2: 0 | ADA2: 1 | ADB2: 0 | ADC2: 0 | ADD2: Puas | ADE2: Puas | ADF2: Puas | ADG2: Puas | ADH2: Tidak | ADJ2: Cukup puas | ADU2: Menghubungi CPO atau pendamping | ADV2: 0 | ADW2: 0 | ADX2: 0 | ADY2: 0 | ADZ2: 1 | AEA2: 0 | AEB2: 0 | AEC2: 0 | AEE2: Laki-laki dewasa | AEG2: Menelepon atau WA langsung | AEI2: Tidak ada, sudah baik | AEJ2: Ya, selalu | AEK2: Pengurangan pengeluaran rumah tangga (bahan bakar minyak, pupuk, dll.) Lebih mudah mendapatkan energi Pasokan energi yang andal Memasak lebih cepat Lebih aman Pengurangan waktu dan tenaga Peningkatan kebersihan kandang ternak Pemanfaatan bio-slurry sebagai pupuk Dapur lebih bersih dan bebas asap Mendapatkan subsidi | AEL2: 1 | AEM2: 1 | AEN2: 1 | AEO2: 1 | AEP2: 1 | AEQ2: 1 | AER2: 1 | AES2: 1 | AET2: 1 | AEU2: 0 | AEV2: 1 | AEW2: 0 | AEY2: Mengurangi pengeluaran energi | AFA2: Yayasan Rumah Energi (YRE) | AFC2: WhatsApp Image 2026-02-03 at 14.09.29-12_41_24.jpeg | AFD2: https://kf.kobotoolbox.org/api/v2/assets/avstPQqLr3Ab3ZdcVTXZ6f/data/663251533/attachments/attBWKrQCnTMv7auhU422Uu3/ | AFE2: WhatsApp Image 2026-02-03 at 14.09.29 (1)-12_41_40.jpeg | AFF2: https://kf.kobotoolbox.org/api/v2/assets/avstPQqLr3Ab3ZdcVTXZ6f/data/663251533/attachments/attVVpXxpF3qsEnbUXJ79Htm/ | AFG2: marmanto / witono
A3: 46057 | B3: 46057 | C3: Marmanto | D3: Ngateno | E3: 6285602796486 | G3: -7.3547225 | H3: 110.33501 | J3: 4.72 | M3: -7.3547225 | N3: 110.33495 | P3: 4.72 | R3: Jawa Tengah | AC3: Klaten | AD3: Tulung | AE3: Mundu | AF3: LPTP | AG3: LPP0347 | AH3: 11 | AI3: VPA1 | AJ3: Tidak aktif | AK3: 59 | AL3: Laki-laki | AM3: Sudah menikah | AN3: SD/Sederajat | AO3: Petani Peternak | AP3: 1 | AQ3: 1 | AR3: 0 | AS3: 0 | AT3: 0 | AU3: 0 | AV3: 0 | AW3: 0 | AY3: Peternak | AZ3: 0 | BA3: 1 | BB3: 0 | BC3: 0 | BD3: 0 | BE3: 0 | BF3: 0 | BG3: 0 | BI3: Rp1.500.000 - Rp2.500.000 | BJ3: 3 | BK3: 1 | BL3: 0 | BM3: 0 | BN3: Milik sendiri | BO3: Permanen (dinding bata dan semen) | BP3: 1 | BQ3: 0 | BR3: 0 | BS3: 0 | BT3: 0 | BV3: Keramik/ubin | BW3: 0 | BX3: 0 | BY3: 1 | BZ3: 0 | CA3: 0 | CC3: Genting | CD3: 0 | CE3: 0 | CF3: 0 | CG3: 0 | CH3: 0 | CI3: 1 | CJ3: 0 | CL3: Ya | CM3: 2014 | CN3: Fixed-Dome (Kubah Tetap) | CO3: 6 m³ (4-5 ekor sapi, ±5 jam memasak/hari, ±50 kg | CP3: Anggota keluarga - laki-laki | CQ3: 0 | CR3: 0 | CS3: 0 | CT3: 0 | CU3: 1 | CV3: 0 | CW3: 0 | CX3: 0 | CY3: Anggota keluarga - laki-laki | CZ3: 1 | DA3: 0 | DB3: 0 | DD3: Anggota keluarga - laki-laki CPO atau pendamping | DE3: 1 | DF3: 0 | DG3: 1 | DH3: 0 | DJ3: CPO atau pendamping | DK3: 0 | DL3: 0 | DM3: 1 | DN3: 0 | DP3: 1 | DQ3: 0 | DR3: 0 | DV3: Tidak berfungsi sama sekali | DW3: >1 tahun yang lalu | DX3: Tidak ada pihak yang mengelola/dapat memperbaiki sistem biogas | EI3: Kurangnya dukungan atau pemantauan dari pemerintah atau CPO Keterbatasan akses terhadap informasi atau pelatihan terkait biogas | EJ3: 0 | EK3: 1 | EL3: 1 | EM3: 0 | EN3: 0 | EP3: Ya, cukup jelas dan mudah diikuti | EQ3: Pelatihan | ER3: CPO atau pendamping | ES3: 1 | ET3: 0 | EU3: 0 | EV3: 0 | EX3: Anggota keluarga - Laki-laki | EY3: 1 | EZ3: 0 | FA3: 0 | FC3: Jarang sekali | FE3: Mengetahui | FF3: Selalu (setiap hari) | FG3: Mengetahui | FH3: Sering (setiap minggu) | FI3: Mengetahui | FJ3: Sering (setiap minggu) | FK3: Mengetahui | FL3: Jarang (setiap bulan atau lebih) | FM3: Mengetahui | FN3: Cukup sering (2 minggu sekali) | FO3: Mengetahui | FP3: Jarang (setiap bulan atau lebih) | FQ3: Mengetahui | FR3: Ya | FS3: Mengetahui | FT3: Ya, selalu | FU3: Laki-laki dewasa | FV3: 1 | FW3: 0 | FX3: 0 | FY3: 0 | FZ3: Cukup memahami | GA3: CPO | GB3: 1 | GC3: 0 | GD3: 0 | GE3: 0 | GG3: Sering | GH3: Tidak | GP3: Penuh (100%) | GQ3: Kayu bakar LPG | GR3: 1 | GS3: 1 | GT3: 0 | GU3: 0 | GV3: 0 | GW3: 0 | GX3: 0 | GZ3: Ya | HA3: 15 | HB3: 150000 | HC3: 0 | HD3: 0 | HE3: 12 | HF3: 100000 | HG3: 0 | HH3: 0 | HY3: 15 | HZ3: 150000 | IA3: 0 | IB3: 0 | IK3: 50-65 kg | IL3: 3-5 jam | IM3: Ya | IN3: Tidak | IO3: Lebih bersih | IQ3: Tidak pernah | IZ3: Tidak pernah | JI3: Tidak pernah | JR3: Tidak pernah | KA3: Tidak pernah | KJ3: Tidak pernah | KS3: Tidak ada perubahan | KT3: 0-1 kali | KU3: 0-1 kali | KV3: Laki-laki dewasa | KW3: 1 | KX3: 0 | KY3: 0 | KZ3: 0 | LA3: Tidak ada perubahan | LB3: Cukup membaik | LC3: 0 | LD3: 0 | LE3: 0 | LF3: 0 | LG3: Tidak | LI3: 100000 | LJ3: Kebutuhan rumah tangga | LK3: 0 | LL3: 0 | LM3: 0 | LN3: 0 | LO3: 1 | LP3: 0 | LQ3: 0 | LS3: 30 | LT3: 30 | LU3: 0 | LV3: 5 | LW3: 5 | LX3: 0 | LY3: 5 | LZ3: 5 | MA3: 0 | MB3: Ya | MC3: 30 | MD3: 20 | ME3: 30 | MF3: 20 | MG3: 30 | MH3: 15 | MI3: Istirahat | MJ3: 0 | MK3: 0 | ML3: 1 | MM3: 0 | MN3: 0 | MO3: 0 | MR3: untuk santai | MT3: untukm kiumpul keluarga santai | MU3: Ya, mempekerjakan orang lain | MV3: Perawatan sistem biogas | MW3: 1 | MX3: 0 | MY3: 0 | MZ3: 0 | NB3: 3 | NL3: Tidak | NM3: Kombinasi dana mandiri dan dana hibah | NN3: 3.000.001-5.000.000 | NO3: Yayasan Rumah Energi atau BIRU | NV3: Anggota keluarga - Laki-laki dewasa | NX3: Sama saja | NY3: 60 | NZ3: 30 | OA3: 0 | OB3: 15 | OC3: 15 | OD3: 0 | OE3: Lebih baik | OF3: Lebih baik (beda waktu memasak 5-30 menit, ATAU tidak lagi ada rasa/bau makanan yang berubah, ATAU alasan lainnya) | OG3: Ya | OH3: 2 | OI3: 0 | OJ3: 0 | OK3: 0 | OL3: 0 | OM3: 0 | ON3: 0 | OO3: 0 | OP3: =VLOOKUP(AG3,'BUS 2'!$G$1:$CU$424,2,0) -> Sapi pedaging | OQ3: =VLOOKUP(AG3,'BUS 2'!$G$1:$CU$424,3,0) -> 1 | OR3: =VLOOKUP(AG3,'BUS 2'!$G$1:$CU$424,4,0) -> 0 | OS3: =VLOOKUP(AG3,'BUS 2'!$G$1:$CU$424,5,0) -> 0 | OT3: =VLOOKUP(AG3,'BUS 2'!$G$1:$CU$424,6,0) -> 0 | OU3: =VLOOKUP(AG3,'BUS 2'!$G$1:$CU$424,7,0) -> 0 | OV3: =VLOOKUP(AG3,'BUS 2'!$G$1:$CU$424,8,0) -> 0 | OW3: =VLOOKUP(AG3,'BUS 2'!$G$1:$CU$424,9,0) -> 0 | OX3: =VLOOKUP(AG3,'BUS 2'!$G$1:$CU$424,10,0) -> 0 | OY3: =VLOOKUP(AG3,'BUS 2'!$G$1:$CU$424,11,0) -> 0 | OZ3: =VLOOKUP(AG3,'BUS 2'!$G$1:$CU$424,12,0) -> Sapi pedaging | PA3: =VLOOKUP(AG3,'BUS 2'!$G$1:$CU$424,13,0) -> 1 | PB3: =VLOOKUP(AG3,'BUS 2'!$G$1:$CU$424,14,0) -> 0 | PC3: =VLOOKUP(AG3,'BUS 2'!$G$1:$CU$424,15,0) -> 0 | PD3: =VLOOKUP(AG3,'BUS 2'!$G$1:$CU$424,16,0) -> 0 | PE3: =VLOOKUP(AG3,'BUS 2'!$G$1:$CU$424,17,0) -> 0 | PF3: =VLOOKUP(AG3,'BUS 2'!$G$1:$CU$424,18,0) -> 0 | PG3: =VLOOKUP(AG3,'BUS 2'!$G$1:$CU$424,19,0) -> 0 | PH3: =VLOOKUP(AG3,'BUS 2'!$G$1:$CU$424,20,0) -> 0 | PI3: =VLOOKUP(AG3,'BUS 2'!$G$1:$CU$424,21,0) -> 0 | PJ3: =VLOOKUP(AG3,'BUS 2'!$G$1:$CU$424,22,0) -> Tidak ada | PK3: =VLOOKUP(AG3,'BUS 2'!$G$1:$CU$424,23,0) -> 0 | PL3: =VLOOKUP(AG3,'BUS 2'!$G$1:$CU$424,24,0) -> 0 | PM3: =VLOOKUP(AG3,'BUS 2'!$G$1:$CU$424,25,0) -> 0 | PN3: =VLOOKUP(AG3,'BUS 2'!$G$1:$CU$424,26,0) -> 0 | PO3: =VLOOKUP(AG3,'BUS 2'!$G$1:$CU$424,27,0) -> 0 | PP3: =VLOOKUP(AG3,'BUS 2'!$G$1:$CU$424,28,0) -> 0 | PQ3: =VLOOKUP(AG3,'BUS 2'!$G$1:$CU$424,29,0) -> 0 | PR3: =VLOOKUP(AG3,'BUS 2'!$G$1:$CU$424,30,0) -> 0 | PS3: =VLOOKUP(AG3,'BUS 2'!$G$1:$CU$424,31,0) -> 1 | PT3: 1-Disebarkan ke lahan terbuka | PU3: 1 | PV3: 0 | PW3: 0 | PX3: 0 | PY3: 0 | PZ3: 0 | QA3: 1 | QB3: 0 | QC3: 0 | QD3: 0 | SY3: =VLOOKUP(AG3,'BUS 2'!$G$1:$CU$424,33,0) -> 3 | SZ3: =VLOOKUP(AG3,'BUS 2'!$G$1:$CU$424,34,0) | TA3: =VLOOKUP(AG3,'BUS 2'!$G$1:$CU$424,35,0) | TB3: =VLOOKUP(AG3,'BUS 2'!$G$1:$CU$424,36,0) | TC3: =VLOOKUP(AG3,'BUS 2'!$G$1:$CU$424,37,0) | TD3: =VLOOKUP(AG3,'BUS 2'!$G$1:$CU$424,38,0) | TE3: =VLOOKUP(AG3,'BUS 2'!$G$1:$CU$424,39,0) | TF3: =VLOOKUP(AG3,'BUS 2'!$G$1:$CU$424,40,0) | TG3: =VLOOKUP(AG3,'BUS 2'!$G$1:$CU$424,42,0) -> 3 | TH3: =VLOOKUP(AG3,'BUS 2'!$G$1:$CU$424,43,0) | TI3: =VLOOKUP(AG3,'BUS 2'!$G$1:$CU$424,44,0) | TJ3: =VLOOKUP(AG3,'BUS 2'!$G$1:$CU$424,45,0) | TK3: =VLOOKUP(AG3,'BUS 2'!$G$1:$CU$424,46,0) | TL3: =VLOOKUP(AG3,'BUS 2'!$G$1:$CU$424,47,0) | TM3: =VLOOKUP(AG3,'BUS 2'!$G$1:$CU$424,48,0) | TN3: =VLOOKUP(AG3,'BUS 2'!$G$1:$CU$424,49,0) | TO3: =VLOOKUP(AG3,'BUS 2'!$G$1:$CU$424,50,0) | TP3: =VLOOKUP(AG3,'BUS 2'!$G$1:$CU$424,51,0) | TQ3: =VLOOKUP(AG3,'BUS 2'!$G$1:$CU$424,52,0) | TR3: =VLOOKUP(AG3,'BUS 2'!$G$1:$CU$424,53,0) | TS3: =VLOOKUP(AG3,'BUS 2'!$G$1:$CU$424,54,0) | TT3: =VLOOKUP(AG3,'BUS 2'!$G$1:$CU$424,55,0) | TU3: =VLOOKUP(AG3,'BUS 2'!$G$1:$CU$424,56,0) | TV3: =VLOOKUP(AG3,'BUS 2'!$G$1:$CU$424,57,0) | TW3: =VLOOKUP(AG3,'BUS 2'!$G$1:$CU$424,58,0) | TX3: =VLOOKUP(AG3,'BUS 2'!$G$1:$CU$424,59,0) | TY3: =VLOOKUP(AG3,'BUS 2'!$G$1:$CU$424,60,0) | TZ3: =VLOOKUP(AG3,'BUS 2'!$G$1:$CU$424,61,0) | UA3: =VLOOKUP(AG3,'BUS 2'!$G$1:$CU$424,62,0) | UB3: =VLOOKUP(AG3,'BUS 2'!$G$1:$CU$424,63,0) | UC3: =VLOOKUP(AG3,'BUS 2'!$G$1:$CU$424,64,0) | UD3: =VLOOKUP(AG3,'BUS 2'!$G$1:$CU$424,65,0) | UE3: =VLOOKUP(AG3,'BUS 2'!$G$1:$CU$424,66,0) | UF3: =VLOOKUP(AG3,'BUS 2'!$G$1:$CU$424,67,0) | UG3: =VLOOKUP(AG3,'BUS 2'!$G$1:$CU$424,68,0) | UH3: =VLOOKUP(AG3,'BUS 2'!$G$1:$CU$424,69,0) | UI3: =VLOOKUP(AG3,'BUS 2'!$G$1:$CU$424,70,0) | UJ3: =VLOOKUP(AG3,'BUS 2'!$G$1:$CU$424,71,0) | UK3: =VLOOKUP(AG3,'BUS 2'!$G$1:$CU$424,72,0) | UL3: =VLOOKUP(AG3,'BUS 2'!$G$1:$CU$424,73,0) | UM3: =VLOOKUP(AG3,'BUS 2'!$G$1:$CU$424,74,0) | UN3: =VLOOKUP(AG3,'BUS 2'!$G$1:$CU$424,75,0) | UO3: =VLOOKUP(AG3,'BUS 2'!$G$1:$CU$424,76,0) | UP3: =VLOOKUP(AG3,'BUS 2'!$G$1:$CU$424,77,0) | UQ3: =VLOOKUP(AG3,'BUS 2'!$G$1:$CU$424,78,0) | UR3: =VLOOKUP(AG3,'BUS 2'!$G$1:$CU$424,79,0) | US3: =VLOOKUP(AG3,'BUS 2'!$G$1:$CU$424,80,0) | UT3: =VLOOKUP(AG3,'BUS 2'!$G$1:$CU$424,81,0) | UU3: Pemberian pakan di kandang | VC3: Sangat teratur (setiap hari) | VK3: Sering (1 kali sehari) | VS3: 3-Disimpan terbuka (dry lot) | VT3: 0 | VU3: 0 | VV3: 0 | VW3: 0 | VX3: 0 | VY3: 0 | VZ3: 1 | WA3: 0 | WB3: 0 | WC3: 0 | WD3: 0 | WE3: 0 | ZV3: 2 | AAD3: Pakan kering (misal: konsentrat, silase, pelet) | AAL3: Tidak | AAR3: Ya | AAS3: Mengetahui | AAT3: Dibuang ke lahan sekitar kandang - yg ditanami tanaman Diberikan gratis ke orang lain | AAU3: 0 | AAV3: 0 | AAW3: 0 | AAX3: 1 | AAY3: 1 | AAZ3: 0 | ABA3: 0 | ABQ3: Rumput | ABR3: Jarang (1 bulan sekali) | ABT3: 1000 | ACK3: Ladang/sawah terlalu jauh, sulit untuk mengangkut ke sana | ACL3: 0 | ACM3: 0 | ACN3: 0 | ACO3: 1 | ACP3: 0 | ACQ3: 0 | ACR3: 0 | ACT3: kotoran unggas | ACU3: Manfaat cukup signifikan, terasa di kehidupan sehari-hari | ACV3: Berkurang | ACW3: Anggota keluarga - Perempuan dewasa | ACX3: Netral/tidak tahu | ACY3: Anggota keluarga - Perempuan dewasa | ACZ3: 0 | ADA3: 1 | ADB3: 0 | ADC3: 0 | ADD3: Cukup puas | ADE3: Cukup puas | ADF3: Cukup puas | ADG3: Cukup puas | ADH3: Ya | ADI3: perlu perbaikan total karena sudah hampir 1 tahun tidak hidup | ADJ3: Cukup puas | ADU3: Menghubungi CPO atau pendamping | ADV3: 0 | ADW3: 0 | ADX3: 0 | ADY3: 0 | ADZ3: 1 | AEA3: 0 | AEB3: 0 | AEC3: 0 | AEE3: Laki-laki dewasa | AEG3: Menelepon atau WA langsung | AEI3: Lebih kepada perawatan oleh user | AEJ3: Kadang-kadang | AEK3: Pengurangan pengeluaran rumah tangga (bahan bakar minyak, pupuk, dll.) Lebih mudah mendapatkan energi Pasokan energi yang andal Memasak lebih cepat Lebih aman Pengurangan waktu dan tenaga Peningkatan kebersihan kandang ternak Dapur lebih bersih dan bebas asap Mendapatkan subsidi | AEL3: 1 | AEM3: 1 | AEN3: 1 | AEO3: 1 | AEP3: 1 | AEQ3: 1 | AER3: 1 | AES3: 0 | AET3: 1 | AEU3: 0 | AEV3: 1 | AEW3: 0 | AEY3: Mengurangi pengeluaran energi | AFA3: Yayasan Rumah Energi (YRE) | AFC3: WhatsApp Image 2026-02-03 at 14.10.08 (1)-14_0_32.jpeg | AFD3: https://kf.kobotoolbox.org/api/v2/assets/avstPQqLr3Ab3ZdcVTXZ6f/data/663301002/attachments/attg4kP2W6ZMftBXbbYhXKqZ/ | AFE3: WhatsApp Image 2026-02-03 at 14.10.08-14_0_54.jpeg | AFF3: https://kf.kobotoolbox.org/api/v2/assets/avstPQqLr3Ab3ZdcVTXZ6f/data/663301002/attachments/attN3Lf5vcXsmwf6Lre4jnYH/ | AFG3: marmanto / witono
A4: 46057 | B4: 46057 | C4: Marmanto | D4: Sunaryo | E4: 6282279139177 | G4: -7.3525908 | H4: 110.3417 | J4: 4.95 | M4: -7.3526148 | N4: 110.34173 | P4: 4.93 | R4: Jawa Tengah | AC4: Klaten | AD4: Tulung | AE4: Mundu | AF4: LPTP | AG4: LPP0318 | AH4: 12 | AI4: VPA1 | AJ4: Tidak aktif | AK4: 60 | AL4: Laki-laki | AM4: Sudah menikah | AN4: SD/Sederajat | AO4: Petani | AP4: 1 | AQ4: 0 | AR4: 0 | AS4: 0 | AT4: 0 | AU4: 0 | AV4: 0 | AW4: 0 | AY4: Peternak | AZ4: 0 | BA4: 1 | BB4: 0 | BC4: 0 | BD4: 0 | BE4: 0 | BF4: 0 | BG4: 0 | BI4: Rp1.500.000 - Rp2.500.000 | BJ4: 3 | BK4: 1 | BL4: 0 | BM4: 0 | BN4: Milik sendiri | BO4: Permanen (dinding bata dan semen) | BP4: 1 | BQ4: 0 | BR4: 0 | BS4: 0 | BT4: 0 | BV4: Keramik/ubin | BW4: 0 | BX4: 0 | BY4: 1 | BZ4: 0 | CA4: 0 | CC4: Genting | CD4: 0 | CE4: 0 | CF4: 0 | CG4: 0 | CH4: 0 | CI4: 1 | CJ4: 0 | CL4: Ya | CM4: 2014 | CN4: Fixed-Dome (Kubah Tetap) | CO4: 6 m³ (4-5 ekor sapi, ±5 jam memasak/hari, ±50 kg | CP4: Anggota keluarga - laki-laki | CQ4: 0 | CR4: 0 | CS4: 0 | CT4: 0 | CU4: 1 | CV4: 0 | CW4: 0 | CX4: 0 | CY4: Anggota keluarga - laki-laki | CZ4: 1 | DA4: 0 | DB4: 0 | DD4: Anggota keluarga - laki-laki CPO atau pendamping | DE4: 1 | DF4: 0 | DG4: 1 | DH4: 0 | DJ4: Anggota keluarga - laki-laki CPO atau pendamping | DK4: 1 | DL4: 0 | DM4: 1 | DN4: 0 | DP4: 1 | DQ4: 0 | DR4: 0 | DV4: Tidak berfungsi sama sekali | DW4: >1 tahun yang lalu | DX4: Tidak ada pihak yang mengelola/dapat memperbaiki sistem biogas | EI4: Lainnya | EJ4: 0 | EK4: 0 | EL4: 0 | EM4: 0 | EN4: 1 | EO4: Yang memelihara bertumpu pada kepala keluarga yang sudah semakin tua dan mau diteruskan anaknya sudah rusak dan sapi pernah dijual dan beli | EP4: Ya, cukup jelas dan mudah diikuti | EQ4: Pelatihan | ER4: CPO atau pendamping | ES4: 1 | ET4: 0 | EU4: 0 | EV4: 0 | EX4: Anggota keluarga - Laki-laki | EY4: 1 | EZ4: 0 | FA4: 0 | FC4: Setiap minggu | FE4: Mengetahui | FF4: Selalu (setiap hari) | FG4: Mengetahui | FH4: Sering (setiap minggu) | FI4: Mengetahui | FJ4: Sering (setiap minggu) | FK4: Mengetahui | FL4: Sering (setiap minggu) | FM4: Mengetahui | FN4: Sering (setiap minggu) | FO4: Mengetahui | FP4: Sering (setiap minggu) | FQ4: Mengetahui | FR4: Ya | FS4: Mengetahui | FT4: Ya, selalu | FU4: Laki-laki dewasa | FV4: 1 | FW4: 0 | FX4: 0 | FY4: 0 | FZ4: Memahami | GA4: CPO | GB4: 1 | GC4: 0 | GD4: 0 | GE4: 0 | GG4: Sering | GH4: Ya | GI4: Tetangga | GJ4: 1 | GK4: 0 | GL4: 0 | GM4: 0 | GO4: 10 | GP4: Penuh (100%) | GQ4: Kayu bakar LPG | GR4: 1 | GS4: 1 | GT4: 0 | GU4: 0 | GV4: 0 | GW4: 0 | GX4: 0 | GZ4: Ya | HA4: 200 | HB4: 200000 | HC4: 100 | HD4: 100000 | HE4: 9 | HF4: 75000 | HG4: 3 | HH4: 25000 | HY4: 100 | HZ4: 100000 | IA4: 9 | IB4: 50000 | IK4: 30-50 kg | IL4: 3-5 jam | IM4: Ya | IN4: Tidak | IO4: Lebih bersih | IQ4: Tidak pernah | IZ4: Tidak pernah | JI4: Tidak pernah | JR4: Tidak pernah | KA4: Tidak pernah | KJ4: Tidak pernah | KS4: Cukup membaik | KT4: 0-1 kali | KU4: 0-1 kali | KV4: Laki-laki dewasa | KW4: 1 | KX4: 0 | KY4: 0 | KZ4: 0 | LA4: Cukup membaik | LB4: Cukup membaik | LC4: 3 | LD4: 3 | LE4: 0 | LF4: 3 | LG4: Ya | LH4: 75000 | LJ4: Kebutuhan rumah tangga | LK4: 0 | LL4: 0 | LM4: 0 | LN4: 0 | LO4: 1 | LP4: 0 | LQ4: 0 | LS4: 10 | LT4: 15 | LU4: 0 | LV4: 5 | LW4: 5 | LX4: 0 | LY4: 5 | LZ4: 5 | MA4: 0 | MB4: Ya | MC4: 30 | MD4: 30 | ME4: 30 | MF4: 20 | MG4: 30 | MH4: 20 | MI4: Istirahat | MJ4: 0 | MK4: 0 | ML4: 1 | MM4: 0 | MN4: 0 | MO4: 0 | MR4: santai | MT4: kumpul keluarga | MU4: Tidak | NL4: Tidak | NM4: Kombinasi dana mandiri dan dana hibah | NN4: 3.000.001-5.000.000 | NO4: Program yayasan/NGO | NV4: Anggota keluarga - Laki-laki dewasa | NX4: Sedikit meningkat | NY4: 45 | NZ4: 20 | OA4: 0 | OB4: 15 | OC4: 15 | OD4: 0 | OE4: Lebih baik | OF4: Lebih baik (beda waktu memasak 5-30 menit, ATAU tidak lagi ada rasa/bau makanan yang berubah, ATAU alasan lainnya) | OG4: Ya | OH4: 5 | OI4: 0 | OJ4: 0 | OK4: 0 | OL4: 0 | OM4: 0 | ON4: 0 | OO4: 0 | OP4: =VLOOKUP(AG4,'BUS 2'!$G$1:$CU$424,2,0) -> Sapi pedaging | OQ4: =VLOOKUP(AG4,'BUS 2'!$G$1:$CU$424,3,0) -> 1 | OR4: =VLOOKUP(AG4,'BUS 2'!$G$1:$CU$424,4,0) -> 0 | OS4: =VLOOKUP(AG4,'BUS 2'!$G$1:$CU$424,5,0) -> 0 | OT4: =VLOOKUP(AG4,'BUS 2'!$G$1:$CU$424,6,0) -> 0 | OU4: =VLOOKUP(AG4,'BUS 2'!$G$1:$CU$424,7,0) -> 0 | OV4: =VLOOKUP(AG4,'BUS 2'!$G$1:$CU$424,8,0) -> 0 | OW4: =VLOOKUP(AG4,'BUS 2'!$G$1:$CU$424,9,0) -> 0 | OX4: =VLOOKUP(AG4,'BUS 2'!$G$1:$CU$424,10,0) -> 0 | OY4: =VLOOKUP(AG4,'BUS 2'!$G$1:$CU$424,11,0) -> 0 | OZ4: =VLOOKUP(AG4,'BUS 2'!$G$1:$CU$424,12,0) -> Sapi pedaging | PA4: =VLOOKUP(AG4,'BUS 2'!$G$1:$CU$424,13,0) -> 1 | PB4: =VLOOKUP(AG4,'BUS 2'!$G$1:$CU$424,14,0) -> 0 | PC4: =VLOOKUP(AG4,'BUS 2'!$G$1:$CU$424,15,0) -> 0 | PD4: =VLOOKUP(AG4,'BUS 2'!$G$1:$CU$424,16,0) -> 0 | PE4: =VLOOKUP(AG4,'BUS 2'!$G$1:$CU$424,17,0) -> 0 | PF4: =VLOOKUP(AG4,'BUS 2'!$G$1:$CU$424,18,0) -> 0 | PG4: =VLOOKUP(AG4,'BUS 2'!$G$1:$CU$424,19,0) -> 0 | PH4: =VLOOKUP(AG4,'BUS 2'!$G$1:$CU$424,20,0) -> 0 | PI4: =VLOOKUP(AG4,'BUS 2'!$G$1:$CU$424,21,0) -> 0 | PJ4: =VLOOKUP(AG4,'BUS 2'!$G$1:$CU$424,22,0) -> Tidak ada | PK4: =VLOOKUP(AG4,'BUS 2'!$G$1:$CU$424,23,0) -> 0 | PL4: =VLOOKUP(AG4,'BUS 2'!$G$1:$CU$424,24,0) -> 0 | PM4: =VLOOKUP(AG4,'BUS 2'!$G$1:$CU$424,25,0) -> 0 | PN4: =VLOOKUP(AG4,'BUS 2'!$G$1:$CU$424,26,0) -> 0 | PO4: =VLOOKUP(AG4,'BUS 2'!$G$1:$CU$424,27,0) -> 0 | PP4: =VLOOKUP(AG4,'BUS 2'!$G$1:$CU$424,28,0) -> 0 | PQ4: =VLOOKUP(AG4,'BUS 2'!$G$1:$CU$424,29,0) -> 0 | PR4: =VLOOKUP(AG4,'BUS 2'!$G$1:$CU$424,30,0) -> 0 | PS4: =VLOOKUP(AG4,'BUS 2'!$G$1:$CU$424,31,0) -> 1 | PT4: 1-Disebarkan ke lahan terbuka | PU4: 1 | PV4: 0 | PW4: 0 | PX4: 0 | PY4: 0 | PZ4: 0 | QA4: 1 | QB4: 0 | QC4: 0 | QD4: 0 | SY4: =VLOOKUP(AG4,'BUS 2'!$G$1:$CU$424,33,0) -> 5 | SZ4: =VLOOKUP(AG4,'BUS 2'!$G$1:$CU$424,34,0) | TA4: =VLOOKUP(AG4,'BUS 2'!$G$1:$CU$424,35,0) | TB4: =VLOOKUP(AG4,'BUS 2'!$G$1:$CU$424,36,0) | TC4: =VLOOKUP(AG4,'BUS 2'!$G$1:$CU$424,37,0) | TD4: =VLOOKUP(AG4,'BUS 2'!$G$1:$CU$424,38,0) | TE4: =VLOOKUP(AG4,'BUS 2'!$G$1:$CU$424,39,0) | TF4: =VLOOKUP(AG4,'BUS 2'!$G$1:$CU$424,40,0) | TG4: =VLOOKUP(AG4,'BUS 2'!$G$1:$CU$424,42,0) -> 5 | TH4: =VLOOKUP(AG4,'BUS 2'!$G$1:$CU$424,43,0) | TI4: =VLOOKUP(AG4,'BUS 2'!$G$1:$CU$424,44,0) | TJ4: =VLOOKUP(AG4,'BUS 2'!$G$1:$CU$424,45,0) | TK4: =VLOOKUP(AG4,'BUS 2'!$G$1:$CU$424,46,0) | TL4: =VLOOKUP(AG4,'BUS 2'!$G$1:$CU$424,47,0) | TM4: =VLOOKUP(AG4,'BUS 2'!$G$1:$CU$424,48,0) | TN4: =VLOOKUP(AG4,'BUS 2'!$G$1:$CU$424,49,0) | TO4: =VLOOKUP(AG4,'BUS 2'!$G$1:$CU$424,50,0) | TP4: =VLOOKUP(AG4,'BUS 2'!$G$1:$CU$424,51,0) | TQ4: =VLOOKUP(AG4,'BUS 2'!$G$1:$CU$424,52,0) | TR4: =VLOOKUP(AG4,'BUS 2'!$G$1:$CU$424,53,0) | TS4: =VLOOKUP(AG4,'BUS 2'!$G$1:$CU$424,54,0) | TT4: =VLOOKUP(AG4,'BUS 2'!$G$1:$CU$424,55,0) | TU4: =VLOOKUP(AG4,'BUS 2'!$G$1:$CU$424,56,0) | TV4: =VLOOKUP(AG4,'BUS 2'!$G$1:$CU$424,57,0) | TW4: =VLOOKUP(AG4,'BUS 2'!$G$1:$CU$424,58,0) | TX4: =VLOOKUP(AG4,'BUS 2'!$G$1:$CU$424,59,0) | TY4: =VLOOKUP(AG4,'BUS 2'!$G$1:$CU$424,60,0) | TZ4: =VLOOKUP(AG4,'BUS 2'!$G$1:$CU$424,61,0) | UA4: =VLOOKUP(AG4,'BUS 2'!$G$1:$CU$424,62,0) | UB4: =VLOOKUP(AG4,'BUS 2'!$G$1:$CU$424,63,0) | UC4: =VLOOKUP(AG4,'BUS 2'!$G$1:$CU$424,64,0) | UD4: =VLOOKUP(AG4,'BUS 2'!$G$1:$CU$424,65,0) | UE4: =VLOOKUP(AG4,'BUS 2'!$G$1:$CU$424,66,0) | UF4: =VLOOKUP(AG4,'BUS 2'!$G$1:$CU$424,67,0) | UG4: =VLOOKUP(AG4,'BUS 2'!$G$1:$CU$424,68,0) | UH4: =VLOOKUP(AG4,'BUS 2'!$G$1:$CU$424,69,0) | UI4: =VLOOKUP(AG4,'BUS 2'!$G$1:$CU$424,70,0) | UJ4: =VLOOKUP(AG4,'BUS 2'!$G$1:$CU$424,71,0) | UK4: =VLOOKUP(AG4,'BUS 2'!$G$1:$CU$424,72,0) | UL4: =VLOOKUP(AG4,'BUS 2'!$G$1:$CU$424,73,0) | UM4: =VLOOKUP(AG4,'BUS 2'!$G$1:$CU$424,74,0) | UN4: =VLOOKUP(AG4,'BUS 2'!$G$1:$CU$424,75,0) | UO4: =VLOOKUP(AG4,'BUS 2'!$G$1:$CU$424,76,0) | UP4: =VLOOKUP(AG4,'BUS 2'!$G$1:$CU$424,77,0) | UQ4: =VLOOKUP(AG4,'BUS 2'!$G$1:$CU$424,78,0) | UR4: =VLOOKUP(AG4,'BUS 2'!$G$1:$CU$424,79,0) | US4: =VLOOKUP(AG4,'BUS 2'!$G$1:$CU$424,80,0) | UT4: =VLOOKUP(AG4,'BUS 2'!$G$1:$CU$424,81,0) | UU4: Pemberian pakan di kandang | VC4: Sangat teratur (setiap hari) | VK4: Sering (1 kali sehari) | VS4: 4-Disimpan dalam kotak bersekat | VT4: 0 | VU4: 0 | VV4: 0 | VW4: 0 | VX4: 0 | VY4: 0 | VZ4: 0 | WA4: 1 | WB4: 0 | WC4: 0 | WD4: 0 | WE4: 0 | ZV4: 2 | AAD4: Pakan kering (misal: konsentrat, silase, pelet) | AAL4: Tidak | AAR4: Ya | AAS4: Mengetahui | AAT4: Digunakan untuk kegiatan peternakan sendiri Diberikan gratis ke orang lain | AAU4: 0 | AAV4: 1 | AAW4: 0 | AAX4: 0 | AAY4: 1 | AAZ4: 0 | ABA4: 0 | ABI4: Lainnya | ABJ4: 0 | ABK4: 0 | ABL4: 0 | ABM4: 0 | ABN4: 1 | ABO4: Pupuk | ACI4: Cukup meningkat | ACJ4: Tidak ada perubahan | ACK4: Tidak punya waktu mengumpulkannya Ladang/sawah terlalu jauh, sulit untuk mengangkut ke sana | ACL4: 0 | ACM4: 0 | ACN4: 1 | ACO4: 1 | ACP4: 0 | ACQ4: 0 | ACR4: 0 | ACT4: tidak | ACU4: Manfaat cukup signifikan, terasa di kehidupan sehari-hari | ACV4: Sama saja | ACW4: Anggota keluarga - Perempuan dewasa | ACX4: Netral/tidak tahu | ACY4: Anggota keluarga - Perempuan dewasa | ACZ4: 0 | ADA4: 1 | ADB4: 0 | ADC4: 0 | ADD4: Cukup puas | ADE4: Cukup puas | ADF4: Cukup puas | ADG4: Cukup puas | ADH4: Ya | ADI4: perlu penggantian kompor yang berkjarat dan pengurasan ulang | ADJ4: Cukup puas | ADU4: Menghubungi CPO atau pendamping | ADV4: 0 | ADW4: 0 | ADX4: 0 | ADY4: 0 | ADZ4: 1 | AEA4: 0 | AEB4: 0 | AEC4: 0 | AEE4: Laki-laki dewasa | AEG4: Menelepon atau WA langsung | AEI4: Lebih kepada perawatan oleh user | AEJ4: Kadang-kadang | AEK4: Pengurangan pengeluaran rumah tangga (bahan bakar minyak, pupuk, dll.) Lebih mudah mendapatkan energi Pasokan energi yang andal Memasak lebih cepat Lebih aman Pengurangan waktu dan tenaga Peningkatan kebersihan kandang ternak | AEL4: 1 | AEM4: 1 | AEN4: 1 | AEO4: 1 | AEP4: 1 | AEQ4: 1 | AER4: 1 | AES4: 0 | AET4: 0 | AEU4: 0 | AEV4: 0 | AEW4: 0 | AEY4: Mengurangi pengeluaran energi | AFA4: Yayasan Rumah Energi (YRE) | AFC4: WhatsApp Image 2026-02-03 at 14.10.45-14_41_12.jpeg | AFD4: https://kf.kobotoolbox.org/api/v2/assets/avstPQqLr3Ab3ZdcVTXZ6f/data/663335540/attachments/att8QJmiQ6TDswj69xqWGwnB/ | AFE4: WhatsApp Image 2026-02-03 at 14.10.45 (1)-14_41_29.jpeg | AFF4: https://kf.kobotoolbox.org/api/v2/assets/avstPQqLr3Ab3ZdcVTXZ6f/data/663335540/attachments/attdrQrJLATCmZAfwrJFtGPn/ | AFG4: manto / witono
A5: 46057 | B5: 46057 | C5: Marmanto | D5: Pujiyanto | E5: 62852322746 | G5: -7.3524846 | H5: 110.34279 | J5: 2.35 | M5: -7.3525236 | N5: 110.34286 | P5: 4.92 | R5: Jawa Tengah | AC5: Klaten | AD5: Tulung | AE5: Mundu | AF5: LPTP | AG5: LPP0514 | AH5: 4 | AI5: VPA2 | AJ5: Tidak aktif | AK5: 53 | AL5: Laki-laki | AM5: Sudah menikah | AN5: SMA/Sederajat | AO5: Petani | AP5: 1 | AQ5: 0 | AR5: 0 | AS5: 0 | AT5: 0 | AU5: 0 | AV5: 0 | AW5: 0 | AY5: Peternak | AZ5: 0 | BA5: 1 | BB5: 0 | BC5: 0 | BD5: 0 | BE5: 0 | BF5: 0 | BG5: 0 | BI5: Rp1.500.000 - Rp2.500.000 | BJ5: 1 | BK5: 1 | BL5: 2 | BM5: 0 | BN5: Milik sendiri | BO5: Permanen (dinding bata dan semen) | BP5: 1 | BQ5: 0 | BR5: 0 | BS5: 0 | BT5: 0 | BV5: Keramik/ubin | BW5: 0 | BX5: 0 | BY5: 1 | BZ5: 0 | CA5: 0 | CC5: Genting | CD5: 0 | CE5: 0 | CF5: 0 | CG5: 0 | CH5: 0 | CI5: 1 | CJ5: 0 | CL5: Ya | CM5: 2022 | CN5: Fixed-Dome (Kubah Tetap) | CO5: 6 m³ (4-5 ekor sapi, ±5 jam memasak/hari, ±50 kg | CP5: Anggota keluarga - laki-laki | CQ5: 0 | CR5: 0 | CS5: 0 | CT5: 0 | CU5: 1 | CV5: 0 | CW5: 0 | CX5: 0 | CY5: Anggota keluarga - laki-laki | CZ5: 1 | DA5: 0 | DB5: 0 | DD5: Anggota keluarga - laki-laki CPO atau pendamping | DE5: 1 | DF5: 0 | DG5: 1 | DH5: 0 | DJ5: Anggota keluarga - laki-laki CPO atau pendamping | DK5: 1 | DL5: 0 | DM5: 1 | DN5: 0 | DP5: 1 | DQ5: 0 | DR5: 0 | DV5: Tidak berfungsi sama sekali | DW5: >1 tahun yang lalu | DX5: Tidak ada ternak | EI5: Keterbatasan akses terhadap informasi atau pelatihan terkait biogas | EJ5: 0 | EK5: 0 | EL5: 1 | EM5: 0 | EN5: 0 | EP5: Ya, cukup jelas dan mudah diikuti | EQ5: Pelatihan | ER5: CPO atau pendamping | ES5: 1 | ET5: 0 | EU5: 0 | EV5: 0 | EX5: Anggota keluarga - Laki-laki | EY5: 1 | EZ5: 0 | FA5: 0 | FC5: Setiap minggu | FE5: Mengetahui | FF5: Sering (setiap minggu) | FG5: Mengetahui | FH5: Sering (setiap minggu) | FI5: Mengetahui | FJ5: Selalu (setiap hari) | FK5: Mengetahui | FL5: Sering (setiap minggu) | FM5: Mengetahui | FN5: Cukup sering (2 minggu sekali) | FO5: Mengetahui | FP5: Cukup sering (2 minggu sekali) | FQ5: Mengetahui | FR5: Ya | FS5: Mengetahui | FT5: Ya, selalu | FU5: Laki-laki dewasa Perempuan dewasa | FV5: 1 | FW5: 1 | FX5: 0 | FY5: 0 | FZ5: Cukup memahami | GA5: CPO Pelatihan | GB5: 1 | GC5: 1 | GD5: 0 | GE5: 0 | GG5: Sering | GH5: Tidak | GP5: Penuh (100%) | GQ5: Kayu bakar LPG | GR5: 1 | GS5: 1 | GT5: 0 | GU5: 0 | GV5: 0 | GW5: 0 | GX5: 0 | GZ5: Ya | HA5: 150 | HB5: 150000 | HC5: 50 | HD5: 50000 | HE5: 12 | HF5: 100000 | HG5: 2 | HH5: 50000 | HY5: 100 | HZ5: 100000 | IA5: 6 | IB5: 50000 | IK5: 50-65 kg | IL5: 3-5 jam | IM5: Ya | IN5: Tidak | IO5: Lebih bersih | IQ5: Tidak pernah | IZ5: Tidak pernah | JI5: Tidak pernah | JR5: Tidak pernah | KA5: Tidak pernah | KJ5: Tidak pernah | KS5: Cukup membaik | KT5: 0-1 kali | KU5: 0-1 kali | KV5: Laki-laki dewasa | KW5: 1 | KX5: 0 | KY5: 0 | KZ5: 0 | LA5: Cukup membaik | LB5: Cukup membaik | LC5: 0 | LD5: 0 | LE5: 0 | LF5: 3 | LG5: Tidak | LI5: 0 | LJ5: Kebutuhan rumah tangga | LK5: 0 | LL5: 0 | LM5: 0 | LN5: 0 | LO5: 1 | LP5: 0 | LQ5: 0 | LS5: 15 | LT5: 15 | LU5: 0 | LV5: 5 | LW5: 5 | LX5: 0 | LY5: 5 | LZ5: 5 | MA5: 0 | MB5: Ya | MC5: 60 | MD5: 30 | ME5: 60 | MF5: 30 | MG5: 0 | MH5: 0 | MI5: Istirahat | MJ5: 0 | MK5: 0 | ML5: 1 | MM5: 0 | MN5: 0 | MO5: 0 | MR5: santai bersama keluarga | MT5: 0 | MU5: Tidak | NL5: Tidak | NM5: Kombinasi dana mandiri dan kredit/pinjaman | NN5: >11.000.001 | NQ5: Pemerintah | NS5: 24 | NT5: Anggota keluarga - Laki-laki dewasa | NV5: Anggota keluarga - Laki-laki dewasa | NX5: Sedikit meningkat | NY5: 45 | NZ5: 15 | OA5: 0 | OB5: 10 | OC5: 5 | OD5: 0 | OE5: Lebih baik | OF5: Lebih baik (beda waktu memasak 5-30 menit, ATAU tidak lagi ada rasa/bau makanan yang berubah, ATAU alasan lainnya) | OG5: Ya | OH5: 0 | OI5: 0 | OJ5: 0 | OK5: 0 | OL5: 0 | OM5: 0 | ON5: 0 | OO5: 0 | OP5: =VLOOKUP(AG5,'BUS 2'!$G$1:$CU$424,2,0) -> Sapi pedaging | OQ5: =VLOOKUP(AG5,'BUS 2'!$G$1:$CU$424,3,0) -> 1 | OR5: =VLOOKUP(AG5,'BUS 2'!$G$1:$CU$424,4,0) -> 0 | OS5: =VLOOKUP(AG5,'BUS 2'!$G$1:$CU$424,5,0) -> 0 | OT5: =VLOOKUP(AG5,'BUS 2'!$G$1:$CU$424,6,0) -> 0 | OU5: =VLOOKUP(AG5,'BUS 2'!$G$1:$CU$424,7,0) -> 0 | OV5: =VLOOKUP(AG5,'BUS 2'!$G$1:$CU$424,8,0) -> 0 | OW5: =VLOOKUP(AG5,'BUS 2'!$G$1:$CU$424,9,0) -> 0 | OX5: =VLOOKUP(AG5,'BUS 2'!$G$1:$CU$424,10,0) -> 0 | OY5: =VLOOKUP(AG5,'BUS 2'!$G$1:$CU$424,11,0) -> 0 | OZ5: =VLOOKUP(AG5,'BUS 2'!$G$1:$CU$424,12,0) -> Sapi pedaging | PA5: =VLOOKUP(AG5,'BUS 2'!$G$1:$CU$424,13,0) -> 1 | PB5: =VLOOKUP(AG5,'BUS 2'!$G$1:$CU$424,14,0) -> 0 | PC5: =VLOOKUP(AG5,'BUS 2'!$G$1:$CU$424,15,0) -> 0 | PD5: =VLOOKUP(AG5,'BUS 2'!$G$1:$CU$424,16,0) -> 0 | PE5: =VLOOKUP(AG5,'BUS 2'!$G$1:$CU$424,17,0) -> 0 | PF5: =VLOOKUP(AG5,'BUS 2'!$G$1:$CU$424,18,0) -> 0 | PG5: =VLOOKUP(AG5,'BUS 2'!$G$1:$CU$424,19,0) -> 0 | PH5: =VLOOKUP(AG5,'BUS 2'!$G$1:$CU$424,20,0) -> 0 | PI5: =VLOOKUP(AG5,'BUS 2'!$G$1:$CU$424,21,0) -> 0 | PJ5: =VLOOKUP(AG5,'BUS 2'!$G$1:$CU$424,22,0) -> Sapi pedaging | PK5: =VLOOKUP(AG5,'BUS 2'!$G$1:$CU$424,23,0) -> 1 | PL5: =VLOOKUP(AG5,'BUS 2'!$G$1:$CU$424,24,0) -> 0 | PM5: =VLOOKUP(AG5,'BUS 2'!$G$1:$CU$424,25,0) -> 0 | PN5: =VLOOKUP(AG5,'BUS 2'!$G$1:$CU$424,26,0) -> 0 | PO5: =VLOOKUP(AG5,'BUS 2'!$G$1:$CU$424,27,0) -> 0 | PP5: =VLOOKUP(AG5,'BUS 2'!$G$1:$CU$424,28,0) -> 0 | PQ5: =VLOOKUP(AG5,'BUS 2'!$G$1:$CU$424,29,0) -> 0 | PR5: =VLOOKUP(AG5,'BUS 2'!$G$1:$CU$424,30,0) -> 0 | PS5: =VLOOKUP(AG5,'BUS 2'!$G$1:$CU$424,31,0) -> 0 | PT5: 1-Disebarkan ke lahan terbuka | PU5: 1 | PV5: 0 | PW5: 0 | PX5: 0 | PY5: 0 | PZ5: 0 | QA5: 1 | QB5: 0 | QC5: 0 | QD5: 0 | SY5: =VLOOKUP(AG5,'BUS 2'!$G$1:$CU$424,33,0) -> 2 | SZ5: =VLOOKUP(AG5,'BUS 2'!$G$1:$CU$424,34,0) | TA5: =VLOOKUP(AG5,'BUS 2'!$G$1:$CU$424,35,0) | TB5: =VLOOKUP(AG5,'BUS 2'!$G$1:$CU$424,36,0) | TC5: =VLOOKUP(AG5,'BUS 2'!$G$1:$CU$424,37,0) | TD5: =VLOOKUP(AG5,'BUS 2'!$G$1:$CU$424,38,0) | TE5: =VLOOKUP(AG5,'BUS 2'!$G$1:$CU$424,39,0) | TF5: =VLOOKUP(AG5,'BUS 2'!$G$1:$CU$424,40,0) | TG5: =VLOOKUP(AG5,'BUS 2'!$G$1:$CU$424,42,0) -> 0 | TH5: =VLOOKUP(AG5,'BUS 2'!$G$1:$CU$424,43,0) | TI5: =VLOOKUP(AG5,'BUS 2'!$G$1:$CU$424,44,0) | TJ5: =VLOOKUP(AG5,'BUS 2'!$G$1:$CU$424,45,0) | TK5: =VLOOKUP(AG5,'BUS 2'!$G$1:$CU$424,46,0) | TL5: =VLOOKUP(AG5,'BUS 2'!$G$1:$CU$424,47,0) | TM5: =VLOOKUP(AG5,'BUS 2'!$G$1:$CU$424,48,0) | TN5: =VLOOKUP(AG5,'BUS 2'!$G$1:$CU$424,49,0) | TO5: =VLOOKUP(AG5,'BUS 2'!$G$1:$CU$424,50,0) -> 2 | TP5: =VLOOKUP(AG5,'BUS 2'!$G$1:$CU$424,51,0) -> 0 | TQ5: =VLOOKUP(AG5,'BUS 2'!$G$1:$CU$424,52,0) -> 0 | TR5: =VLOOKUP(AG5,'BUS 2'!$G$1:$CU$424,53,0) -> 0 | TS5: =VLOOKUP(AG5,'BUS 2'!$G$1:$CU$424,54,0) | TT5: =VLOOKUP(AG5,'BUS 2'!$G$1:$CU$424,55,0) | TU5: =VLOOKUP(AG5,'BUS 2'!$G$1:$CU$424,56,0) | TV5: =VLOOKUP(AG5,'BUS 2'!$G$1:$CU$424,57,0) | TW5: =VLOOKUP(AG5,'BUS 2'!$G$1:$CU$424,58,0) | TX5: =VLOOKUP(AG5,'BUS 2'!$G$1:$CU$424,59,0) | TY5: =VLOOKUP(AG5,'BUS 2'!$G$1:$CU$424,60,0) | TZ5: =VLOOKUP(AG5,'BUS 2'!$G$1:$CU$424,61,0) | UA5: =VLOOKUP(AG5,'BUS 2'!$G$1:$CU$424,62,0) | UB5: =VLOOKUP(AG5,'BUS 2'!$G$1:$CU$424,63,0) | UC5: =VLOOKUP(AG5,'BUS 2'!$G$1:$CU$424,64,0) | UD5: =VLOOKUP(AG5,'BUS 2'!$G$1:$CU$424,65,0) | UE5: =VLOOKUP(AG5,'BUS 2'!$G$1:$CU$424,66,0) | UF5: =VLOOKUP(AG5,'BUS 2'!$G$1:$CU$424,67,0) | UG5: =VLOOKUP(AG5,'BUS 2'!$G$1:$CU$424,68,0) | UH5: =VLOOKUP(AG5,'BUS 2'!$G$1:$CU$424,69,0) | UI5: =VLOOKUP(AG5,'BUS 2'!$G$1:$CU$424,70,0) | UJ5: =VLOOKUP(AG5,'BUS 2'!$G$1:$CU$424,71,0) | UK5: =VLOOKUP(AG5,'BUS 2'!$G$1:$CU$424,72,0) | UL5: =VLOOKUP(AG5,'BUS 2'!$G$1:$CU$424,73,0) | UM5: =VLOOKUP(AG5,'BUS 2'!$G$1:$CU$424,74,0) | UN5: =VLOOKUP(AG5,'BUS 2'!$G$1:$CU$424,75,0) | UO5: =VLOOKUP(AG5,'BUS 2'!$G$1:$CU$424,76,0) | UP5: =VLOOKUP(AG5,'BUS 2'!$G$1:$CU$424,77,0) | UQ5: =VLOOKUP(AG5,'BUS 2'!$G$1:$CU$424,78,0) | UR5: =VLOOKUP(AG5,'BUS 2'!$G$1:$CU$424,79,0) | US5: =VLOOKUP(AG5,'BUS 2'!$G$1:$CU$424,80,0) | UT5: =VLOOKUP(AG5,'BUS 2'!$G$1:$CU$424,81,0) | AAL5: Tidak | AAR5: Ya | AAS5: Mengetahui | AAT5: Digunakan untuk pupuk di lahan pertanian sendiri Diberikan gratis ke orang lain | AAU5: 1 | AAV5: 0 | AAW5: 0 | AAX5: 0 | AAY5: 1 | AAZ5: 0 | ABA5: 0 | ABB5: Pupuk cair untuk tanaman | ABC5: 1 | ABD5: 0 | ABE5: 0 | ABF5: 0 | ABG5: 0 | ABQ5: Rumput | ABR5: Cukup (2 minggu sekali) | ABS5: 1500 | ABU5: 500 | ABV5: 500 | ABW5: NPK | ABY5: 20 | ABZ5: 10 | ACA5: 10 | ACB5: 700 | ACC5: 7000 | ACD5: 400 | ACE5: Tidak | ACF5: Cukup meningkat | ACG5: Cukup meningkat | ACH5: Cukup meningkat | ACK5: Tidak punya waktu mengumpulkannya Ladang/sawah terlalu jauh, sulit untuk mengangkut ke sana | ACL5: 0 | ACM5: 0 | ACN5: 1 | ACO5: 1 | ACP5: 0 | ACQ5: 0 | ACR5: 0 | ACT5: tidak | ACU5: Manfaat cukup signifikan, terasa di kehidupan sehari-hari | ACV5: Bertambah | ACW5: Kontribusi beberapa anggota keluarga | ACX5: Netral/tidak tahu | ACY5: Anggota keluarga - Perempuan dewasa | ACZ5: 0 | ADA5: 1 | ADB5: 0 | ADC5: 0 | ADD5: Cukup puas | ADE5: Cukup puas | ADF5: Cukup puas | ADG5: Cukup puas | ADH5: Ya | ADI5: pemngurasan , kompor , mixer dll | ADJ5: Cukup puas | ADU5: Menghubungi CPO atau pendamping | ADV5: 0 | ADW5: 0 | ADX5: 0 | ADY5: 0 | ADZ5: 1 | AEA5: 0 | AEB5: 0 | AEC5: 0 | AEE5: Laki-laki dewasa | AEG5: Menelepon atau WA langsung | AEI5: Tidak ada | AEJ5: Kadang-kadang | AEK5: Pengurangan pengeluaran rumah tangga (bahan bakar minyak, pupuk, dll.) Lebih mudah mendapatkan energi Pasokan energi yang andal Memasak lebih cepat Lebih aman | AEL5: 1 | AEM5: 1 | AEN5: 1 | AEO5: 1 | AEP5: 1 | AEQ5: 0 | AER5: 0 | AES5: 0 | AET5: 0 | AEU5: 0 | AEV5: 0 | AEW5: 0 | AEY5: Mengurangi pengeluaran energi | AFA5: Yayasan Rumah Energi (YRE) | AFC5: WhatsApp Image 2026-02-03 at 14.14.40-19_36_45.jpeg | AFD5: https://kf.kobotoolbox.org/api/v2/assets/avstPQqLr3Ab3ZdcVTXZ6f/data/663630485/attachments/att929sawMu4BTL72Yra6Ga7/ | AFE5: WhatsApp Image 2026-02-03 at 14.14.40 (1)-19_37_9.jpeg | AFF5: https://kf.kobotoolbox.org/api/v2/assets/avstPQqLr3Ab3ZdcVTXZ6f/data/663630485/attachments/att6DkGeDscczRhQdqeYyGU3/ | AFG5: manto / witono | AFI5: sudah tidak punya sapi lagi dijual belum beli lagi karena PMK
A6: 46057 | B6: 46057 | C6: Marmanto | D6: Sugeng Raharjo | E6: 6282136100417 | G6: -7.351814 | H6: 110.35235 | J6: 4.82 | M6: -7.3511364 | N6: 110.3523 | P6: 4.5 | R6: Jawa Tengah | AC6: Klaten | AD6: Tulung | AE6: Sudimoro | AF6: LPTP | AG6: LPP0345 | AH6: 11 | AI6: VPA1 | AJ6: Tidak aktif | AK6: 60 | AL6: Laki-laki | AM6: Sudah menikah | AN6: SMP/Sederajat | AO6: Petani | AP6: 1 | AQ6: 0 | AR6: 0 | AS6: 0 | AT6: 0 | AU6: 0 | AV6: 0 | AW6: 0 | AY6: Pekerja lepas | AZ6: 0 | BA6: 0 | BB6: 1 | BC6: 0 | BD6: 0 | BE6: 0 | BF6: 0 | BG6: 0 | BI6: Rp1.500.000 - Rp2.500.000 | BJ6: 2 | BK6: 2 | BL6: 2 | BM6: 0 | BN6: Milik sendiri | BO6: Permanen (dinding bata dan semen) | BP6: 1 | BQ6: 0 | BR6: 0 | BS6: 0 | BT6: 0 | BV6: Keramik/ubin | BW6: 0 | BX6: 0 | BY6: 1 | BZ6: 0 | CA6: 0 | CC6: Genting | CD6: 0 | CE6: 0 | CF6: 0 | CG6: 0 | CH6: 0 | CI6: 1 | CJ6: 0 | CL6: Ya | CM6: 2015 | CN6: Fixed-Dome (Kubah Tetap) | CO6: 6 m³ (4-5 ekor sapi, ±5 jam memasak/hari, ±50 kg | CP6: Anggota keluarga - laki-laki | CQ6: 0 | CR6: 0 | CS6: 0 | CT6: 0 | CU6: 1 | CV6: 0 | CW6: 0 | CX6: 0 | CY6: Anggota keluarga - laki-laki | CZ6: 1 | DA6: 0 | DB6: 0 | DD6: Anggota keluarga - laki-laki CPO atau pendamping | DE6: 1 | DF6: 0 | DG6: 1 | DH6: 0 | DJ6: Anggota keluarga - laki-laki CPO atau pendamping | DK6: 1 | DL6: 0 | DM6: 1 | DN6: 0 | DP6: 1 | DQ6: 0 | DR6: 0 | DV6: Tidak berfungsi sama sekali | DW6: >1 tahun yang lalu | DX6: Tidak ada ternak | EI6: Keterbatasan akses terhadap informasi atau pelatihan terkait biogas Tidak ada masalah | EJ6: 0 | EK6: 0 | EL6: 1 | EM6: 1 | EN6: 0 | EP6: Ya, cukup jelas dan mudah diikuti | EQ6: Pelatihan | ER6: CPO atau pendamping Pegawai koperasi | ES6: 1 | ET6: 0 | EU6: 1 | EV6: 0 | EX6: Anggota keluarga - Laki-laki Anggota keluarga - Perempuan dewasa | EY6: 1 | EZ6: 1 | FA6: 0 | FC6: Setiap minggu | FE6: Mengetahui | FF6: Selalu (setiap hari) | FG6: Mengetahui | FH6: Sering (setiap minggu) | FI6: Mengetahui | FJ6: Sering (setiap minggu) | FK6: Mengetahui | FL6: Sering (setiap minggu) | FM6: Mengetahui | FN6: Jarang (setiap bulan atau lebih) | FO6: Mengetahui | FP6: Jarang (setiap bulan atau lebih) | FQ6: Mengetahui | FR6: Ya | FS6: Mengetahui | FT6: Ya, selalu | FU6: Laki-laki dewasa Perempuan dewasa | FV6: 1 | FW6: 1 | FX6: 0 | FY6: 0 | FZ6: Cukup memahami | GA6: CPO Pelatihan | GB6: 1 | GC6: 1 | GD6: 0 | GE6: 0 | GG6: Sering | GH6: Tidak | GP6: Penuh (100%) | GQ6: Kayu bakar LPG | GR6: 1 | GS6: 1 | GT6: 0 | GU6: 0 | GV6: 0 | GW6: 0 | GX6: 0 | GZ6: Tidak | HA6: 200 | HB6: 200000 | HC6: 50 | HD6: 50000 | HE6: 12 | HF6: 100000 | HG6: 3 | HH6: 25000 | HY6: 150 | HZ6: 150000 | IA6: 9 | IB6: 75000 | IK6: 50-65 kg | IL6: 3-5 jam | IM6: Ya | IN6: Tidak | IO6: Lebih bersih | IQ6: Tidak pernah | IZ6: Tidak pernah | JI6: Tidak pernah | JR6: Tidak pernah | KA6: Tidak pernah | KJ6: Tidak pernah | KS6: Cukup membaik | KT6: 0-1 kali | KU6: 0-1 kali | KV6: Perempuan dewasa | KW6: 0 | KX6: 1 | KY6: 0 | KZ6: 0 | LA6: Cukup membaik | LB6: Cukup membaik | LC6: 0 | LD6: 0 | LE6: 0 | LF6: 0 | LG6: Ya | LH6: 100000 | LJ6: Kebutuhan rumah tangga | LK6: 0 | LL6: 0 | LM6: 0 | LN6: 0 | LO6: 1 | LP6: 0 | LQ6: 0 | LS6: 15 | LT6: 15 | LU6: 0 | LV6: 5 | LW6: 5 | LX6: 0 | LY6: 5 | LZ6: 5 | MA6: 0 | MB6: Ya | MC6: 30 | MD6: 15 | ME6: 30 | MF6: 15 | MG6: 0 | MH6: 0 | MI6: Istirahat | MJ6: 0 | MK6: 0 | ML6: 1 | MM6: 0 | MN6: 0 | MO6: 0 | MR6: untuk santai keluarga | MT6: untuk santai | MU6: Tidak | NL6: Tidak | NM6: Kombinasi dana mandiri dan dana hibah | NN6: >11.000.001 | NO6: Program yayasan/NGO | NV6: Anggota keluarga - Laki-laki dewasa | NX6: Sedikit meningkat | NY6: 45 | NZ6: 30 | OA6: 0 | OB6: 10 | OC6: 5 | OD6: 0 | OE6: Lebih baik | OF6: Lebih baik (beda waktu memasak 5-30 menit, ATAU tidak lagi ada rasa/bau makanan yang berubah, ATAU alasan lainnya) | OG6: Tidak | OH6: 0 | OI6: 0 | OJ6: 0 | OK6: 0 | OL6: 0 | OM6: 0 | ON6: 0 | OO6: 0 | OP6: =VLOOKUP(AG6,'BUS 2'!$G$1:$CU$424,2,0) -> Sapi pedaging | OQ6: =VLOOKUP(AG6,'BUS 2'!$G$1:$CU$424,3,0) -> 1 | OR6: =VLOOKUP(AG6,'BUS 2'!$G$1:$CU$424,4,0) -> 0 | OS6: =VLOOKUP(AG6,'BUS 2'!$G$1:$CU$424,5,0) -> 0 | OT6: =VLOOKUP(AG6,'BUS 2'!$G$1:$CU$424,6,0) -> 0 | OU6: =VLOOKUP(AG6,'BUS 2'!$G$1:$CU$424,7,0) -> 0 | OV6: =VLOOKUP(AG6,'BUS 2'!$G$1:$CU$424,8,0) -> 0 | OW6: =VLOOKUP(AG6,'BUS 2'!$G$1:$CU$424,9,0) -> 0 | OX6: =VLOOKUP(AG6,'BUS 2'!$G$1:$CU$424,10,0) -> 0 | OY6: =VLOOKUP(AG6,'BUS 2'!$G$1:$CU$424,11,0) -> 0 | OZ6: =VLOOKUP(AG6,'BUS 2'!$G$1:$CU$424,12,0) -> Sapi pedaging | PA6: =VLOOKUP(AG6,'BUS 2'!$G$1:$CU$424,13,0) -> 1 | PB6: =VLOOKUP(AG6,'BUS 2'!$G$1:$CU$424,14,0) -> 0 | PC6: =VLOOKUP(AG6,'BUS 2'!$G$1:$CU$424,15,0) -> 0 | PD6: =VLOOKUP(AG6,'BUS 2'!$G$1:$CU$424,16,0) -> 0 | PE6: =VLOOKUP(AG6,'BUS 2'!$G$1:$CU$424,17,0) -> 0 | PF6: =VLOOKUP(AG6,'BUS 2'!$G$1:$CU$424,18,0) -> 0 | PG6: =VLOOKUP(AG6,'BUS 2'!$G$1:$CU$424,19,0) -> 0 | PH6: =VLOOKUP(AG6,'BUS 2'!$G$1:$CU$424,20,0) -> 0 | PI6: =VLOOKUP(AG6,'BUS 2'!$G$1:$CU$424,21,0) -> 0 | PJ6: =VLOOKUP(AG6,'BUS 2'!$G$1:$CU$424,22,0) -> Tidak ada | PK6: =VLOOKUP(AG6,'BUS 2'!$G$1:$CU$424,23,0) -> 0 | PL6: =VLOOKUP(AG6,'BUS 2'!$G$1:$CU$424,24,0) -> 0 | PM6: =VLOOKUP(AG6,'BUS 2'!$G$1:$CU$424,25,0) -> 0 | PN6: =VLOOKUP(AG6,'BUS 2'!$G$1:$CU$424,26,0) -> 0 | PO6: =VLOOKUP(AG6,'BUS 2'!$G$1:$CU$424,27,0) -> 0 | PP6: =VLOOKUP(AG6,'BUS 2'!$G$1:$CU$424,28,0) -> 0 | PQ6: =VLOOKUP(AG6,'BUS 2'!$G$1:$CU$424,29,0) -> 0 | PR6: =VLOOKUP(AG6,'BUS 2'!$G$1:$CU$424,30,0) -> 0 | PS6: =VLOOKUP(AG6,'BUS 2'!$G$1:$CU$424,31,0) -> 1 | PT6: 1-Disebarkan ke lahan terbuka | PU6: 1 | PV6: 0 | PW6: 0 | PX6: 0 | PY6: 0 | PZ6: 0 | QA6: 1 | QB6: 0 | QC6: 0 | QD6: 0 | SY6: =VLOOKUP(AG6,'BUS 2'!$G$1:$CU$424,33,0) -> 2 | SZ6: =VLOOKUP(AG6,'BUS 2'!$G$1:$CU$424,34,0) | TA6: =VLOOKUP(AG6,'BUS 2'!$G$1:$CU$424,35,0) | TB6: =VLOOKUP(AG6,'BUS 2'!$G$1:$CU$424,36,0) | TC6: =VLOOKUP(AG6,'BUS 2'!$G$1:$CU$424,37,0) | TD6: =VLOOKUP(AG6,'BUS 2'!$G$1:$CU$424,38,0) | TE6: =VLOOKUP(AG6,'BUS 2'!$G$1:$CU$424,39,0) | TF6: =VLOOKUP(AG6,'BUS 2'!$G$1:$CU$424,40,0) | TG6: =VLOOKUP(AG6,'BUS 2'!$G$1:$CU$424,42,0) -> 2 | TH6: =VLOOKUP(AG6,'BUS 2'!$G$1:$CU$424,43,0) | TI6: =VLOOKUP(AG6,'BUS 2'!$G$1:$CU$424,44,0) | TJ6: =VLOOKUP(AG6,'BUS 2'!$G$1:$CU$424,45,0) | TK6: =VLOOKUP(AG6,'BUS 2'!$G$1:$CU$424,46,0) | TL6: =VLOOKUP(AG6,'BUS 2'!$G$1:$CU$424,47,0) | TM6: =VLOOKUP(AG6,'BUS 2'!$G$1:$CU$424,48,0) | TN6: =VLOOKUP(AG6,'BUS 2'!$G$1:$CU$424,49,0) | TO6: =VLOOKUP(AG6,'BUS 2'!$G$1:$CU$424,50,0) | TP6: =VLOOKUP(AG6,'BUS 2'!$G$1:$CU$424,51,0) | TQ6: =VLOOKUP(AG6,'BUS 2'!$G$1:$CU$424,52,0) | TR6: =VLOOKUP(AG6,'BUS 2'!$G$1:$CU$424,53,0) | TS6: =VLOOKUP(AG6,'BUS 2'!$G$1:$CU$424,54,0) | TT6: =VLOOKUP(AG6,'BUS 2'!$G$1:$CU$424,55,0) | TU6: =VLOOKUP(AG6,'BUS 2'!$G$1:$CU$424,56,0) | TV6: =VLOOKUP(AG6,'BUS 2'!$G$1:$CU$424,57,0) | TW6: =VLOOKUP(AG6,'BUS 2'!$G$1:$CU$424,58,0) | TX6: =VLOOKUP(AG6,'BUS 2'!$G$1:$CU$424,59,0) | TY6: =VLOOKUP(AG6,'BUS 2'!$G$1:$CU$424,60,0) | TZ6: =VLOOKUP(AG6,'BUS 2'!$G$1:$CU$424,61,0) | UA6: =VLOOKUP(AG6,'BUS 2'!$G$1:$CU$424,62,0) | UB6: =VLOOKUP(AG6,'BUS 2'!$G$1:$CU$424,63,0) | UC6: =VLOOKUP(AG6,'BUS 2'!$G$1:$CU$424,64,0) | UD6: =VLOOKUP(AG6,'BUS 2'!$G$1:$CU$424,65,0) | UE6: =VLOOKUP(AG6,'BUS 2'!$G$1:$CU$424,66,0) | UF6: =VLOOKUP(AG6,'BUS 2'!$G$1:$CU$424,67,0) | UG6: =VLOOKUP(AG6,'BUS 2'!$G$1:$CU$424,68,0) | UH6: =VLOOKUP(AG6,'BUS 2'!$G$1:$CU$424,69,0) | UI6: =VLOOKUP(AG6,'BUS 2'!$G$1:$CU$424,70,0) | UJ6: =VLOOKUP(AG6,'BUS 2'!$G$1:$CU$424,71,0) | UK6: =VLOOKUP(AG6,'BUS 2'!$G$1:$CU$424,72,0) | UL6: =VLOOKUP(AG6,'BUS 2'!$G$1:$CU$424,73,0) | UM6: =VLOOKUP(AG6,'BUS 2'!$G$1:$CU$424,74,0) | UN6: =VLOOKUP(AG6,'BUS 2'!$G$1:$CU$424,75,0) | UO6: =VLOOKUP(AG6,'BUS 2'!$G$1:$CU$424,76,0) | UP6: =VLOOKUP(AG6,'BUS 2'!$G$1:$CU$424,77,0) | UQ6: =VLOOKUP(AG6,'BUS 2'!$G$1:$CU$424,78,0) | UR6: =VLOOKUP(AG6,'BUS 2'!$G$1:$CU$424,79,0) | US6: =VLOOKUP(AG6,'BUS 2'!$G$1:$CU$424,80,0) | UT6: =VLOOKUP(AG6,'BUS 2'!$G$1:$CU$424,81,0) | AAL6: Tidak | AAR6: Ya | AAS6: Mengetahui | AAT6: Diberikan gratis ke orang lain | AAU6: 0 | AAV6: 0 | AAW6: 0 | AAX6: 0 | AAY6: 1 | AAZ6: 0 | ABA6: 0 | ACK6: Tidak punya waktu mengumpulkannya Ladang/sawah terlalu jauh, sulit untuk mengangkut ke sana | ACL6: 0 | ACM6: 0 | ACN6: 1 | ACO6: 1 | ACP6: 0 | ACQ6: 0 | ACR6: 0 | ACT6: tidak | ACU6: Manfaat cukup signifikan, terasa di kehidupan sehari-hari | ACV6: Bertambah | ACW6: Anggota keluarga - Perempuan dewasa | ACX6: Setuju | ACY6: Anggota keluarga - Laki-laki dewasa Anggota keluarga - Perempuan dewasa Anggota keluarga - Anak-anak | ACZ6: 1 | ADA6: 1 | ADB6: 1 | ADC6: 0 | ADD6: Cukup puas | ADE6: Cukup puas | ADF6: Cukup puas | ADG6: Cukup puas | ADH6: Ya | ADI6: tidak | ADJ6: Cukup puas | ADU6: Menghubungi CPO atau pendamping Memperbaiki sendiri | ADV6: 0 | ADW6: 0 | ADX6: 0 | ADY6: 0 | ADZ6: 1 | AEA6: 1 | AEB6: 0 | AEC6: 0 | AEE6: Laki-laki dewasa | AEG6: Menelepon atau WA langsung | AEI6: Tidak ada, sudah baik | AEJ6: Kadang-kadang | AEK6: Lebih mudah mendapatkan energi Pasokan energi yang andal Memasak lebih cepat Lebih aman Pengurangan waktu dan tenaga Peningkatan kebersihan kandang ternak | AEL6: 0 | AEM6: 1 | AEN6: 1 | AEO6: 1 | AEP6: 1 | AEQ6: 1 | AER6: 1 | AES6: 0 | AET6: 0 | AEU6: 0 | AEV6: 0 | AEW6: 0 | AEY6: Mengurangi pengeluaran energi | AFA6: Yayasan Rumah Energi (YRE) | AFC6: WhatsApp Image 2026-02-03 at 14.15.10-20_20_30.jpeg | AFD6: https://kf.kobotoolbox.org/api/v2/assets/avstPQqLr3Ab3ZdcVTXZ6f/data/663655830/attachments/attMgVfQxjHGzHqxKorbqRsb/ | AFE6: WhatsApp Image 2026-02-03 at 14.15.10 (1)-20_20_52.jpeg | AFF6: https://kf.kobotoolbox.org/api/v2/assets/avstPQqLr3Ab3ZdcVTXZ6f/data/663655830/attachments/attfzvzMBtnrabApiEvRCRMS/ | AFG6: manto / witono
A7: 46057 | B7: 46057 | C7: Marmanto | D7: Ibrahim | E7: 6285701460813 | G7: -7.3243326 | H7: 110.38137 | J7: 4.87 | M7: -7.3243404 | N7: 110.3813 | P7: 4.87 | R7: Jawa Tengah | AC7: Boyolali | AD7: Mojosongo | AE7: Mojosongo | AF7: LPTP | AG7: LPP0005 | AH7: 16 | AI7: VPA1 | AJ7: Tidak aktif | AK7: 60 | AL7: Laki-laki | AM7: Sudah menikah | AN7: SD/Sederajat | AO7: Petani | AP7: 1 | AQ7: 0 | AR7: 0 | AS7: 0 | AT7: 0 | AU7: 0 | AV7: 0 | AW7: 0 | AY7: Peternak | AZ7: 0 | BA7: 1 | BB7: 0 | BC7: 0 | BD7: 0 | BE7: 0 | BF7: 0 | BG7: 0 | BI7: Rp2.500.000 - Rp3.500.000 | BJ7: 1 | BK7: 4 | BL7: 0 | BM7: 0 | BN7: Milik sendiri | BO7: Permanen (dinding bata dan semen) | BP7: 1 | BQ7: 0 | BR7: 0 | BS7: 0 | BT7: 0 | BV7: Keramik/ubin | BW7: 0 | BX7: 0 | BY7: 1 | BZ7: 0 | CA7: 0 | CC7: Genting | CD7: 0 | CE7: 0 | CF7: 0 | CG7: 0 | CH7: 0 | CI7: 1 | CJ7: 0 | CL7: Ya | CM7: 2010 | CN7: Fixed-Dome (Kubah Tetap) | CO7: 6 m³ (4-5 ekor sapi, ±5 jam memasak/hari, ±50 kg | CP7: Anggota keluarga - laki-laki | CQ7: 0 | CR7: 0 | CS7: 0 | CT7: 0 | CU7: 1 | CV7: 0 | CW7: 0 | CX7: 0 | CY7: Anggota keluarga - laki-laki | CZ7: 1 | DA7: 0 | DB7: 0 | DD7: Anggota keluarga - laki-laki CPO atau pendamping | DE7: 1 | DF7: 0 | DG7: 1 | DH7: 0 | DJ7: Anggota keluarga - laki-laki CPO atau pendamping | DK7: 1 | DL7: 0 | DM7: 1 | DN7: 0 | DP7: 1 | DQ7: 0 | DR7: 0 | DV7: Tidak berfungsi sama sekali | DW7: >1 tahun yang lalu | DX7: Tidak ada ternak | EI7: Kurangnya dukungan atau pemantauan dari pemerintah atau CPO Keterbatasan akses terhadap informasi atau pelatihan terkait biogas | EJ7: 0 | EK7: 1 | EL7: 1 | EM7: 0 | EN7: 0 | EP7: Ya, cukup jelas dan mudah diikuti | EQ7: Pelatihan | ER7: CPO atau pendamping | ES7: 1 | ET7: 0 | EU7: 0 | EV7: 0 | EX7: Anggota keluarga - Laki-laki Anggota keluarga - Perempuan dewasa | EY7: 1 | EZ7: 1 | FA7: 0 | FC7: Setiap bulan | FE7: Mengetahui | FF7: Selalu (setiap hari) | FG7: Mengetahui | FH7: Sering (setiap minggu) | FI7: Mengetahui | FJ7: Selalu (setiap hari) | FK7: Mengetahui | FL7: Sering (setiap minggu) | FM7: Mengetahui | FN7: Jarang (setiap bulan atau lebih) | FO7: Mengetahui | FP7: Jarang (setiap bulan atau lebih) | FQ7: Mengetahui | FR7: Ya | FS7: Mengetahui | FT7: Ya, selalu | FU7: Laki-laki dewasa Perempuan dewasa | FV7: 1 | FW7: 1 | FX7: 0 | FY7: 0 | FZ7: Cukup memahami | GA7: CPO Pelatihan | GB7: 1 | GC7: 1 | GD7: 0 | GE7: 0 | GG7: Sering | GH7: Ya | GI7: Tetangga | GJ7: 1 | GK7: 0 | GL7: 0 | GM7: 0 | GO7: 8 | GP7: Penuh (100%) | GQ7: Kayu bakar LPG | GR7: 1 | GS7: 1 | GT7: 0 | GU7: 0 | GV7: 0 | GW7: 0 | GX7: 0 | GZ7: Ya | HA7: 150 | HB7: 150000 | HC7: 50 | HD7: 50000 | HE7: 12 | HF7: 100000 | HG7: 3 | HH7: 25000 | HY7: 50 | HZ7: 50000 | IA7: 3 | IB7: 25000 | IK7: 50-65 kg | IL7: 3-5 jam | IM7: Ya | IN7: Tidak | IO7: Lebih bersih | IQ7: Tidak pernah | IZ7: Tidak pernah | JI7: Tidak pernah | JR7: Tidak pernah | KA7: Tidak pernah | KJ7: Tidak pernah | KS7: Cukup membaik | KT7: 0-1 kali | KU7: 0-1 kali | KV7: Laki-laki dewasa Perempuan dewasa | KW7: 1 | KX7: 1 | KY7: 0 | KZ7: 0 | LA7: Cukup membaik | LB7: Cukup membaik | LC7: 0 | LD7: 0 | LE7: 0 | LF7: 0 | LG7: Ya | LH7: 100000 | LJ7: Kebutuhan rumah tangga | LK7: 0 | LL7: 0 | LM7: 0 | LN7: 0 | LO7: 1 | LP7: 0 | LQ7: 0 | LS7: 15 | LT7: 15 | LU7: 0 | LV7: 5 | LW7: 5 | LX7: 0 | LY7: 5 | LZ7: 5 | MA7: 0 | MB7: Ya | MC7: 30 | MD7: 15 | ME7: 30 | MF7: 15 | MG7: 0 | MH7: 0 | MI7: Istirahat | MJ7: 0 | MK7: 0 | ML7: 1 | MM7: 0 | MN7: 0 | MO7: 0 | MR7: santai dengan keluarga | MT7: kumpul keluarga | MU7: Ya, untuk anggota keluarga | MV7: Pemasangan sistem biogas | MW7: 0 | MX7: 1 | MY7: 0 | MZ7: 0 | NL7: Tidak | NM7: Kombinasi dana mandiri dan dana hibah | NN7: 9.000.001-11.000.000 | NO7: Pemerintah | NV7: Anggota keluarga - Laki-laki dewasa | NX7: Sedikit meningkat | NY7: 40 | NZ7: 20 | OA7: 0 | OB7: 10 | OC7: 10 | OD7: 0 | OE7: Lebih baik | OF7: Lebih baik (beda waktu memasak 5-30 menit, ATAU tidak lagi ada rasa/bau makanan yang berubah, ATAU alasan lainnya) | OG7: Ya | OH7: 0 | OI7: 0 | OJ7: 0 | OK7: 0 | OL7: 0 | OM7: 0 | ON7: 0 | OO7: 0 | OP7: =VLOOKUP(AG7,'BUS 2'!$G$1:$CU$424,2,0) -> Sapi pedaging | OQ7: =VLOOKUP(AG7,'BUS 2'!$G$1:$CU$424,3,0) -> 1 | OR7: =VLOOKUP(AG7,'BUS 2'!$G$1:$CU$424,4,0) -> 0 | OS7: =VLOOKUP(AG7,'BUS 2'!$G$1:$CU$424,5,0) -> 0 | OT7: =VLOOKUP(AG7,'BUS 2'!$G$1:$CU$424,6,0) -> 0 | OU7: =VLOOKUP(AG7,'BUS 2'!$G$1:$CU$424,7,0) -> 0 | OV7: =VLOOKUP(AG7,'BUS 2'!$G$1:$CU$424,8,0) -> 0 | OW7: =VLOOKUP(AG7,'BUS 2'!$G$1:$CU$424,9,0) -> 0 | OX7: =VLOOKUP(AG7,'BUS 2'!$G$1:$CU$424,10,0) -> 0 | OY7: =VLOOKUP(AG7,'BUS 2'!$G$1:$CU$424,11,0) -> 0 | OZ7: =VLOOKUP(AG7,'BUS 2'!$G$1:$CU$424,12,0) -> Sapi pedaging | PA7: =VLOOKUP(AG7,'BUS 2'!$G$1:$CU$424,13,0) -> 1 | PB7: =VLOOKUP(AG7,'BUS 2'!$G$1:$CU$424,14,0) -> 0 | PC7: =VLOOKUP(AG7,'BUS 2'!$G$1:$CU$424,15,0) -> 0 | PD7: =VLOOKUP(AG7,'BUS 2'!$G$1:$CU$424,16,0) -> 0 | PE7: =VLOOKUP(AG7,'BUS 2'!$G$1:$CU$424,17,0) -> 0 | PF7: =VLOOKUP(AG7,'BUS 2'!$G$1:$CU$424,18,0) -> 0 | PG7: =VLOOKUP(AG7,'BUS 2'!$G$1:$CU$424,19,0) -> 0 | PH7: =VLOOKUP(AG7,'BUS 2'!$G$1:$CU$424,20,0) -> 0 | PI7: =VLOOKUP(AG7,'BUS 2'!$G$1:$CU$424,21,0) -> 0 | PJ7: =VLOOKUP(AG7,'BUS 2'!$G$1:$CU$424,22,0) -> Tidak ada | PK7: =VLOOKUP(AG7,'BUS 2'!$G$1:$CU$424,23,0) -> 0 | PL7: =VLOOKUP(AG7,'BUS 2'!$G$1:$CU$424,24,0) -> 0 | PM7: =VLOOKUP(AG7,'BUS 2'!$G$1:$CU$424,25,0) -> 0 | PN7: =VLOOKUP(AG7,'BUS 2'!$G$1:$CU$424,26,0) -> 0 | PO7: =VLOOKUP(AG7,'BUS 2'!$G$1:$CU$424,27,0) -> 0 | PP7: =VLOOKUP(AG7,'BUS 2'!$G$1:$CU$424,28,0) -> 0 | PQ7: =VLOOKUP(AG7,'BUS 2'!$G$1:$CU$424,29,0) -> 0 | PR7: =VLOOKUP(AG7,'BUS 2'!$G$1:$CU$424,30,0) -> 0 | PS7: =VLOOKUP(AG7,'BUS 2'!$G$1:$CU$424,31,0) -> 1 | PT7: 1-Disebarkan ke lahan terbuka | PU7: 1 | PV7: 0 | PW7: 0 | PX7: 0 | PY7: 0 | PZ7: 0 | QA7: 1 | QB7: 0 | QC7: 0 | QD7: 0 | SY7: =VLOOKUP(AG7,'BUS 2'!$G$1:$CU$424,33,0) -> 3 | SZ7: =VLOOKUP(AG7,'BUS 2'!$G$1:$CU$424,34,0) | TA7: =VLOOKUP(AG7,'BUS 2'!$G$1:$CU$424,35,0) | TB7: =VLOOKUP(AG7,'BUS 2'!$G$1:$CU$424,36,0) | TC7: =VLOOKUP(AG7,'BUS 2'!$G$1:$CU$424,37,0) | TD7: =VLOOKUP(AG7,'BUS 2'!$G$1:$CU$424,38,0) | TE7: =VLOOKUP(AG7,'BUS 2'!$G$1:$CU$424,39,0) | TF7: =VLOOKUP(AG7,'BUS 2'!$G$1:$CU$424,40,0) | TG7: =VLOOKUP(AG7,'BUS 2'!$G$1:$CU$424,42,0) -> 3 | TH7: =VLOOKUP(AG7,'BUS 2'!$G$1:$CU$424,43,0) | TI7: =VLOOKUP(AG7,'BUS 2'!$G$1:$CU$424,44,0) | TJ7: =VLOOKUP(AG7,'BUS 2'!$G$1:$CU$424,45,0) | TK7: =VLOOKUP(AG7,'BUS 2'!$G$1:$CU$424,46,0) | TL7: =VLOOKUP(AG7,'BUS 2'!$G$1:$CU$424,47,0) | TM7: =VLOOKUP(AG7,'BUS 2'!$G$1:$CU$424,48,0) | TN7: =VLOOKUP(AG7,'BUS 2'!$G$1:$CU$424,49,0) | TO7: =VLOOKUP(AG7,'BUS 2'!$G$1:$CU$424,50,0) | TP7: =VLOOKUP(AG7,'BUS 2'!$G$1:$CU$424,51,0) | TQ7: =VLOOKUP(AG7,'BUS 2'!$G$1:$CU$424,52,0) | TR7: =VLOOKUP(AG7,'BUS 2'!$G$1:$CU$424,53,0) | TS7: =VLOOKUP(AG7,'BUS 2'!$G$1:$CU$424,54,0) | TT7: =VLOOKUP(AG7,'BUS 2'!$G$1:$CU$424,55,0) | TU7: =VLOOKUP(AG7,'BUS 2'!$G$1:$CU$424,56,0) | TV7: =VLOOKUP(AG7,'BUS 2'!$G$1:$CU$424,57,0) | TW7: =VLOOKUP(AG7,'BUS 2'!$G$1:$CU$424,58,0) | TX7: =VLOOKUP(AG7,'BUS 2'!$G$1:$CU$424,59,0) | TY7: =VLOOKUP(AG7,'BUS 2'!$G$1:$CU$424,60,0) | TZ7: =VLOOKUP(AG7,'BUS 2'!$G$1:$CU$424,61,0) | UA7: =VLOOKUP(AG7,'BUS 2'!$G$1:$CU$424,62,0) | UB7: =VLOOKUP(AG7,'BUS 2'!$G$1:$CU$424,63,0) | UC7: =VLOOKUP(AG7,'BUS 2'!$G$1:$CU$424,64,0) | UD7: =VLOOKUP(AG7,'BUS 2'!$G$1:$CU$424,65,0) | UE7: =VLOOKUP(AG7,'BUS 2'!$G$1:$CU$424,66,0) | UF7: =VLOOKUP(AG7,'BUS 2'!$G$1:$CU$424,67,0) | UG7: =VLOOKUP(AG7,'BUS 2'!$G$1:$CU$424,68,0) | UH7: =VLOOKUP(AG7,'BUS 2'!$G$1:$CU$424,69,0) | UI7: =VLOOKUP(AG7,'BUS 2'!$G$1:$CU$424,70,0) | UJ7: =VLOOKUP(AG7,'BUS 2'!$G$1:$CU$424,71,0) | UK7: =VLOOKUP(AG7,'BUS 2'!$G$1:$CU$424,72,0) | UL7: =VLOOKUP(AG7,'BUS 2'!$G$1:$CU$424,73,0) | UM7: =VLOOKUP(AG7,'BUS 2'!$G$1:$CU$424,74,0) | UN7: =VLOOKUP(AG7,'BUS 2'!$G$1:$CU$424,75,0) | UO7: =VLOOKUP(AG7,'BUS 2'!$G$1:$CU$424,76,0) | UP7: =VLOOKUP(AG7,'BUS 2'!$G$1:$CU$424,77,0) | UQ7: =VLOOKUP(AG7,'BUS 2'!$G$1:$CU$424,78,0) | UR7: =VLOOKUP(AG7,'BUS 2'!$G$1:$CU$424,79,0) | US7: =VLOOKUP(AG7,'BUS 2'!$G$1:$CU$424,80,0) | UT7: =VLOOKUP(AG7,'BUS 2'!$G$1:$CU$424,81,0) | AAL7: Ya | AAM7: Padat Cair | AAN7: 1 | AAO7: 1 | AAP7: 45 | AAQ7: 45 | AAR7: Ya | AAS7: Mengetahui | AAT7: Digunakan untuk pupuk di lahan pertanian sendiri Diberikan gratis ke orang lain | AAU7: 1 | AAV7: 0 | AAW7: 0 | AAX7: 0 | AAY7: 1 | AAZ7: 0 | ABA7: 0 | ABB7: Pupuk cair untuk tanaman | ABC7: 1 | ABD7: 0 | ABE7: 0 | ABF7: 0 | ABG7: 0 | ABQ7: Rumput | ABR7: Cukup (2 minggu sekali) | ABS7: 2000 | ABU7: 45 | ABV7: 45 | ABW7: NPK | ABY7: 40 | ABZ7: 4000 | ACA7: 20 | ACB7: 5000 | ACC7: 500 | ACD7: 500 | ACE7: Ya | ACF7: Cukup meningkat | ACG7: Menurun | ACH7: Cukup meningkat | ACK7: Tidak punya waktu mengumpulkannya Ladang/sawah terlalu jauh, sulit untuk mengangkut ke sana | ACL7: 0 | ACM7: 0 | ACN7: 1 | ACO7: 1 | ACP7: 0 | ACQ7: 0 | ACR7: 0 | ACT7: tidak | ACU7: Manfaat cukup signifikan, terasa di kehidupan sehari-hari | ACV7: Berkurang | ACW7: Anggota keluarga - Perempuan dewasa | ACX7: Setuju | ACY7: Anggota keluarga - Laki-laki dewasa Anggota keluarga - Perempuan dewasa | ACZ7: 1 | ADA7: 1 | ADB7: 0 | ADC7: 0 | ADD7: Cukup puas | ADE7: Cukup puas | ADF7: Cukup puas | ADG7: Cukup puas | ADH7: Tidak | ADJ7: Cukup puas | ADU7: Menghubungi CPO atau pendamping Memperbaiki sendiri | ADV7: 0 | ADW7: 0 | ADX7: 0 | ADY7: 0 | ADZ7: 1 | AEA7: 1 | AEB7: 0 | AEC7: 0 | AEE7: Laki-laki dewasa | AEG7: Menelepon atau WA langsung | AEI7: Tidak ada | AEJ7: Kadang-kadang | AEK7: Lebih mudah mendapatkan energi Pasokan energi yang andal Memasak lebih cepat Lebih aman Pengurangan waktu dan tenaga Peningkatan kebersihan kandang ternak Pemanfaatan bio-slurry sebagai pupuk Dapur lebih bersih dan bebas asap | AEL7: 0 | AEM7: 1 | AEN7: 1 | AEO7: 1 | AEP7: 1 | AEQ7: 1 | AER7: 1 | AES7: 1 | AET7: 1 | AEU7: 0 | AEV7: 0 | AEW7: 0 | AEY7: Mengurangi pengeluaran energi | AFA7: Yayasan Rumah Energi (YRE) | AFC7: WhatsApp Image 2026-02-03 at 14.15.32-21_27_21.jpeg | AFD7: https://kf.kobotoolbox.org/api/v2/assets/avstPQqLr3Ab3ZdcVTXZ6f/data/663732541/attachments/attdwtkkxxWMPXzr9nFauzRu/ | AFE7: WhatsApp Image 2026-02-03 at 14.15.32 (1)-21_27_31.jpeg | AFF7: https://kf.kobotoolbox.org/api/v2/assets/avstPQqLr3Ab3ZdcVTXZ6f/data/663732541/attachments/attTDpcqVFTdYLvZAYYmCEtF/ | AFG7: manto / witono
A8: 46057 | B8: 46057 | C8: Marmanto | D8: Subagyo | E8: 6282128590068 | G8: -7.4256713 | H8: 110.335 | J8: 4.58 | M8: -7.4255 | N8: 110.335 | P8: 4.98 | R8: Jawa Tengah | AC8: Klaten | AD8: Kebon Arum | AE8: Gondang | AF8: RUMAH ILHAM | AG8: HIP0213 | AH8: 6 | AI8: VPA2 | AJ8: Tidak aktif | AK8: 60 | AL8: Laki-laki | AM8: Sudah menikah | AN8: SD/Sederajat | AO8: Petani | AP8: 1 | AQ8: 0 | AR8: 0 | AS8: 0 | AT8: 0 | AU8: 0 | AV8: 0 | AW8: 0 | AY8: Peternak | AZ8: 0 | BA8: 1 | BB8: 0 | BC8: 0 | BD8: 0 | BE8: 0 | BF8: 0 | BG8: 0 | BI8: Rp2.500.000 - Rp3.500.000 | BJ8: 1 | BK8: 3 | BL8: 0 | BM8: 0 | BN8: Milik sendiri | BO8: Permanen (dinding bata dan semen) | BP8: 1 | BQ8: 0 | BR8: 0 | BS8: 0 | BT8: 0 | BV8: Keramik/ubin | BW8: 0 | BX8: 0 | BY8: 1 | BZ8: 0 | CA8: 0 | CC8: Genting | CD8: 0 | CE8: 0 | CF8: 0 | CG8: 0 | CH8: 0 | CI8: 1 | CJ8: 0 | CL8: Ya | CM8: 2020 | CN8: Fixed-Dome (Kubah Tetap) | CO8: 6 m³ (4-5 ekor sapi, ±5 jam memasak/hari, ±50 kg | CP8: Anggota keluarga - laki-laki | CQ8: 0 | CR8: 0 | CS8: 0 | CT8: 0 | CU8: 1 | CV8: 0 | CW8: 0 | CX8: 0 | CY8: Anggota keluarga - laki-laki | CZ8: 1 | DA8: 0 | DB8: 0 | DD8: Anggota keluarga - laki-laki CPO atau pendamping | DE8: 1 | DF8: 0 | DG8: 1 | DH8: 0 | DJ8: Anggota keluarga - laki-laki CPO atau pendamping | DK8: 1 | DL8: 0 | DM8: 1 | DN8: 0 | DP8: 1 | DQ8: 0 | DR8: 0 | DV8: Tidak berfungsi sama sekali | DW8: >1 tahun yang lalu | DX8: Tidak ada ternak | EI8: Kurangnya dukungan atau pemantauan dari pemerintah atau CPO Keterbatasan akses terhadap informasi atau pelatihan terkait biogas | EJ8: 0 | EK8: 1 | EL8: 1 | EM8: 0 | EN8: 0 | EP8: Ya, cukup jelas dan mudah diikuti | EQ8: Pelatihan | ER8: CPO atau pendamping Staff BIRU | ES8: 1 | ET8: 1 | EU8: 0 | EV8: 0 | EX8: Anggota keluarga - Laki-laki | EY8: 1 | EZ8: 0 | FA8: 0 | FC8: Setiap minggu | FE8: Mengetahui | FF8: Cukup sering (2 minggu sekali) | FG8: Mengetahui | FH8: Sering (setiap minggu) | FI8: Mengetahui | FJ8: Sering (setiap minggu) | FK8: Mengetahui | FL8: Cukup sering (2 minggu sekali) | FM8: Mengetahui | FN8: Jarang (setiap bulan atau lebih) | FO8: Mengetahui | FP8: Cukup sering (2 minggu sekali) | FQ8: Mengetahui | FR8: Ya | FS8: Mengetahui | FT8: Ya, selalu | FU8: Laki-laki dewasa Perempuan dewasa | FV8: 1 | FW8: 1 | FX8: 0 | FY8: 0 | FZ8: Cukup memahami | GA8: CPO Pelatihan | GB8: 1 | GC8: 1 | GD8: 0 | GE8: 0 | GG8: Sering | GH8: Tidak | GP8: Penuh (100%) | GQ8: Kayu bakar LPG | GR8: 1 | GS8: 1 | GT8: 0 | GU8: 0 | GV8: 0 | GW8: 0 | GX8: 0 | GZ8: Ya | HA8: 150 | HB8: 175000 | HC8: 50 | HD8: 50000 | HE8: 12 | HF8: 100000 | HG8: 3 | HH8: 25000 | HY8: 100 | HZ8: 100000 | IA8: 9 | IB8: 75000 | IK8: 50-65 kg | IL8: 3-5 jam | IM8: Ya | IN8: Tidak | IO8: Lebih bersih | IQ8: Tidak pernah | IZ8: Tidak pernah | JI8: Tidak pernah | JR8: Tidak pernah | KA8: Tidak pernah | KJ8: Tidak pernah | KS8: Cukup membaik | KT8: 0-1 kali | KU8: 0-1 kali | KV8: Laki-laki dewasa Perempuan dewasa | KW8: 1 | KX8: 1 | KY8: 0 | KZ8: 0 | LA8: Cukup membaik | LB8: Cukup membaik | LC8: 0 | LD8: 0 | LE8: 0 | LF8: 0 | LG8: Ya | LH8: 150000 | LJ8: Kebutuhan rumah tangga | LK8: 0 | LL8: 0 | LM8: 0 | LN8: 0 | LO8: 1 | LP8: 0 | LQ8: 0 | LS8: 15 | LT8: 15 | LU8: 0 | LV8: 5 | LW8: 5 | LX8: 0 | LY8: 5 | LZ8: 5 | MA8: 0 | MB8: Ya | MC8: 30 | MD8: 15 | ME8: 30 | MF8: 15 | MG8: 0 | MH8: 0 | MI8: Istirahat, Pendidikan diri sendiri | MJ8: 0 | MK8: 0 | ML8: 1 | MM8: 1 | MN8: 0 | MO8: 0 | MR8: istirahat | MT8: kumpul keluarga | MU8: Ya, untuk anggota keluarga | MV8: Perawatan sistem biogas | MW8: 1 | MX8: 0 | MY8: 0 | MZ8: 0 | NL8: Tidak | NM8: Kombinasi dana mandiri dan dana hibah | NN8: >11.000.001 | NO8: Program yayasan/NGO | NV8: Anggota keluarga - Laki-laki dewasa | NX8: Sedikit meningkat | NY8: 40 | NZ8: 20 | OA8: 0 | OB8: 10 | OC8: 10 | OD8: 0 | OE8: Lebih baik | OF8: Lebih baik (beda waktu memasak 5-30 menit, ATAU tidak lagi ada rasa/bau makanan yang berubah, ATAU alasan lainnya) | OG8: Ya | OH8: 0 | OI8: 0 | OJ8: 0 | OK8: 0 | OL8: 0 | OM8: 0 | ON8: 0 | OO8: 0 | OP8: =VLOOKUP(AG8,'BUS 2'!$G$1:$CU$424,2,0) -> Sapi pedaging | OQ8: =VLOOKUP(AG8,'BUS 2'!$G$1:$CU$424,3,0) -> 1 | OR8: =VLOOKUP(AG8,'BUS 2'!$G$1:$CU$424,4,0) -> 0 | OS8: =VLOOKUP(AG8,'BUS 2'!$G$1:$CU$424,5,0) -> 0 | OT8: =VLOOKUP(AG8,'BUS 2'!$G$1:$CU$424,6,0) -> 0 | OU8: =VLOOKUP(AG8,'BUS 2'!$G$1:$CU$424,7,0) -> 0 | OV8: =VLOOKUP(AG8,'BUS 2'!$G$1:$CU$424,8,0) -> 0 | OW8: =VLOOKUP(AG8,'BUS 2'!$G$1:$CU$424,9,0) -> 0 | OX8: =VLOOKUP(AG8,'BUS 2'!$G$1:$CU$424,10,0) -> 0 | OY8: =VLOOKUP(AG8,'BUS 2'!$G$1:$CU$424,11,0) -> 0 | OZ8: =VLOOKUP(AG8,'BUS 2'!$G$1:$CU$424,12,0) -> Sapi pedaging | PA8: =VLOOKUP(AG8,'BUS 2'!$G$1:$CU$424,13,0) -> 1 | PB8: =VLOOKUP(AG8,'BUS 2'!$G$1:$CU$424,14,0) -> 0 | PC8: =VLOOKUP(AG8,'BUS 2'!$G$1:$CU$424,15,0) -> 0 | PD8: =VLOOKUP(AG8,'BUS 2'!$G$1:$CU$424,16,0) -> 0 | PE8: =VLOOKUP(AG8,'BUS 2'!$G$1:$CU$424,17,0) -> 0 | PF8: =VLOOKUP(AG8,'BUS 2'!$G$1:$CU$424,18,0) -> 0 | PG8: =VLOOKUP(AG8,'BUS 2'!$G$1:$CU$424,19,0) -> 0 | PH8: =VLOOKUP(AG8,'BUS 2'!$G$1:$CU$424,20,0) -> 0 | PI8: =VLOOKUP(AG8,'BUS 2'!$G$1:$CU$424,21,0) -> 0 | PJ8: =VLOOKUP(AG8,'BUS 2'!$G$1:$CU$424,22,0) -> Tidak ada | PK8: =VLOOKUP(AG8,'BUS 2'!$G$1:$CU$424,23,0) -> 0 | PL8: =VLOOKUP(AG8,'BUS 2'!$G$1:$CU$424,24,0) -> 0 | PM8: =VLOOKUP(AG8,'BUS 2'!$G$1:$CU$424,25,0) -> 0 | PN8: =VLOOKUP(AG8,'BUS 2'!$G$1:$CU$424,26,0) -> 0 | PO8: =VLOOKUP(AG8,'BUS 2'!$G$1:$CU$424,27,0) -> 0 | PP8: =VLOOKUP(AG8,'BUS 2'!$G$1:$CU$424,28,0) -> 0 | PQ8: =VLOOKUP(AG8,'BUS 2'!$G$1:$CU$424,29,0) -> 0 | PR8: =VLOOKUP(AG8,'BUS 2'!$G$1:$CU$424,30,0) -> 0 | PS8: =VLOOKUP(AG8,'BUS 2'!$G$1:$CU$424,31,0) -> 1 | PT8: 1-Disebarkan ke lahan terbuka | PU8: 1 | PV8: 0 | PW8: 0 | PX8: 0 | PY8: 0 | PZ8: 0 | QA8: 1 | QB8: 0 | QC8: 0 | QD8: 0 | SY8: =VLOOKUP(AG8,'BUS 2'!$G$1:$CU$424,33,0) -> 2 | SZ8: =VLOOKUP(AG8,'BUS 2'!$G$1:$CU$424,34,0) | TA8: =VLOOKUP(AG8,'BUS 2'!$G$1:$CU$424,35,0) | TB8: =VLOOKUP(AG8,'BUS 2'!$G$1:$CU$424,36,0) | TC8: =VLOOKUP(AG8,'BUS 2'!$G$1:$CU$424,37,0) | TD8: =VLOOKUP(AG8,'BUS 2'!$G$1:$CU$424,38,0) | TE8: =VLOOKUP(AG8,'BUS 2'!$G$1:$CU$424,39,0) | TF8: =VLOOKUP(AG8,'BUS 2'!$G$1:$CU$424,40,0) | TG8: =VLOOKUP(AG8,'BUS 2'!$G$1:$CU$424,42,0) -> 2 | TH8: =VLOOKUP(AG8,'BUS 2'!$G$1:$CU$424,43,0) | TI8: =VLOOKUP(AG8,'BUS 2'!$G$1:$CU$424,44,0) | TJ8: =VLOOKUP(AG8,'BUS 2'!$G$1:$CU$424,45,0) | TK8: =VLOOKUP(AG8,'BUS 2'!$G$1:$CU$424,46,0) | TL8: =VLOOKUP(AG8,'BUS 2'!$G$1:$CU$424,47,0) | TM8: =VLOOKUP(AG8,'BUS 2'!$G$1:$CU$424,48,0) | TN8: =VLOOKUP(AG8,'BUS 2'!$G$1:$CU$424,49,0) | TO8: =VLOOKUP(AG8,'BUS 2'!$G$1:$CU$424,50,0) | TP8: =VLOOKUP(AG8,'BUS 2'!$G$1:$CU$424,51,0) | TQ8: =VLOOKUP(AG8,'BUS 2'!$G$1:$CU$424,52,0) | TR8: =VLOOKUP(AG8,'BUS 2'!$G$1:$CU$424,53,0) | TS8: =VLOOKUP(AG8,'BUS 2'!$G$1:$CU$424,54,0) | TT8: =VLOOKUP(AG8,'BUS 2'!$G$1:$CU$424,55,0) | TU8: =VLOOKUP(AG8,'BUS 2'!$G$1:$CU$424,56,0) | TV8: =VLOOKUP(AG8,'BUS 2'!$G$1:$CU$424,57,0) | TW8: =VLOOKUP(AG8,'BUS 2'!$G$1:$CU$424,58,0) | TX8: =VLOOKUP(AG8,'BUS 2'!$G$1:$CU$424,59,0) | TY8: =VLOOKUP(AG8,'BUS 2'!$G$1:$CU$424,60,0) | TZ8: =VLOOKUP(AG8,'BUS 2'!$G$1:$CU$424,61,0) | UA8: =VLOOKUP(AG8,'BUS 2'!$G$1:$CU$424,62,0) | UB8: =VLOOKUP(AG8,'BUS 2'!$G$1:$CU$424,63,0) | UC8: =VLOOKUP(AG8,'BUS 2'!$G$1:$CU$424,64,0) | UD8: =VLOOKUP(AG8,'BUS 2'!$G$1:$CU$424,65,0) | UE8: =VLOOKUP(AG8,'BUS 2'!$G$1:$CU$424,66,0) | UF8: =VLOOKUP(AG8,'BUS 2'!$G$1:$CU$424,67,0) | UG8: =VLOOKUP(AG8,'BUS 2'!$G$1:$CU$424,68,0) | UH8: =VLOOKUP(AG8,'BUS 2'!$G$1:$CU$424,69,0) | UI8: =VLOOKUP(AG8,'BUS 2'!$G$1:$CU$424,70,0) | UJ8: =VLOOKUP(AG8,'BUS 2'!$G$1:$CU$424,71,0) | UK8: =VLOOKUP(AG8,'BUS 2'!$G$1:$CU$424,72,0) | UL8: =VLOOKUP(AG8,'BUS 2'!$G$1:$CU$424,73,0) | UM8: =VLOOKUP(AG8,'BUS 2'!$G$1:$CU$424,74,0) | UN8: =VLOOKUP(AG8,'BUS 2'!$G$1:$CU$424,75,0) | UO8: =VLOOKUP(AG8,'BUS 2'!$G$1:$CU$424,76,0) | UP8: =VLOOKUP(AG8,'BUS 2'!$G$1:$CU$424,77,0) | UQ8: =VLOOKUP(AG8,'BUS 2'!$G$1:$CU$424,78,0) | UR8: =VLOOKUP(AG8,'BUS 2'!$G$1:$CU$424,79,0) | US8: =VLOOKUP(AG8,'BUS 2'!$G$1:$CU$424,80,0) | UT8: =VLOOKUP(AG8,'BUS 2'!$G$1:$CU$424,81,0) | AAL8: Tidak | AAR8: Ya | AAS8: Mengetahui | AAT8: Digunakan untuk pupuk di lahan pertanian sendiri Diberikan gratis ke orang lain | AAU8: 1 | AAV8: 0 | AAW8: 0 | AAX8: 0 | AAY8: 1 | AAZ8: 0 | ABA8: 0 | ABB8: Pupuk cair untuk tanaman Pembenah tanah (soil conditioner) | ABC8: 1 | ABD8: 1 | ABE8: 0 | ABF8: 0 | ABG8: 0 | ABQ8: Rumput | ABR8: Cukup (2 minggu sekali) | ABS8: 2000 | ABU8: 400 | ABV8: 400 | ABW8: NPK | ABY8: 50 | ABZ8: 6000 | ACA8: 20 | ACB8: 6000 | ACC8: 500 | ACD8: 700 | ACE8: Tidak | ACF8: Cukup meningkat | ACG8: Menurun | ACH8: Cukup meningkat | ACK8: Tidak punya waktu mengumpulkannya Ladang/sawah terlalu jauh, sulit untuk mengangkut ke sana | ACL8: 0 | ACM8: 0 | ACN8: 1 | ACO8: 1 | ACP8: 0 | ACQ8: 0 | ACR8: 0 | ACT8: tidak | ACU8: Manfaat besar dan membantu kehidupan sehari-hari | ACV8: Berkurang | ACW8: Anggota keluarga - Perempuan dewasa | ACX8: Setuju | ACY8: Anggota keluarga - Laki-laki dewasa Anggota keluarga - Perempuan dewasa Anggota keluarga - Anak-anak | ACZ8: 1 | ADA8: 1 | ADB8: 1 | ADC8: 0 | ADD8: Cukup puas | ADE8: Cukup puas | ADF8: Cukup puas | ADG8: Cukup puas | ADH8: Tidak | ADJ8: Cukup puas | ADU8: Menghubungi CPO atau pendamping Memperbaiki sendiri | ADV8: 0 | ADW8: 0 | ADX8: 0 | ADY8: 0 | ADZ8: 1 | AEA8: 1 | AEB8: 0 | AEC8: 0 | AEE8: Laki-laki dewasa | AEG8: Menelepon atau WA langsung | AEI8: Tidak ada | AEJ8: Kadang-kadang | AEK8: Lebih mudah mendapatkan energi Pasokan energi yang andal Memasak lebih cepat Lebih aman Pengurangan waktu dan tenaga Peningkatan kebersihan kandang ternak Pemanfaatan bio-slurry sebagai pupuk Dapur lebih bersih dan bebas asap | AEL8: 0 | AEM8: 1 | AEN8: 1 | AEO8: 1 | AEP8: 1 | AEQ8: 1 | AER8: 1 | AES8: 1 | AET8: 1 | AEU8: 0 | AEV8: 0 | AEW8: 0 | AEY8: Mengurangi pengeluaran energi | AFA8: Yayasan Rumah Energi (YRE) | AFC8: WhatsApp Image 2026-02-03 at 14.16.25-21_57_46.jpeg | AFD8: https://kf.kobotoolbox.org/api/v2/assets/avstPQqLr3Ab3ZdcVTXZ6f/data/663773956/attachments/attbVJCDPFzqny5Mf2G4f76U/ | AFE8: WhatsApp Image 2026-02-03 at 14.16.26-21_58_0.jpeg | AFF8: https://kf.kobotoolbox.org/api/v2/assets/avstPQqLr3Ab3ZdcVTXZ6f/data/663773956/attachments/attuqTD9rXWjdtcYHAXBTusn/ | AFG8: manto/ witono
A9: 46057 | B9: 46057 | C9: Marmanto | D9: Gito Suparno | E9: 6282133265228 | G9: -7.41793 | H9: 110.33123 | J9: 4.4 | M9: -7.41784 | N9: 110.3312 | P9: 4.48 | R9: Jawa Tengah | AC9: Klaten | AD9: Kebon Arum | AE9: Menden | AF9: SPTN HPS | AG9: SHP0076 | AH9: 14 | AI9: VPA1 | AJ9: Tidak aktif | AK9: 60 | AL9: Laki-laki | AM9: Sudah menikah | AN9: SD/Sederajat | AO9: Petani | AP9: 1 | AQ9: 0 | AR9: 0 | AS9: 0 | AT9: 0 | AU9: 0 | AV9: 0 | AW9: 0 | AY9: Peternak | AZ9: 0 | BA9: 1 | BB9: 0 | BC9: 0 | BD9: 0 | BE9: 0 | BF9: 0 | BG9: 0 | BI9: Rp2.500.000 - Rp3.500.000 | BJ9: 1 | BK9: 1 | BL9: 0 | BM9: 0 | BN9: Milik sendiri | BO9: Permanen (dinding bata dan semen) | BP9: 1 | BQ9: 0 | BR9: 0 | BS9: 0 | BT9: 0 | BV9: Keramik/ubin | BW9: 0 | BX9: 0 | BY9: 1 | BZ9: 0 | CA9: 0 | CC9: Genting | CD9: 0 | CE9: 0 | CF9: 0 | CG9: 0 | CH9: 0 | CI9: 1 | CJ9: 0 | CL9: Ya | CM9: 2012 | CN9: Fixed-Dome (Kubah Tetap) | CO9: 6 m³ (4-5 ekor sapi, ±5 jam memasak/hari, ±50 kg | CP9: Anggota keluarga - laki-laki Anggota keluarga - perempuan dewasa | CQ9: 0 | CR9: 0 | CS9: 0 | CT9: 0 | CU9: 1 | CV9: 1 | CW9: 0 | CX9: 0 | CY9: Anggota keluarga - laki-laki Anggota keluarga - perempuan dewasa | CZ9: 1 | DA9: 1 | DB9: 0 | DD9: Anggota keluarga - laki-laki CPO atau pendamping | DE9: 1 | DF9: 0 | DG9: 1 | DH9: 0 | DJ9: Anggota keluarga - laki-laki CPO atau pendamping | DK9: 1 | DL9: 0 | DM9: 1 | DN9: 0 | DP9: 1 | DQ9: 1 | DR9: 0 | DV9: Tidak berfungsi sama sekali | DW9: >1 tahun yang lalu | DX9: Tidak ada ternak | EI9: Keterbatasan akses terhadap informasi atau pelatihan terkait biogas | EJ9: 0 | EK9: 0 | EL9: 1 | EM9: 0 | EN9: 0 | EP9: Ya, cukup jelas dan mudah diikuti | EQ9: Pelatihan | ER9: CPO atau pendamping | ES9: 1 | ET9: 0 | EU9: 0 | EV9: 0 | EX9: Anggota keluarga - Laki-laki | EY9: 1 | EZ9: 0 | FA9: 0 | FC9: Setiap minggu | FE9: Mengetahui | FF9: Selalu (setiap hari) | FG9: Mengetahui | FH9: Sering (setiap minggu) | FI9: Mengetahui | FJ9: Sering (setiap minggu) | FK9: Mengetahui | FL9: Jarang (setiap bulan atau lebih) | FM9: Mengetahui | FN9: Jarang (setiap bulan atau lebih) | FO9: Mengetahui | FP9: Cukup sering (2 minggu sekali) | FQ9: Mengetahui | FR9: Ya | FS9: Mengetahui | FT9: Ya, selalu | FU9: Laki-laki dewasa Perempuan dewasa | FV9: 1 | FW9: 1 | FX9: 0 | FY9: 0 | FZ9: Cukup memahami | GA9: CPO Pelatihan | GB9: 1 | GC9: 1 | GD9: 0 | GE9: 0 | GG9: Sering | GH9: Tidak | GP9: Penuh (100%) | GQ9: Kayu bakar LPG | GR9: 1 | GS9: 1 | GT9: 0 | GU9: 0 | GV9: 0 | GW9: 0 | GX9: 0 | GZ9: Ya | HA9: 200 | HB9: 200000 | HC9: 50 | HD9: 50000 | HE9: 12 | HF9: 25000 | HG9: 3 | HH9: 25000 | HY9: 150 | HZ9: 150000 | IA9: 9 | IB9: 75000 | IK9: 50-65 kg | IL9: 3-5 jam | IM9: Ya | IN9: Tidak | IO9: Lebih bersih | IQ9: Tidak pernah | IZ9: Tidak pernah | JI9: Tidak pernah | JR9: Tidak pernah | KA9: Tidak pernah | KJ9: Tidak pernah | KS9: Cukup membaik | KT9: 0-1 kali | KU9: 0-1 kali | KV9: Laki-laki dewasa | KW9: 1 | KX9: 0 | KY9: 0 | KZ9: 0 | LA9: Cukup membaik | LB9: Cukup membaik | LC9: 3 | LD9: 3 | LE9: 0 | LF9: 0 | LG9: Ya | LH9: 150000 | LJ9: Kebutuhan rumah tangga | LK9: 0 | LL9: 0 | LM9: 0 | LN9: 0 | LO9: 1 | LP9: 0 | LQ9: 0 | LS9: 15 | LT9: 15 | LU9: 0 | LV9: 5 | LW9: 5 | LX9: 0 | LY9: 5 | LZ9: 5 | MA9: 0 | MB9: Ya | MC9: 30 | MD9: 20 | ME9: 30 | MF9: 20 | MG9: 0 | MH9: 0 | MI9: Istirahat | MJ9: 0 | MK9: 0 | ML9: 1 | MM9: 0 | MN9: 0 | MO9: 0 | MR9: istirahat | MT9: kumpul keluarga | MU9: Tidak | NL9: Tidak | NM9: Kombinasi dana mandiri dan dana hibah | NN9: 9.000.001-11.000.000 | NO9: Pemerintah | NV9: Anggota keluarga - Laki-laki dewasa | NX9: Sedikit meningkat | NY9: 30 | NZ9: 30 | OA9: 0 | OB9: 5 | OC9: 5 | OD9: 0 | OE9: Lebih baik | OF9: Lebih baik (beda waktu memasak 5-30 menit, ATAU tidak lagi ada rasa/bau makanan yang berubah, ATAU alasan lainnya) | OG9: Ya | OH9: 0 | OI9: 0 | OJ9: 0 | OK9: 0 | OL9: 0 | OM9: 0 | ON9: 0 | OO9: 0 | OP9: =VLOOKUP(AG9,'BUS 2'!$G$1:$CU$424,2,0) -> Sapi perah | OQ9: =VLOOKUP(AG9,'BUS 2'!$G$1:$CU$424,3,0) -> 0 | OR9: =VLOOKUP(AG9,'BUS 2'!$G$1:$CU$424,4,0) -> 1 | OS9: =VLOOKUP(AG9,'BUS 2'!$G$1:$CU$424,5,0) -> 0 | OT9: =VLOOKUP(AG9,'BUS 2'!$G$1:$CU$424,6,0) -> 0 | OU9: =VLOOKUP(AG9,'BUS 2'!$G$1:$CU$424,7,0) -> 0 | OV9: =VLOOKUP(AG9,'BUS 2'!$G$1:$CU$424,8,0) -> 0 | OW9: =VLOOKUP(AG9,'BUS 2'!$G$1:$CU$424,9,0) -> 0 | OX9: =VLOOKUP(AG9,'BUS 2'!$G$1:$CU$424,10,0) -> 0 | OY9: =VLOOKUP(AG9,'BUS 2'!$G$1:$CU$424,11,0) -> 0 | OZ9: =VLOOKUP(AG9,'BUS 2'!$G$1:$CU$424,12,0) -> Sapi perah | PA9: =VLOOKUP(AG9,'BUS 2'!$G$1:$CU$424,13,0) -> 0 | PB9: =VLOOKUP(AG9,'BUS 2'!$G$1:$CU$424,14,0) -> 1 | PC9: =VLOOKUP(AG9,'BUS 2'!$G$1:$CU$424,15,0) -> 0 | PD9: =VLOOKUP(AG9,'BUS 2'!$G$1:$CU$424,16,0) -> 0 | PE9: =VLOOKUP(AG9,'BUS 2'!$G$1:$CU$424,17,0) -> 0 | PF9: =VLOOKUP(AG9,'BUS 2'!$G$1:$CU$424,18,0) -> 0 | PG9: =VLOOKUP(AG9,'BUS 2'!$G$1:$CU$424,19,0) -> 0 | PH9: =VLOOKUP(AG9,'BUS 2'!$G$1:$CU$424,20,0) -> 0 | PI9: =VLOOKUP(AG9,'BUS 2'!$G$1:$CU$424,21,0) -> 0 | PJ9: =VLOOKUP(AG9,'BUS 2'!$G$1:$CU$424,22,0) -> Tidak ada | PK9: =VLOOKUP(AG9,'BUS 2'!$G$1:$CU$424,23,0) -> 0 | PL9: =VLOOKUP(AG9,'BUS 2'!$G$1:$CU$424,24,0) -> 0 | PM9: =VLOOKUP(AG9,'BUS 2'!$G$1:$CU$424,25,0) -> 0 | PN9: =VLOOKUP(AG9,'BUS 2'!$G$1:$CU$424,26,0) -> 0 | PO9: =VLOOKUP(AG9,'BUS 2'!$G$1:$CU$424,27,0) -> 0 | PP9: =VLOOKUP(AG9,'BUS 2'!$G$1:$CU$424,28,0) -> 0 | PQ9: =VLOOKUP(AG9,'BUS 2'!$G$1:$CU$424,29,0) -> 0 | PR9: =VLOOKUP(AG9,'BUS 2'!$G$1:$CU$424,30,0) -> 0 | PS9: =VLOOKUP(AG9,'BUS 2'!$G$1:$CU$424,31,0) -> 1 | PT9: 1-Disebarkan ke lahan terbuka | PU9: 1 | PV9: 0 | PW9: 0 | PX9: 0 | PY9: 0 | PZ9: 0 | QA9: 1 | QB9: 0 | QC9: 0 | QD9: 0 | SY9: =VLOOKUP(AG9,'BUS 2'!$G$1:$CU$424,33,0) | SZ9: =VLOOKUP(AG9,'BUS 2'!$G$1:$CU$424,34,0) -> 3 | TA9: =VLOOKUP(AG9,'BUS 2'!$G$1:$CU$424,35,0) | TB9: =VLOOKUP(AG9,'BUS 2'!$G$1:$CU$424,36,0) | TC9: =VLOOKUP(AG9,'BUS 2'!$G$1:$CU$424,37,0) | TD9: =VLOOKUP(AG9,'BUS 2'!$G$1:$CU$424,38,0) | TE9: =VLOOKUP(AG9,'BUS 2'!$G$1:$CU$424,39,0) | TF9: =VLOOKUP(AG9,'BUS 2'!$G$1:$CU$424,40,0) | TG9: =VLOOKUP(AG9,'BUS 2'!$G$1:$CU$424,42,0) | TH9: =VLOOKUP(AG9,'BUS 2'!$G$1:$CU$424,43,0) -> 3 | TI9: =VLOOKUP(AG9,'BUS 2'!$G$1:$CU$424,44,0) | TJ9: =VLOOKUP(AG9,'BUS 2'!$G$1:$CU$424,45,0) | TK9: =VLOOKUP(AG9,'BUS 2'!$G$1:$CU$424,46,0) | TL9: =VLOOKUP(AG9,'BUS 2'!$G$1:$CU$424,47,0) | TM9: =VLOOKUP(AG9,'BUS 2'!$G$1:$CU$424,48,0) | TN9: =VLOOKUP(AG9,'BUS 2'!$G$1:$CU$424,49,0) | TO9: =VLOOKUP(AG9,'BUS 2'!$G$1:$CU$424,50,0) | TP9: =VLOOKUP(AG9,'BUS 2'!$G$1:$CU$424,51,0) | TQ9: =VLOOKUP(AG9,'BUS 2'!$G$1:$CU$424,52,0) | TR9: =VLOOKUP(AG9,'BUS 2'!$G$1:$CU$424,53,0) | TS9: =VLOOKUP(AG9,'BUS 2'!$G$1:$CU$424,54,0) | TT9: =VLOOKUP(AG9,'BUS 2'!$G$1:$CU$424,55,0) | TU9: =VLOOKUP(AG9,'BUS 2'!$G$1:$CU$424,56,0) | TV9: =VLOOKUP(AG9,'BUS 2'!$G$1:$CU$424,57,0) | TW9: =VLOOKUP(AG9,'BUS 2'!$G$1:$CU$424,58,0) | TX9: =VLOOKUP(AG9,'BUS 2'!$G$1:$CU$424,59,0) | TY9: =VLOOKUP(AG9,'BUS 2'!$G$1:$CU$424,60,0) | TZ9: =VLOOKUP(AG9,'BUS 2'!$G$1:$CU$424,61,0) | UA9: =VLOOKUP(AG9,'BUS 2'!$G$1:$CU$424,62,0) | UB9: =VLOOKUP(AG9,'BUS 2'!$G$1:$CU$424,63,0) | UC9: =VLOOKUP(AG9,'BUS 2'!$G$1:$CU$424,64,0) | UD9: =VLOOKUP(AG9,'BUS 2'!$G$1:$CU$424,65,0) | UE9: =VLOOKUP(AG9,'BUS 2'!$G$1:$CU$424,66,0) | UF9: =VLOOKUP(AG9,'BUS 2'!$G$1:$CU$424,67,0) | UG9: =VLOOKUP(AG9,'BUS 2'!$G$1:$CU$424,68,0) | UH9: =VLOOKUP(AG9,'BUS 2'!$G$1:$CU$424,69,0) | UI9: =VLOOKUP(AG9,'BUS 2'!$G$1:$CU$424,70,0) | UJ9: =VLOOKUP(AG9,'BUS 2'!$G$1:$CU$424,71,0) | UK9: =VLOOKUP(AG9,'BUS 2'!$G$1:$CU$424,72,0) | UL9: =VLOOKUP(AG9,'BUS 2'!$G$1:$CU$424,73,0) | UM9: =VLOOKUP(AG9,'BUS 2'!$G$1:$CU$424,74,0) | UN9: =VLOOKUP(AG9,'BUS 2'!$G$1:$CU$424,75,0) | UO9: =VLOOKUP(AG9,'BUS 2'!$G$1:$CU$424,76,0) | UP9: =VLOOKUP(AG9,'BUS 2'!$G$1:$CU$424,77,0) | UQ9: =VLOOKUP(AG9,'BUS 2'!$G$1:$CU$424,78,0) | UR9: =VLOOKUP(AG9,'BUS 2'!$G$1:$CU$424,79,0) | US9: =VLOOKUP(AG9,'BUS 2'!$G$1:$CU$424,80,0) | UT9: =VLOOKUP(AG9,'BUS 2'!$G$1:$CU$424,81,0) | AAL9: Tidak | AAR9: Ya | AAS9: Mengetahui | AAT9: Digunakan untuk pupuk di lahan pertanian sendiri Diberikan gratis ke orang lain | AAU9: 1 | AAV9: 0 | AAW9: 0 | AAX9: 0 | AAY9: 1 | AAZ9: 0 | ABA9: 0 | ABB9: Pupuk cair untuk tanaman | ABC9: 1 | ABD9: 0 | ABE9: 0 | ABF9: 0 | ABG9: 0 | ABQ9: Rumput | ABR9: Jarang (1 bulan sekali) | ABS9: 1500 | ABU9: 400 | ABV9: 400 | ABW9: NPK | ABY9: 50 | ABZ9: 6000 | ACA9: 20 | ACB9: 6000 | ACC9: 500 | ACD9: 700 | ACE9: Tidak | ACF9: Cukup meningkat | ACG9: Cukup meningkat | ACH9: Cukup meningkat | ACK9: Tidak punya waktu mengumpulkannya Ladang/sawah terlalu jauh, sulit untuk mengangkut ke sana | ACL9: 0 | ACM9: 0 | ACN9: 1 | ACO9: 1 | ACP9: 0 | ACQ9: 0 | ACR9: 0 | ACT9: TIDAK | ACU9: Manfaat besar dan membantu kehidupan sehari-hari | ACV9: Bertambah | ACW9: Anggota keluarga - Perempuan dewasa | ACX9: Netral/tidak tahu | ACY9: Anggota keluarga - Laki-laki dewasa Anggota keluarga - Perempuan dewasa | ACZ9: 1 | ADA9: 1 | ADB9: 0 | ADC9: 0 | ADD9: Cukup puas | ADE9: Cukup puas | ADF9: Cukup puas | ADG9: Cukup puas | ADH9: Tidak | ADJ9: Cukup puas | ADU9: Menghubungi CPO atau pendamping Memperbaiki sendiri | ADV9: 0 | ADW9: 0 | ADX9: 0 | ADY9: 0 | ADZ9: 1 | AEA9: 1 | AEB9: 0 | AEC9: 0 | AEE9: Laki-laki dewasa | AEG9: Menelepon atau WA langsung | AEI9: Tidak ada | AEJ9: Kadang-kadang | AEK9: Lebih mudah mendapatkan energi Pasokan energi yang andal Memasak lebih cepat Lebih aman Pengurangan waktu dan tenaga Peningkatan kebersihan kandang ternak Pemanfaatan bio-slurry sebagai pupuk Dapur lebih bersih dan bebas asap | AEL9: 0 | AEM9: 1 | AEN9: 1 | AEO9: 1 | AEP9: 1 | AEQ9: 1 | AER9: 1 | AES9: 1 | AET9: 1 | AEU9: 0 | AEV9: 0 | AEW9: 0 | AEY9: Mengurangi pengeluaran energi | AFA9: Yayasan Rumah Energi (YRE) | AFC9: WhatsApp Image 2026-02-03 at 14.16.48 (1)-22_58_50.jpeg | AFD9: https://kf.kobotoolbox.org/api/v2/assets/avstPQqLr3Ab3ZdcVTXZ6f/data/663839040/attachments/attKugCHwDTgZrMTayGkn7Hh/ | AFE9: WhatsApp Image 2026-02-03 at 14.16.48-22_59_9.jpeg | AFF9: https://kf.kobotoolbox.org/api/v2/assets/avstPQqLr3Ab3ZdcVTXZ6f/data/663839040/attachments/attb2fKMXnjBPsWkR8mJqUDQ/ | AFG9: manto/witono
A10: 46058 | B10: 46058 | C10: Marmanto | D10: Dinoyo | E10: 6285701460813 | G10: -7.3673861 | H10: 110.29551 | J10: 2.57 | M10: -7.36783 | N10: 110.29553 | P10: 3.92 | R10: Jawa Tengah | AC10: Klaten | AD10: Kemalang | AE10: Tlogowatu | AF10: KJUB PUSPETASARI | AG10: PUS0039 | AH10: 2 | AI10: VPA2 | AJ10: Aktif | AK10: 47 | AL10: Laki-laki | AM10: Sudah menikah | AN10: SMP/Sederajat | AO10: Petani | AP10: 1 | AQ10: 0 | AR10: 0 | AS10: 0 | AT10: 0 | AU10: 0 | AV10: 0 | AW10: 0 | AY10: Peternak | AZ10: 0 | BA10: 1 | BB10: 0 | BC10: 0 | BD10: 0 | BE10: 0 | BF10: 0 | BG10: 0 | BI10: Rp2.500.000 - Rp3.500.000 | BJ10: 1 | BK10: 1 | BL10: 2 | BM10: 0 | BN10: Milik sendiri | BO10: Permanen (dinding bata dan semen) | BP10: 1 | BQ10: 0 | BR10: 0 | BS10: 0 | BT10: 0 | BV10: Keramik/ubin | BW10: 0 | BX10: 0 | BY10: 1 | BZ10: 0 | CA10: 0 | CC10: Genting | CD10: 0 | CE10: 0 | CF10: 0 | CG10: 0 | CH10: 0 | CI10: 1 | CJ10: 0 | CL10: Ya | CM10: 2023 | CN10: Fixed-Dome (Kubah Tetap) | CO10: 6 m³ (4-5 ekor sapi, ±5 jam memasak/hari, ±50 kg | CP10: Anggota keluarga - laki-laki Anggota keluarga - perempuan dewasa | CQ10: 0 | CR10: 0 | CS10: 0 | CT10: 0 | CU10: 1 | CV10: 1 | CW10: 0 | CX10: 0 | CY10: Anggota keluarga - laki-laki Anggota keluarga - perempuan dewasa | CZ10: 1 | DA10: 1 | DB10: 0 | DD10: Anggota keluarga - laki-laki CPO atau pendamping | DE10: 1 | DF10: 0 | DG10: 1 | DH10: 0 | DJ10: Anggota keluarga - laki-laki CPO atau pendamping | DK10: 1 | DL10: 0 | DM10: 1 | DN10: 0 | DP10: 1 | DQ10: 1 | DR10: 0 | DV10: Ya | EI10: Tidak ada masalah | EJ10: 0 | EK10: 0 | EL10: 0 | EM10: 1 | EN10: 0 | EP10: Ya, cukup jelas dan mudah diikuti | EQ10: Pelatihan | ER10: CPO atau pendamping Staff BIRU | ES10: 1 | ET10: 1 | EU10: 0 | EV10: 0 | EX10: Anggota keluarga - Laki-laki Anggota keluarga - Perempuan dewasa | EY10: 1 | EZ10: 1 | FA10: 0 | FC10: Setiap hari | FE10: Mengetahui | FF10: Selalu (setiap hari) | FG10: Mengetahui | FH10: Sering (setiap minggu) | FI10: Mengetahui | FJ10: Sering (setiap minggu) | FK10: Mengetahui | FL10: Cukup sering (2 minggu sekali) | FM10: Mengetahui | FN10: Sering (setiap minggu) | FO10: Mengetahui | FP10: Cukup sering (2 minggu sekali) | FQ10: Mengetahui | FR10: Ya | FS10: Mengetahui | FT10: Ya, selalu | FU10: Laki-laki dewasa Perempuan dewasa | FV10: 1 | FW10: 1 | FX10: 0 | FY10: 0 | FZ10: Cukup memahami | GA10: CPO Pelatihan | GB10: 1 | GC10: 1 | GD10: 0 | GE10: 0 | GG10: Sering | GH10: Ya | GI10: Tetangga | GJ10: 1 | GK10: 0 | GL10: 0 | GM10: 0 | GO10: 8 | GP10: Penuh (100%) | GQ10: Kayu bakar LPG | GR10: 1 | GS10: 1 | GT10: 0 | GU10: 0 | GV10: 0 | GW10: 0 | GX10: 0 | GZ10: Ya | HA10: 150 | HB10: 150000 | HC10: 50 | HD10: 50000 | HE10: 12 | HF10: 100000 | HG10: 3 | HH10: 25000 | HY10: 100 | HZ10: 100000 | IA10: 9 | IB10: 75000 | IK10: 50-65 kg | IL10: 3-5 jam | IM10: Ya | IN10: Tidak | IO10: Lebih bersih | IQ10: Tidak pernah | IZ10: Tidak pernah | JI10: Tidak pernah | JR10: Tidak pernah | KA10: Tidak pernah | KJ10: Tidak pernah | KS10: Cukup membaik | KT10: 0-1 kali | KU10: 0-1 kali | KV10: Laki-laki dewasa Perempuan dewasa | KW10: 1 | KX10: 1 | KY10: 0 | KZ10: 0 | LA10: Cukup membaik | LB10: Cukup membaik | LC10: 3 | LD10: 3 | LE10: 0 | LF10: 0 | LG10: Ya | LH10: 150000 | LJ10: Kebutuhan rumah tangga | LK10: 0 | LL10: 0 | LM10: 0 | LN10: 0 | LO10: 1 | LP10: 0 | LQ10: 0 | LS10: 15 | LT10: 15 | LU10: 0 | LV10: 5 | LW10: 5 | LX10: 0 | LY10: 5 | LZ10: 5 | MA10: 0 | MB10: Ya | MC10: 30 | MD10: 15 | ME10: 30 | MF10: 15 | MG10: 0 | MH10: 0 | MI10: Istirahat | MJ10: 0 | MK10: 0 | ML10: 1 | MM10: 0 | MN10: 0 | MO10: 0 | MR10: untuk santai | MT10: kumpul keluarga | MU10: Ya, untuk anggota keluarga | MV10: Perawatan sistem biogas | MW10: 1 | MX10: 0 | MY10: 0 | MZ10: 0 | NL10: Tidak | NM10: Kombinasi dana mandiri dan dana hibah | NN10: >11.000.001 | NO10: Program yayasan/NGO | NV10: Anggota keluarga - Laki-laki dewasa | NX10: Sedikit meningkat | NY10: 30 | NZ10: 0 | OA10: 0 | OB10: 5 | OC10: 5 | OD10: 0 | OE10: Lebih baik | OF10: Lebih baik (beda waktu memasak 5-30 menit, ATAU tidak lagi ada rasa/bau makanan yang berubah, ATAU alasan lainnya) | OG10: Ya | OH10: 5 | OI10: 0 | OJ10: 0 | OK10: 0 | OL10: 0 | OM10: 0 | ON10: 0 | OO10: 0 | OP10: =VLOOKUP(AG10,'BUS 2'!$G$1:$CU$424,2,0) -> #N/A | OQ10: =VLOOKUP(AG10,'BUS 2'!$G$1:$CU$424,3,0) -> #N/A | OR10: =VLOOKUP(AG10,'BUS 2'!$G$1:$CU$424,4,0) -> #N/A | OS10: =VLOOKUP(AG10,'BUS 2'!$G$1:$CU$424,5,0) -> #N/A | OT10: =VLOOKUP(AG10,'BUS 2'!$G$1:$CU$424,6,0) -> #N/A | OU10: =VLOOKUP(AG10,'BUS 2'!$G$1:$CU$424,7,0) -> #N/A | OV10: =VLOOKUP(AG10,'BUS 2'!$G$1:$CU$424,8,0) -> #N/A | OW10: =VLOOKUP(AG10,'BUS 2'!$G$1:$CU$424,9,0) -> #N/A | OX10: =VLOOKUP(AG10,'BUS 2'!$G$1:$CU$424,10,0) -> #N/A | OY10: =VLOOKUP(AG10,'BUS 2'!$G$1:$CU$424,11,0) -> #N/A | OZ10: =VLOOKUP(AG10,'BUS 2'!$G$1:$CU$424,12,0) -> #N/A | PA10: =VLOOKUP(AG10,'BUS 2'!$G$1:$CU$424,13,0) -> #N/A | PB10: =VLOOKUP(AG10,'BUS 2'!$G$1:$CU$424,14,0) -> #N/A | PC10: =VLOOKUP(AG10,'BUS 2'!$G$1:$CU$424,15,0) -> #N/A | PD10: =VLOOKUP(AG10,'BUS 2'!$G$1:$CU$424,16,0) -> #N/A | PE10: =VLOOKUP(AG10,'BUS 2'!$G$1:$CU$424,17,0) -> #N/A | PF10: =VLOOKUP(AG10,'BUS 2'!$G$1:$CU$424,18,0) -> #N/A | PG10: =VLOOKUP(AG10,'BUS 2'!$G$1:$CU$424,19,0) -> #N/A | PH10: =VLOOKUP(AG10,'BUS 2'!$G$1:$CU$424,20,0) -> #N/A | PI10: =VLOOKUP(AG10,'BUS 2'!$G$1:$CU$424,21,0) -> #N/A | PJ10: =VLOOKUP(AG10,'BUS 2'!$G$1:$CU$424,22,0) -> #N/A | PK10: =VLOOKUP(AG10,'BUS 2'!$G$1:$CU$424,23,0) -> #N/A | PL10: =VLOOKUP(AG10,'BUS 2'!$G$1:$CU$424,24,0) -> #N/A | PM10: =VLOOKUP(AG10,'BUS 2'!$G$1:$CU$424,25,0) -> #N/A | PN10: =VLOOKUP(AG10,'BUS 2'!$G$1:$CU$424,26,0) -> #N/A | PO10: =VLOOKUP(AG10,'BUS 2'!$G$1:$CU$424,27,0) -> #N/A | PP10: =VLOOKUP(AG10,'BUS 2'!$G$1:$CU$424,28,0) -> #N/A | PQ10: =VLOOKUP(AG10,'BUS 2'!$G$1:$CU$424,29,0) -> #N/A | PR10: =VLOOKUP(AG10,'BUS 2'!$G$1:$CU$424,30,0) -> #N/A | PS10: =VLOOKUP(AG10,'BUS 2'!$G$1:$CU$424,31,0) -> #N/A | PT10: 1-Disebarkan ke lahan terbuka | PU10: 1 | PV10: 0 | PW10: 0 | PX10: 0 | PY10: 0 | PZ10: 0 | QA10: 1 | QB10: 0 | QC10: 0 | QD10: 0 | SY10: =VLOOKUP(AG10,'BUS 2'!$G$1:$CU$424,33,0) -> #N/A | SZ10: =VLOOKUP(AG10,'BUS 2'!$G$1:$CU$424,34,0) -> #N/A | TA10: =VLOOKUP(AG10,'BUS 2'!$G$1:$CU$424,35,0) -> #N/A | TB10: =VLOOKUP(AG10,'BUS 2'!$G$1:$CU$424,36,0) -> #N/A | TC10: =VLOOKUP(AG10,'BUS 2'!$G$1:$CU$424,37,0) -> #N/A | TD10: =VLOOKUP(AG10,'BUS 2'!$G$1:$CU$424,38,0) -> #N/A | TE10: =VLOOKUP(AG10,'BUS 2'!$G$1:$CU$424,39,0) -> #N/A | TF10: =VLOOKUP(AG10,'BUS 2'!$G$1:$CU$424,40,0) -> #N/A | TG10: =VLOOKUP(AG10,'BUS 2'!$G$1:$CU$424,42,0) -> #N/A | TH10: =VLOOKUP(AG10,'BUS 2'!$G$1:$CU$424,43,0) -> #N/A | TI10: =VLOOKUP(AG10,'BUS 2'!$G$1:$CU$424,44,0) -> #N/A | TJ10: =VLOOKUP(AG10,'BUS 2'!$G$1:$CU$424,45,0) -> #N/A | TK10: =VLOOKUP(AG10,'BUS 2'!$G$1:$CU$424,46,0) -> #N/A | TL10: =VLOOKUP(AG10,'BUS 2'!$G$1:$CU$424,47,0) -> #N/A | TM10: =VLOOKUP(AG10,'BUS 2'!$G$1:$CU$424,48,0) -> #N/A | TN10: =VLOOKUP(AG10,'BUS 2'!$G$1:$CU$424,49,0) -> #N/A | TO10: =VLOOKUP(AG10,'BUS 2'!$G$1:$CU$424,50,0) -> #N/A | TP10: =VLOOKUP(AG10,'BUS 2'!$G$1:$CU$424,51,0) -> #N/A | TQ10: =VLOOKUP(AG10,'BUS 2'!$G$1:$CU$424,52,0) -> #N/A | TR10: =VLOOKUP(AG10,'BUS 2'!$G$1:$CU$424,53,0) -> #N/A | TS10: =VLOOKUP(AG10,'BUS 2'!$G$1:$CU$424,54,0) -> #N/A | TT10: =VLOOKUP(AG10,'BUS 2'!$G$1:$CU$424,55,0) -> #N/A | TU10: =VLOOKUP(AG10,'BUS 2'!$G$1:$CU$424,56,0) -> #N/A | TV10: =VLOOKUP(AG10,'BUS 2'!$G$1:$CU$424,57,0) -> #N/A | TW10: =VLOOKUP(AG10,'BUS 2'!$G$1:$CU$424,58,0) -> #N/A | TX10: =VLOOKUP(AG10,'BUS 2'!$G$1:$CU$424,59,0) -> #N/A | TY10: =VLOOKUP(AG10,'BUS 2'!$G$1:$CU$424,60,0) -> #N/A | TZ10: =VLOOKUP(AG10,'BUS 2'!$G$1:$CU$424,61,0) -> #N/A | UA10: =VLOOKUP(AG10,'BUS 2'!$G$1:$CU$424,62,0) -> #N/A | UB10: =VLOOKUP(AG10,'BUS 2'!$G$1:$CU$424,63,0) -> #N/A | UC10: =VLOOKUP(AG10,'BUS 2'!$G$1:$CU$424,64,0) -> #N/A | UD10: =VLOOKUP(AG10,'BUS 2'!$G$1:$CU$424,65,0) -> #N/A | UE10: =VLOOKUP(AG10,'BUS 2'!$G$1:$CU$424,66,0) -> #N/A | UF10: =VLOOKUP(AG10,'BUS 2'!$G$1:$CU$424,67,0) -> #N/A | UG10: =VLOOKUP(AG10,'BUS 2'!$G$1:$CU$424,68,0) -> #N/A | UH10: =VLOOKUP(AG10,'BUS 2'!$G$1:$CU$424,69,0) -> #N/A | UI10: =VLOOKUP(AG10,'BUS 2'!$G$1:$CU$424,70,0) -> #N/A | UJ10: =VLOOKUP(AG10,'BUS 2'!$G$1:$CU$424,71,0) -> #N/A | UK10: =VLOOKUP(AG10,'BUS 2'!$G$1:$CU$424,72,0) -> #N/A | UL10: =VLOOKUP(AG10,'BUS 2'!$G$1:$CU$424,73,0) -> #N/A | UM10: =VLOOKUP(AG10,'BUS 2'!$G$1:$CU$424,74,0) -> #N/A | UN10: =VLOOKUP(AG10,'BUS 2'!$G$1:$CU$424,75,0) -> #N/A | UO10: =VLOOKUP(AG10,'BUS 2'!$G$1:$CU$424,76,0) -> #N/A | UP10: =VLOOKUP(AG10,'BUS 2'!$G$1:$CU$424,77,0) -> #N/A | UQ10: =VLOOKUP(AG10,'BUS 2'!$G$1:$CU$424,78,0) -> #N/A | UR10: =VLOOKUP(AG10,'BUS 2'!$G$1:$CU$424,79,0) -> #N/A | US10: =VLOOKUP(AG10,'BUS 2'!$G$1:$CU$424,80,0) -> #N/A | UT10: =VLOOKUP(AG10,'BUS 2'!$G$1:$CU$424,81,0) -> #N/A | UU10: Pemberian pakan di kandang | VC10: Sangat teratur (setiap hari) | VK10: Sering (1 kali sehari) | VS10: 3-Disimpan terbuka (dry lot) 4-Disimpan dalam kotak bersekat | VT10: 0 | VU10: 0 | VV10: 0 | VW10: 0 | VX10: 0 | VY10: 0 | VZ10: 1 | WA10: 1 | WB10: 0 | WC10: 0 | WD10: 0 | WE10: 0 | ZV10: 2 | AAD10: Pakan kering (misal: konsentrat, silase, pelet) | AAL10: Ya | AAM10: Padat Cair | AAN10: 1 | AAO10: 1 | AAP10: 200 | AAQ10: 200 | AAR10: Ya | AAS10: Mengetahui | AAT10: Digunakan untuk pupuk di lahan pertanian sendiri Dibuang ke lahan sekitar kandang - yg ditanami tanaman Diberikan gratis ke orang lain | AAU10: 1 | AAV10: 0 | AAW10: 0 | AAX10: 1 | AAY10: 1 | AAZ10: 0 | ABA10: 0 | ABB10: Pupuk cair untuk tanaman | ABC10: 1 | ABD10: 0 | ABE10: 0 | ABF10: 0 | ABG10: 0 | ABQ10: Rumput | ABR10: Sering ( 1 minggu 2 kali) | ABS10: 2000 | ABT10: 1500 | ABU10: 250 | ABV10: 250 | ABW10: NPK | ABY10: 15 | ABZ10: 5000 | ACA10: 10 | ACB10: 5000 | ACC10: 400 | ACD10: 600 | ACE10: Ya | ACF10: Cukup meningkat | ACG10: Cukup meningkat | ACH10: Cukup meningkat | ACK10: Tidak punya waktu mengumpulkannya Ladang/sawah terlalu jauh, sulit untuk mengangkut ke sana | ACL10: 0 | ACM10: 0 | ACN10: 1 | ACO10: 1 | ACP10: 0 | ACQ10: 0 | ACR10: 0 | ACT10: tidak | ACU10: Manfaat cukup signifikan, terasa di kehidupan sehari-hari | ACV10: Berkurang | ACW10: Anggota keluarga - Perempuan dewasa | ACX10: Setuju | ACY10: Anggota keluarga - Laki-laki dewasa Anggota keluarga - Perempuan dewasa Anggota keluarga - Anak-anak | ACZ10: 1 | ADA10: 1 | ADB10: 1 | ADC10: 0 | ADD10: Cukup puas | ADE10: Cukup puas | ADF10: Cukup puas | ADG10: Cukup puas | ADH10: Tidak | ADJ10: Puas | ADU10: Menghubungi CPO atau pendamping Memperbaiki sendiri | ADV10: 0 | ADW10: 0 | ADX10: 0 | ADY10: 0 | ADZ10: 1 | AEA10: 1 | AEB10: 0 | AEC10: 0 | AEE10: Laki-laki dewasa | AEG10: Menelepon atau WA langsung | AEI10: Tidak ada | AEJ10: Kadang-kadang | AEK10: Pengurangan pengeluaran rumah tangga (bahan bakar minyak, pupuk, dll.) Lebih mudah mendapatkan energi Pasokan energi yang andal Memasak lebih cepat Lebih aman Pengurangan waktu dan tenaga Peningkatan kebersihan kandang ternak Pemanfaatan bio-slurry sebagai pupuk | AEL10: 1 | AEM10: 1 | AEN10: 1 | AEO10: 1 | AEP10: 1 | AEQ10: 1 | AER10: 1 | AES10: 1 | AET10: 0 | AEU10: 0 | AEV10: 0 | AEW10: 0 | AEY10: Mengurangi pengeluaran energi | AFA10: Koperasi | AFC10: WhatsApp Image 2026-02-03 at 14.17.57-11_26_33.jpeg | AFD10: https://kf.kobotoolbox.org/api/v2/assets/avstPQqLr3Ab3ZdcVTXZ6f/data/664110988/attachments/attG6zMJyNjggZFEUoF2m44U/ | AFE10: WhatsApp Image 2026-02-03 at 14.17.58-11_26_50.jpeg | AFF10: https://kf.kobotoolbox.org/api/v2/assets/avstPQqLr3Ab3ZdcVTXZ6f/data/664110988/attachments/attyZDscvqHBpWZeb6shDZyX/ | AFG10: manto / witono
